Workbook

Sheet README
A1: Northlight Software: driver-based planning model
A2: Assumption set v1.3. Generated by run_model.py; every number in this file comes from the model outputs.
A4: How to read this workbook
A5: 1. Assumptions: every driver, its value in each scenario, and whether it is anchored on a published benchmark, derived from a published rate table, or a judgment call.
A6: 2. Change log: what changed since the FY2026 budget was locked (v1.0), when, by whom and why. Snapshot + log = current values.
A7: 3. Actuals P&L and Budget FY2026: monthly detail. Yellow cells are values from the model; blue cells are Excel formulas you can click into.
A8: 4. Bridge YTD: January to August 2026 actual versus budget, by driver component. Impact is the effect on EBITDA, favorable positive. The components sum to the EBITDA variance.
A9: 5. The three scenario sheets hold the recommended option: P&L, ARR roll-forward, cloud and cash, with subtotals and the cash roll-forward as formulas.
A10: 6. Workforce: FTE and people cost per month by function and location for the recommended option, base scenario.
A11: 7. Checks: every formula subtotal recomputed against the model value. All differences must be zero.
A13: Conventions
A14: Revenue = closing ARR / 12. Net revenue retention is all-in (includes the January price increase). Cloud cost = min(units, commitment) x price x (1 - discount) + overage x price + fixed.
... A19: Guardrails: downside runway at least 18 months in every month; base gross margin at least 74% in every month.

Sheet Assumptions
A1: One row per driver. source_type: benchmark = published survey figure (named), derived = computed from a published rate table, judgment = own call.
A3: id | B3: category | C3: name | D3: unit | E3: base | F3: upside | G3: downside | H3: source_type | I3: source
A4: logos_per_ramped_ae_month | B4: revenue | C4: New customers won per fully ramped account executive per month | D4: logos/AE/month | E4: 0.9 | F4: 1.1 | G4: 0.5 | H4: judgment | I4: Base set at the trailing 2026 actual (0.92). Downside is a 45% productivity shortfall (pipeline does not rebuild). No external source.
A5: initial_acv_usd | B5: revenue | C5: Annual contract value of a new Platform customer | D5: USD/year | E5: 38000 | F5: 38000 | G5: 38000 | H5: judgment | I5: Chosen inside the USD 25k-50k ACV band so retention benchmarks for that band apply (SaaS Capital, Research Brief 32, 2025).
A6: nrr_annual | B6: revenue | C6: Net revenue retention (annual all-in including the January price increase) on the Platform base | D6: ratio | E6: 1.05 | F6: 1.1 | G6: 0.96 | H6: benchmark | I6: SaaS Capital, 2025 B2B SaaS Retention Benchmarks (Research Brief 32, 1,000+ companies): median NRR 102% for USD 25k-50k ACV, 104% for USD 50k-100k, 101% overall. Base 105% sits at the top of that median range; downside 96% sits just below the 25th percentile for USD 25k-50k ACV (97%).
A7: grr_annual | B7: revenue | C7: Gross revenue retention (annual) | D7: ratio | E7: 0.9 | F7: 0.92 | G7: 0.86 | H7: benchmark | I7: SaaS Capital, 2025 B2B SaaS Retention Benchmarks: median GRR 91% for USD 25k-50k ACV, 90% overall. Downside 86% is a judgment call below the median.
A8: price_increase_pct_jan | B8: revenue | C8: Price increase applied to existing Platform ARR every January | D8: ratio | E8: 0.05 | F8: 0.07 | G8: 0.03 | H8: judgment | I8: Company pricing policy assumption. No external source.
A9: attach_gain_pts_month | B9: revenue | C9: Monthly gain in the Insights add-on attach rate | D9: percentage points/month | E9: 0.6 | F9: 0.9 | G9: 0.2 | H9: judgment | I9: Product roadmap assumption. No external source.
A10: attach_rate_cap | B10: revenue | C10: Ceiling on the Insights attach rate | D10: ratio | E10: 0.45 | F10: 0.45 | G10: 0.45 | H10: judgment | I10: Product assumption. No external source.
A11: insights_usage_growth_month | B11: revenue | C11: Monthly growth in Insights revenue per customer from usage | D11: ratio/month | E11: 0.01 | F11: 0.015 | G11: 0.005 | H11: judgment | I11: Usage-based pricing assumption. No external source.
A12: ae_ramp_months | B12: revenue | C12: Months for a new account executive to reach full productivity | D12: months | E12: 4 | F12: 4 | G12: 4 | H12: judgment | I12: Common sales-planning convention. No external source.
A13: csm_ramp_months | B13: cost_of_revenue | C13: Months for a new customer success manager to carry a full book | D13: months | E13: 2 | F13: 2 | G13: 2 | H13: judgment | I13: Planning convention. No external source.
A14: customers_per_csm | B14: cost_of_revenue | C14: Customers carried per fully ramped customer success manager | D14: customers/CSM | E14: 45 | F14: 45 | G14: 45 | H14: judgment | I14: Coverage-ratio assumption for a mid-market book. No external source.
A15: cloud_units_per_platform_customer | B15: cost_of_revenue | C15: Compute units consumed per Platform customer per month | D15: units/customer/month | E15: 200 | F15: 200 | G15: 200 | H15: judgment | I15: Internal usage metric. No external source.
... A42: materiality_abs_override_usd | B42: materiality | C42: Bridge component is material above this absolute impact regardless of percentage | D42: USD | E42: 100000 | F42: 100000 | G42: 100000 | H42: judgment | I42: Reporting policy. No external source.

Sheet Change log
A1: Every change to assumptions.csv since v1.0. Replaying this log onto the v1.0 snapshot reproduces the current file (tested).
A3: version | B3: date | C3: assumption_id | D3: scenario | E3: old_value | F3: new_value | G3: changed_by | H3: reason
A4: 1.1 | B4: 2026-04-14 | C4: nrr_annual | D4: base | E4: 1.06 | F4: 1.05 | G4: Alan Vourc'h (FP&A) | H4: Q1 2026 churn review: SMB logo churn ran above budget for three consecutive months; net retention re-based to the trailing actual
A5: 1.1 | B5: 2026-04-14 | C5: logos_per_ramped_ae_month | D5: base | E5: 1.10 | F5: 0.90 | G5: Alan Vourc'h (FP&A) | H5: Q1 2026 new logos per ramped account executive ran at 0.92 against a budget of 1.10; base reset to the trailing actual (0.90)
A6: 1.2 | B6: 2026-07-08 | C6: cloud_units_per_insights_customer | D6: all | E6: 1500 | F6: 2000 | G6: Alan Vourc'h (FP&A) | H6: Insights customers' data volumes stepped up about 30% from March 2026; unit consumption re-based on April to June actuals
A7: 1.2 | B7: 2026-07-08 | C7: marketing_program_cost_per_new_logo | D7: base | E7: 28000 | F7: 30000 | G7: Alan Vourc'h (FP&A) | H7: H1 2026 programme spend per new logo ran at 30.7k including the May conference; base re-based
A8: 1.3 | B8: 2026-09-10 | C8: min_runway_months_downside | D8: all | E8: 12 | F8: 18 | G8: Alan Vourc'h (FP&A) | H8: Board asked for 18 months of downside runway after the March 2026 Series C extension (USD 25M)
A9: 1.3 | B9: 2026-09-10 | C9: cloud_unit_price_usd | D9: downside | E9: 0.44 | F9: 0.46 | G9: Alan Vourc'h (FP&A) | H9: Provider announced a list-price change on the instance family used for Insights workloads; the downside now carries it

Sheet Locations
A1: location | B1: employer_tax_rate | C1: benefits_rate | D1: rent_per_head_month_usd | E1: source_type | F1: source
A2: Montreal | B2: 0.11 | C2: 0.06 | D2: 450 | E2: derived | F2: Employer tax rate derived from Raymond Chabot Grant Thornton Tax News 930R4 (February 2026): QPP employer 6.30% on earnings from CAD 3,500 to 74,600 plus 4.00% on 74,600 to 85,000; QPIP employer 0.602% to CAD 103,000; EI employer (Quebec) 1.82% to CAD 68,900; Health Services Fund 4.26% for total payroll of CAD 7.8M or more. At a CAD 110k salary these total about 10.8%; CNESST (industry-rated) approximated at 0.4%. Benefits and rent are judgment calls.
A3: Paris | B3: 0.42 | C3: 0.05 | D3: 600 | E3: derived | F3: PwC Worldwide Tax Summaries, France, Other taxes: employer share of social contributions is about 45% of gross salary on average, declining as salary rises above the ceilings. 42% used for cadre-level technology salaries: own judgment. Benefits (mutuelle, meal vouchers) and rent are judgment calls.
A4: Austin | B4: 0.085 | C4: 0.14 | D4: 500 | E4: derived | F4: IRS Tax Topic 751 (2026): employer Social Security 6.2% up to the USD 184,500 wage base and Medicare 1.45% uncapped. FUTA and Texas SUTA approximated at 0.85%: own judgment. Benefits rate (health insurance heavy) and rent are judgment calls.

Sheet Salary table
A1: Annual salary in USD by role and location; sales_role = commission plan, no bonus accrual.
A3: role | B3: function | C3: cost_bucket | D3: sales_role | E3: Montreal | F3: Paris | G3: Austin
A4: Software Engineer | B4: R&D | C4: R&D | D4: FALSE | E4: 95000 | F4: 80000 | G4: 135000
A5: Senior Software Engineer | B5: R&D | C5: R&D | D5: FALSE | E5: 125000 | F5: 105000 | G5: 175000
A6: Engineering Manager | B6: R&D | C6: R&D | D6: FALSE | E6: 150000 | F6: 130000 | G6: 200000
A7: Product Manager | B7: R&D | C7: R&D | D7: FALSE | E7: 120000 | F7: 100000 | G7: 160000
A8: Product Designer | B8: R&D | C8: R&D | D8: FALSE | E8: 100000 | F8: 85000 | G8: 140000
A9: Data Engineer | B9: R&D | C9: R&D | D9: FALSE | E9: 115000 | F9: 95000 | G9: 155000
A10: Site Reliability Engineer | B10: Customer Operations | C10: COGS | D10: FALSE | E10: 120000 | F10: 105000 | G10: 165000
A11: Customer Success Manager | B11: Customer Operations | C11: COGS | D11: FALSE | E11: 75000 | F11: 65000 | G11: 90000
A12: Support Engineer | B12: Customer Operations | C12: COGS | D12: FALSE | E12: 65000 | F12: 55000 | G12: 75000
A13: Account Executive | B13: S&M | C13: S&M | D13: TRUE | E13: 90000 | F13: 80000 | G13: 110000
A14: Sales Development Rep | B14: S&M | C14: S&M | D14: TRUE | E14: 55000 | F14: 48000 | G14: 65000
A15: Marketing Manager | B15: S&M | C15: S&M | D15: FALSE | E15: 95000 | F15: 80000 | G15: 120000
... A18: Executive | B18: G&A | C18: G&A | D18: FALSE | E18: 240000 | F18: 220000 | G18: 280000

Sheet Hiring plans
A1: phased and front_loaded are the candidate plans; fy2026_budget is the plan inside the FY2026 budget.
A3: plan_id | B3: role | C3: location | D3: start_month | E3: count | F3: rationale
A4: phased | B4: Senior Software Engineer | C4: Montreal | D4: 2026-10 | E4: 2 | F4: Platform reliability squad
A5: phased | B5: Software Engineer | C5: Montreal | D5: 2026-11 | E5: 2 | F5: Platform reliability squad
A6: phased | B6: Software Engineer | C6: Paris | D6: 2026-11 | E6: 2 | F6: Insights data pipeline squad
A7: phased | B7: Data Engineer | C7: Paris | D7: 2027-01 | E7: 2 | F7: Insights data pipeline squad
A8: phased | B8: Senior Software Engineer | C8: Paris | D8: 2027-02 | E8: 1 | F8: Insights data pipeline squad lead
A9: phased | B9: Software Engineer | C9: Montreal | D9: 2027-03 | E9: 2 | F9: Integrations squad
A10: phased | B10: Product Manager | C10: Montreal | D10: 2027-01 | E10: 1 | F10: Insights product owner
A11: phased | B11: Software Engineer | C11: Paris | D11: 2027-05 | E11: 2 | F11: Integrations squad
A12: phased | B12: Account Executive | C12: Austin | D12: 2026-10 | E12: 1 | F12: Mid-market pod
A13: phased | B13: Account Executive | C13: Austin | D13: 2027-01 | E13: 2 | F13: Mid-market pod
A14: phased | B14: Account Executive | C14: Austin | D14: 2027-04 | E14: 1 | F14: Mid-market pod
A15: phased | B15: Sales Development Rep | C15: Austin | D15: 2027-01 | E15: 2 | F15: Pipeline coverage for new AEs
... A42: fy2026_budget | B42: Finance & Operations | C42: Montreal | D42: 2026-02 | E42: 1 | F42: FY2026 budget: billing operations

Sheet Options
A1: One row per option: guardrail results and headline outcomes. Feasible = both guardrails hold.
A3: option_id | B3: label | C3: downside_runway_min | D3: runway_ok | E3: base_gm_min | F3: gm_ok | G3: feasible | H3: base_arr_end | I3: base_cum_burn | J3: upside_arr_end | K3: downside_arr_end | L3: downside_cash_min
A4: hold_ondemand | B4: Hold hiring; cloud on demand | C4: 43.748582 | D4: TRUE | E4: 0.72860101 | F4: FALSE | G4: FALSE | H4: 38325017 | I4: 4149447.6 | J4: 44853935 | K4: 28548915 | L4: 17045571
A5: hold_commit | B5: Hold hiring; one-year cloud commitment | C5: 47.807616 | D5: TRUE | E5: 0.74839602 | F5: TRUE | G5: TRUE | H5: 38325017 | I5: 3339990.7 | J5: 44853935 | K5: 28548915 | L5: 17805272
A6: phased_ondemand | B6: Phased plan; cloud on demand | C6: 20.648966 | D6: TRUE | E6: 0.72860101 | F6: FALSE | G6: FALSE | H6: 40498712 | I6: 8619868.1 | J6: 47700306 | K6: 29686367 | L6: 12686738
A7: phased_commit | B7: Phased plan; one-year cloud commitment | C7: 23.282208 | D7: TRUE | E7: 0.74839602 | F7: TRUE | G7: TRUE | H7: 40498712 | I7: 7810224.1 | J7: 47700306 | K7: 29686367 | L7: 13466842
A8: front_ondemand | B8: Front-loaded plan with Insights contractors; cloud on demand | C8: 14.662368 | D8: FALSE | E8: 0.72860101 | F8: FALSE | G8: FALSE | H8: 42210227 | I8: 11446438 | J8: 49826907 | K8: 30601464 | L8: 9891945.8
A9: front_commit | B9: Front-loaded plan with Insights contractors; one-year cloud commitment | C9: 16.895252 | D9: FALSE | E9: 0.74839602 | F9: TRUE | G9: FALSE | H9: 42210227 | I9: 10636616 | J9: 49826907 | K9: 30601464 | L9: 10685919

Sheet Option grid
A1: Every option under every scenario: 18 runs of the same engine.
A3: option_id | B3: scenario | C3: arr_end | D3: arr_growth | E3: revenue_18m | F3: gross_profit_18m | G3: ebitda_18m | H3: cum_burn | I3: cash_end | J3: cash_min | K3: runway_min | L3: gm_min | M3: gm_avg | N3: fte_end | O3: rd_fte_end | P3: cloud_18m | Q3: stranded_cost_18m | R3: plan_hires | S3: plan_hire_cost_18m
A4: hold_ondemand | B4: base | C4: 38325017 | D4: 0.58027777 | E4: 46835089 | F4: 35361605 | G4: -4970369.1 | H4: 4149447.6 | I4: 20600832 | J4: 20074090 | K4: 36.414583 | L4: 0.72860101 | M4: 0.75502375 | N4: 139.16 | O4: 70.56 | P4: 4225935.9 | Q4: 0 | R4: 0 | S4: 0
A5: hold_ondemand | B5: upside | C5: 44853935 | D5: 0.84948846 | E5: 51311657 | F5: 39068261 | G5: -2519727 | H5: 1324951.9 | I5: 23425327 | J5: 21087638 | K5: 34.22913 | L5: 0.72940885 | M5: 0.76139153 | N5: 141.12 | O5: 70.56 | P5: 4689592.7 | Q5: 0 | R5: 2 | S5: 106396.7
A6: hold_ondemand | B6: downside | C6: 28548915 | D6: 0.17717407 | E6: 39610106 | F6: 29144874 | G6: -7955357.6 | H6: 7704708.7 | I6: 17045571 | J6: 17045571 | K6: 43.748582 | L6: 0.72652001 | M6: 0.7357939 | N6: 139.16 | O6: 70.56 | P6: 3542807 | Q6: 0 | R6: 0 | S6: 0
A7: hold_commit | B7: base | C7: 38325017 | D7: 0.58027777 | E7: 46835089 | F7: 36171062 | G7: -4160912.3 | H7: 3339990.7 | I7: 21410288 | J7: 20715215 | K7: 38.886526 | L7: 0.74839602 | M7: 0.77230687 | N7: 139.16 | O7: 70.56 | P7: 3416479 | Q7: 42596.581 | R7: 0 | S7: 0
A8: hold_commit | B8: upside | C8: 44853935 | D8: 0.84948846 | E8: 51311657 | F8: 39875437 | G8: -1712550.8 | H8: 517775.74 | I8: 24232503 | J8: 21537632 | K8: 36.446065 | L8: 0.7493189 | M8: 0.77712238 | N8: 141.12 | O8: 70.56 | P8: 3882416.5 | Q8: 26182.643 | R8: 2 | S8: 106396.7
A9: hold_commit | B9: downside | C9: 28548915 | D9: 0.17717407 | E9: 39610106 | F9: 29904576 | G9: -7195655.9 | H9: 6945006.9 | I9: 17805272 | J9: 17805272 | K9: 47.807616 | L9: 0.7461893 | M9: 0.75497339 | N9: 139.16 | O9: 70.56 | P9: 2783105.2 | Q9: 239171.21 | R9: 0 | S9: 0
A10: phased_ondemand | B10: base | C10: 40498712 | D10: 0.66990701 | E10: 47952580 | F10: 36238414 | G10: -9487088.5 | H10: 8619868.1 | I10: 16130411 | J10: 16080649 | K10: 29.79418 | L10: 0.72860101 | M10: 0.75571354 | N10: 161.7 | O10: 84.28 | P10: 4373229.9 | Q10: 0 | R10: 23 | S10: 3798557.3
A11: phased_ondemand | B11: upside | C11: 47700306 | D11: 0.96685452 | E11: 52744032 | F11: 40172457 | G11: -7029722.3 | H11: 5749408.9 | I11: 19000870 | J11: 18079217 | K11: 30.369355 | L11: 0.72940885 | M11: 0.76164933 | N11: 163.66 | O11: 84.28 | P11: 4871648.3 | Q11: 0 | R11: 25 | S11: 3944308
A12: phased_ondemand | B12: downside | C12: 29686367 | D12: 0.22407528 | E12: 40211019 | F12: 29627033 | G12: -12303541 | H12: 12063541 | I12: 12686738 | J12: 12686738 | K12: 20.648966 | L12: 0.72652001 | M12: 0.73678892 | N12: 160.72 | O12: 84.28 | P12: 3634520.2 | Q12: 0 | R12: 22 | S12: 3754853.1
A13: phased_commit | B13: base | C13: 40498712 | D13: 0.66990701 | E13: 47952580 | F13: 37048058 | G13: -8677444.5 | H13: 7810224.1 | I13: 16940055 | J13: 16800235 | K13: 32.678794 | L13: 0.74839602 | M13: 0.7725978 | N13: 161.7 | O13: 84.28 | P13: 3563585.9 | Q13: 42035.169 | R13: 23 | S13: 3798557.3
A14: phased_commit | B14: upside | C14: 47700306 | D14: 0.96685452 | E14: 52744032 | F14: 40979655 | G14: -6222524.2 | H14: 4942210.8 | I14: 19808068 | J14: 18721575 | K14: 32.650663 | L14: 0.7493189 | M14: 0.7769534 | N14: 163.66 | O14: 84.28 | P14: 4064450.2 | Q14: 26116.984 | R14: 25 | S14: 3944308
A15: phased_commit | B15: downside | C15: 29686367 | D15: 0.22407528 | E15: 40211019 | F15: 30407137 | G15: -11523437 | H15: 11283437 | I15: 13466842 | J15: 13466842 | K15: 23.282208 | L15: 0.7461893 | M15: 0.75618917 | N15: 160.72 | O15: 84.28 | P15: 2854416.1 | Q15: 177964.32 | R15: 22 | S15: 3754853.1
... A21: front_commit | B21: downside | C21: 30601464 | D21: 0.26180799 | E21: 40814965 | F21: 30873851 | G21: -14333241 | H21: 14064361 | I21: 10685919 | J21: 10685919 | K21: 16.895252 | L21: 0.7461893 | M21: 0.75643459 | N21: 167.58 | O21: 88.2 | P21: 2964470.1 | Q21: 136357.88 | R21: 29 | S21: 5591751.1

Sheet Actuals
A1: Actuals: P&L
A2: USD, monthly | B2: 2024-09 | C2: 2024-10 | D2: 2024-11 | E2: 2024-12 | F2: 2025-01 | G2: 2025-02 | H2: 2025-03 | I2: 2025-04 | J2: 2025-05 | K2: 2025-06 | L2: 2025-07 | M2: 2025-08 | N2: 2025-09 | O2: 2025-10 | P2: 2025-11 | Q2: 2025-12 | R2: 2026-01 | S2: 2026-02 | T2: 2026-03 | U2: 2026-04 | V2: 2026-05 | W2: 2026-06 | X2: 2026-07 | Y2: 2026-08
A3: Platform revenue | B3: 981087.54 | C3: 1005101.4 | D3: 1028451.5 | E3: 1058221.6 | F3: 1132259.3 | G3: 1156928.7 | H3: 1188773 | I3: 1213418.3 | J3: 1244815.3 | K3: 1279344.2 | L3: 1311167.6 | M3: 1338204.8 | N3: 1377821.6 | O3: 1413919.5 | P3: 1454201.3 | Q3: 1499311.7 | R3: 1612141.7 | S3: 1642915.6 | T3: 1679561.8 | U3: 1713674.2 | V3: 1753549.6 | W3: 1790911.9 | X3: 1820439.9 | Y3: 1855089.4
A4: Insights revenue | B4: 46887.791 | C4: 50241.447 | D4: 53663.045 | E4: 57489.502 | F4: 60996.656 | G4: 64792.621 | H4: 69049.882 | I4: 73098.061 | J4: 77648.099 | K4: 82525.814 | L4: 87370.617 | M4: 92158.861 | N4: 97963.036 | O4: 103731.41 | P4: 109933.91 | Q4: 116837.67 | R4: 121566.29 | S4: 127024.79 | T4: 133055.28 | U4: 139082.3 | V4: 145879.91 | W4: 152547.34 | X4: 158978.88 | Y4: 165916.92
A5: Revenue | B5: =B3+B4 | C5: =C3+C4 | D5: =D3+D4 | E5: =E3+E4 | F5: =F3+F4 | G5: =G3+G4 | H5: =H3+H4 | I5: =I3+I4 | ... Y5: =Y3+Y4
A6: Cloud hosting | B6: 88894.382 | C6: 93872.642 | D6: 95173.662 | E6: 96609.632 | F6: 100661.17 | G6: 102072.86 | H6: 103677.1 | I6: 108090.19 | J6: 109691.41 | K6: 111802.67 | L6: 115169.34 | M6: 116982 | N6: 123894.71 | O6: 125658.23 | P6: 125937.75 | Q6: 131699.79 | R6: 139519.28 | S6: 140607.98 | T6: 166479.2 | U6: 168149.6 | V6: 175878.46 | W6: 179584.58 | X6: 179693.64 | Y6: 188164.5
A7: Third-party software and data | B7: 30839.26 | C7: 31660.286 | D7: 32463.436 | E7: 33471.332 | F7: 35797.68 | G7: 36651.641 | H7: 37734.687 | I7: 38595.492 | J7: 39673.901 | K7: 40856.099 | L7: 41956.147 | M7: 42910.911 | N7: 44273.54 | O7: 45529.528 | P7: 46924.055 | Q7: 48484.481 | R7: 52011.239 | S7: 53098.213 | T7: 54378.511 | U7: 55582.696 | V7: 56982.884 | W7: 58303.776 | X7: 59382.564 | Y7: 60630.191
A8: Payment processing | B8: 15419.63 | C8: 15830.143 | D8: 16231.718 | E8: 16735.666 | F8: 17898.84 | G8: 18325.82 | H8: 18867.344 | I8: 19297.746 | J8: 19836.951 | K8: 20428.05 | L8: 20978.073 | M8: 21455.455 | N8: 22136.77 | O8: 22764.764 | P8: 23462.027 | Q8: 24242.24 | R8: 26005.62 | S8: 26549.106 | T8: 27189.255 | U8: 27791.348 | V8: 28491.442 | W8: 29151.888 | X8: 29691.282 | Y8: 30315.095
A9: Customer operations payroll | B9: 222370.56 | C9: 222370.56 | D9: 222370.56 | E9: 222370.56 | F9: 240095.71 | G9: 240095.71 | H9: 240095.71 | I9: 246775.54 | J9: 246775.54 | K9: 248489.18 | L9: 237684.54 | M9: 244781.41 | N9: 244781.41 | O9: 252735.9 | P9: 265489.5 | Q9: 265489.5 | R9: 274781.63 | S9: 274781.63 | T9: 283037.15 | U9: 283037.15 | V9: 283037.15 | W9: 282552.53 | X9: 282552.53 | Y9: 282552.53
A10: Customer operations recruiting | B10: 0 | C10: 0 | D10: 0 | E10: 0 | F10: 13642.261 | G10: 0 | H10: 0 | I10: 9551.7058 | J10: 0 | K10: 13381.939 | L10: 0 | M10: 10148.053 | N10: 0 | O10: 11374.386 | P10: 18236.795 | Q10: 0 | R10: 0 | S10: 0 | T10: 26770.03 | U10: 0 | V10: 0 | W10: 13524.443 | X10: 0 | Y10: 0
A11: Cost of revenue | B11: =B6+B7+B8+B9+B10 | C11: =C6+C7+C8+C9+C10 | D11: =D6+D7+D8+D9+D10 | E11: =E6+E7+E8+E9+E10 | F11: =F6+F7+F8+F9+F10 | G11: =G6+G7+G8+G9+G10 | H11: =H6+H7+H8+H9+H10 | I11: =I6+I7+I8+I9+I10 | ... Y11: =Y6+Y7+Y8+Y9+Y10
A12: Gross profit | B12: =B5-B11 | C12: =C5-C11 | D12: =D5-D11 | E12: =E5-E11 | F12: =F5-F11 | G12: =G5-G11 | H12: =H5-H11 | I12: =I5-I11 | ... Y12: =Y5-Y11
A13: Gross margin | B13: =IF(B5=0,0,B12/B5) | C13: =IF(C5=0,0,C12/C5) | D13: =IF(D5=0,0,D12/D5) | E13: =IF(E5=0,0,E12/E5) | F13: =IF(F5=0,0,F12/F5) | G13: =IF(G5=0,0,G12/G5) | H13: =IF(H5=0,0,H12/H5) | I13: =IF(I5=0,0,I12/I5) | ... Y13: =IF(Y5=0,0,Y12/Y5)
A14: R&D payroll | B14: 673876.11 | C14: 683643.19 | D14: 676675.92 | E14: 676675.92 | F14: 706370.87 | G14: 720011.33 | H14: 754184.7 | I14: 756900.63 | J14: 774196.61 | K14: 774196.61 | L14: 787402.77 | M14: 800933.62 | N14: 833018.62 | O14: 833018.62 | P14: 827647.36 | Q14: 827647.36 | R14: 856615.02 | S14: 856615.02 | T14: 862049.07 | U14: 885296.31 | V14: 910300.98 | W14: 890741.58 | X14: 925826.96 | Y14: 935879.88
A15: R&D recruiting | B15: 0 | C15: 13966.276 | D15: 12351.818 | E15: 0 | F15: 29113.757 | G15: 15504.431 | H15: 42618.522 | I15: 18602.984 | J15: 43278.389 | K15: 0 | L15: 18883.925 | M15: 19348.206 | N15: 39686.422 | O15: 0 | P15: 13927.866 | Q15: 0 | R15: 0 | S15: 0 | T15: 28759.315 | U15: 42383.073 | V15: 43841.115 | W15: 14438.192 | X15: 43898.195 | Y15: 14375.004
A16: R&D tooling | B16: 22950 | C16: 23400 | D16: 23400 | E16: 23400 | F16: 23850 | G16: 24300 | H16: 25650 | I16: 25650 | J16: 26550 | K16: 26550 | L16: 27000 | M16: 27450 | N16: 28800 | O16: 28800 | P16: 28800 | Q16: 28800 | R16: 28800 | S16: 28800 | T16: 29250 | U16: 30150 | V16: 31050 | W16: 30600 | X16: 31950 | Y16: 32400
A17: R&D contractors | B17: 55000 | C17: 55000 | D17: 55000 | E17: 55000 | F17: 55000 | G17: 55000 | H17: 55000 | I17: 55000 | J17: 55000 | K17: 55000 | L17: 55000 | M17: 55000 | N17: 55000 | O17: 55000 | P17: 55000 | Q17: 55000 | R17: 60000 | S17: 60000 | T17: 60000 | U17: 60000 | V17: 60000 | W17: 60000 | X17: 60000 | Y17: 60000
A18: R&D total | B18: =B14+B15+B16+B17 | C18: =C14+C15+C16+C17 | D18: =D14+D15+D16+D17 | E18: =E14+E15+E16+E17 | F18: =F14+F15+F16+F17 | G18: =G14+G15+G16+G17 | H18: =H14+H15+H16+H17 | I18: =I14+I15+I16+I17 | ... Y18: =Y14+Y15+Y16+Y17
A19: Sales and marketing payroll | B19: 206685.85 | C19: 206685.85 | D19: 218341.68 | E19: 218341.68 | F19: 232797.7 | G19: 244451.59 | H19: 244451.59 | I19: 255750.61 | J19: 247571.39 | K19: 253299.08 | L19: 288526.12 | M19: 281712.06 | N19: 288550.23 | O19: 306993.18 | P19: 306993.18 | Q19: 306993.18 | R19: 327723.15 | S19: 334190.58 | T19: 306855.27 | U19: 306855.27 | V19: 320140.53 | W19: 320140.53 | X19: 320140.53 | Y19: 320140.53
A20: Sales and marketing recruiting | B20: 0 | C20: 0 | D20: 17126.939 | E20: 0 | F20: 10012.488 | G20: 17124.094 | H20: 0 | I20: 16602.643 | J20: 0 | K20: 18243.62 | L20: 51762.18 | M20: 0 | N20: 10047.915 | O20: 27099.843 | P20: 0 | Q20: 0 | R20: 34134.999 | S20: 9503.1718 | T20: 0 | U20: 0 | V20: 18229.508 | W20: 0 | X20: 0 | Y20: 0
A21: Sales commission | B21: 38017.948 | C21: 38371.493 | D21: 38874.272 | E21: 46694.134 | F21: 36787.45 | G21: 41221.06 | H21: 49900.673 | I21: 41803.745 | J21: 49890.48 | K21: 54306.455 | L21: 51512.004 | M21: 46229.702 | N21: 61485.318 | O21: 58014.99 | P21: 63340.661 | Q21: 69546.983 | R21: 48737.061 | S21: 58264.46 | T21: 67352.568 | U21: 63305.941 | V21: 70130.115 | W21: 68101.655 | X21: 56649.129 | Y21: 62767.852
A22: Marketing programmes | B22: 224000 | C22: 224000 | D22: 224000 | E22: 280000 | F22: 196000 | G22: 224000 | H22: 280000 | I22: 224000 | J22: 280000 | K22: 308000 | L22: 280000 | M22: 252000 | N22: 364000 | O22: 336000 | P22: 364000 | Q22: 420000 | R22: 276300 | S22: 337700 | T22: 399100 | U22: 368400 | V22: 549800 | W22: 399100 | X22: 337700 | Y22: 368400
A23: Sales and marketing total | B23: =B19+B20+B21+B22 | C23: =C19+C20+C21+C22 | D23: =D19+D20+D21+D22 | E23: =E19+E20+E21+E22 | F23: =F19+F20+F21+F22 | G23: =G19+G20+G21+G22 | H23: =H19+H20+H21+H22 | I23: =I19+I20+I21+I22 | ... Y23: =Y19+Y20+Y21+Y22
A24: G&A payroll | B24: 221317.18 | C24: 221317.18 | D24: 221317.18 | E24: 221317.18 | F24: 229063.28 | G24: 229063.28 | H24: 229063.28 | I24: 229063.28 | J24: 218412.6 | K24: 218412.6 | L24: 218412.6 | M24: 218412.6 | N24: 218412.6 | O24: 228002.69 | P24: 228002.69 | Q24: 236914.49 | R24: 245206.49 | S24: 245206.49 | T24: 254910.49 | U24: 254910.49 | V24: 254910.49 | W24: 244028.04 | X24: 244028.04 | Y24: 252881.29
A25: G&A recruiting | B25: 0 | C25: 0 | D25: 0 | E25: 0 | F25: 0 | G25: 0 | H25: 0 | I25: 0 | J25: 0 | K25: 0 | L25: 0 | M25: 0 | N25: 0 | O25: 13713.186 | P25: 0 | Q25: 12743.278 | R25: 0 | S25: 0 | T25: 13876.07 | U25: 0 | V25: 0 | W25: 0 | X25: 0 | Y25: 12659.558
A26: Rent | B26: 50600 | C26: 51050 | D26: 51700 | E26: 51700 | F26: 53150 | G26: 54250 | H26: 55900 | I26: 56850 | J26: 56950 | K26: 57000 | L26: 58950 | M26: 59350 | N26: 61500 | O26: 63400 | P26: 63850 | Q26: 64300 | R26: 64800 | S26: 65300 | T26: 65550 | U26: 66750 | V26: 68300 | W26: 67450 | X26: 69100 | Y26: 70000
A27: Software seats | B27: 18720 | C27: 18900 | D27: 19080 | E27: 19080 | F27: 19620 | G27: 19980 | H27: 20520 | I27: 20880 | J27: 20880 | K27: 20880 | L27: 21600 | M27: 21780 | N27: 22500 | O27: 23220 | P27: 23400 | Q27: 23580 | R27: 23760 | S27: 23940 | T27: 24120 | U27: 24480 | V27: 25020 | W27: 24660 | X27: 25200 | Y27: 25560
A28: Fixed G&A | B28: 72000 | C28: 72000 | D28: 72000 | E28: 72000 | F28: 72000 | G28: 72000 | H28: 72000 | I28: 72000 | J28: 72000 | K28: 72000 | L28: 72000 | M28: 72000 | N28: 72000 | O28: 72000 | P28: 72000 | Q28: 72000 | R28: 75000 | S28: 75000 | T28: 75000 | U28: 75000 | V28: 75000 | W28: 75000 | X28: 75000 | Y28: 75000
A29: G&A total | B29: =B24+B25+B26+B27+B28 | C29: =C24+C25+C26+C27+C28 | D29: =D24+D25+D26+D27+D28 | E29: =E24+E25+E26+E27+E28 | F29: =F24+F25+F26+F27+F28 | G29: =G24+G25+G26+G27+G28 | H29: =H24+H25+H26+H27+H28 | I29: =I24+I25+I26+I27+I28 | ... Y29: =Y24+Y25+Y26+Y27+Y28
A30: Operating expenses | B30: =B18+B23+B29 | C30: =C18+C23+C29 | D30: =D18+D23+D29 | E30: =E18+E23+E29 | F30: =F18+F23+F29 | G30: =G18+G23+G29 | H30: =H18+H23+H29 | I30: =I18+I23+I29 | ... Y30: =Y18+Y23+Y29
A31: EBITDA | B31: =B12-B30 | C31: =C12-C30 | D31: =D12-D30 | E31: =E12-E30 | F31: =F12-F30 | G31: =G12-G30 | H31: =H12-H30 | I31: =I12-I30 | ... Y31: =Y12-Y30
A32: EBITDA margin | B32: =IF(B5=0,0,B31/B5) | C32: =IF(C5=0,0,C31/C5) | D32: =IF(D5=0,0,D31/D5) | E32: =IF(E5=0,0,E31/E5) | F32: =IF(F5=0,0,F31/F5) | G32: =IF(G5=0,0,G31/G5) | H32: =IF(H5=0,0,H31/H5) | I32: =IF(I5=0,0,I31/I5) | ... Y32: =IF(Y5=0,0,Y31/Y5)
A33: FTE total | B33: 104 | C33: 105 | D33: 106 | E33: 106 | F33: 109 | G33: 111 | H33: 114 | I33: 116 | J33: 116 | K33: 116 | L33: 120 | M33: 121 | N33: 125 | O33: 129 | P33: 130 | Q33: 131 | R33: 132 | S33: 133 | T33: 134 | U33: 136 | V33: 139 | W33: 137 | X33: 140 | Y33: 142
A34: FTE customer operations | B34: 22 | C34: 22 | D34: 22 | E34: 22 | F34: 23 | G34: 23 | H34: 23 | I34: 24 | J34: 24 | K34: 24 | L34: 23 | M34: 24 | N34: 24 | O34: 25 | P34: 26 | Q34: 26 | R34: 26 | S34: 26 | T34: 27 | U34: 27 | V34: 27 | W34: 27 | X34: 27 | Y34: 27
A35: FTE R&D | B35: 51 | C35: 52 | D35: 52 | E35: 52 | F35: 53 | G35: 54 | H35: 57 | I35: 57 | J35: 59 | K35: 59 | L35: 60 | M35: 61 | N35: 64 | O35: 64 | P35: 64 | Q35: 64 | R35: 64 | S35: 64 | T35: 65 | U35: 67 | V35: 69 | W35: 68 | X35: 71 | Y35: 72
A36: FTE sales and marketing | B36: 18 | C36: 18 | D36: 19 | E36: 19 | F36: 20 | G36: 21 | H36: 21 | I36: 22 | J36: 21 | K36: 21 | L36: 25 | M36: 24 | N36: 25 | O36: 27 | P36: 27 | Q36: 27 | R36: 28 | S36: 29 | T36: 27 | U36: 27 | V36: 28 | W36: 28 | X36: 28 | Y36: 28
A37: FTE G&A | B37: 13 | C37: 13 | D37: 13 | E37: 13 | F37: 13 | G37: 13 | H37: 13 | I37: 13 | J37: 12 | K37: 12 | L37: 12 | M37: 12 | N37: 12 | O37: 13 | P37: 13 | Q37: 14 | R37: 14 | S37: 14 | T37: 15 | U37: 15 | V37: 15 | W37: 14 | X37: 14 | Y37: 15
A38: Total ARR (closing) | B38: 12335704 | C38: 12664114 | D38: 12985374 | E38: 13388533 | F38: 14319072 | G38: 14660656 | H38: 15093875 | I38: 15438197 | J38: 15869561 | K38: 16342440 | L38: 16782459 | M38: 17164364 | N38: 17709416 | O38: 18211811 | P38: 18769622 | Q38: 19393792 | R38: 20804496 | S38: 21239285 | T38: 21751404 | U38: 22233078 | V38: 22793154 | W38: 23321510 | X38: 23753026 | Y38: 24252076
A39: Shaded yellow: values from the model. Shaded blue: Excel formulas.
A41: Actuals: ARR roll-forward
A42: USD, monthly | B42: 2024-09 | C42: 2024-10 | D42: 2024-11 | E42: 2024-12 | F42: 2025-01 | G42: 2025-02 | H42: 2025-03 | I42: 2025-04 | J42: 2025-05 | K42: 2025-06 | L42: 2025-07 | M42: 2025-08 | N42: 2025-09 | O42: 2025-10 | P42: 2025-11 | Q42: 2025-12 | R42: 2026-01 | S42: 2026-02 | T42: 2026-03 | U42: 2026-04 | V42: 2026-05 | W42: 2026-06 | X42: 2026-07 | Y42: 2026-08
A43: Opening Platform ARR | B43: 11500000 | C43: 11773051 | D43: 12061217 | E43: 12341418 | F43: 12698659 | G43: 13587112 | H43: 13883145 | I43: 14265276 | J43: 14561020 | K43: 14937783 | L43: 15352130 | M43: 15734011 | N43: 16058458 | O43: 16533860 | P43: 16967034 | Q43: 17450415 | R43: 17991740 | S43: 19345700 | T43: 19714988 | U43: 20154741 | V43: 20564091 | W43: 21042595 | X43: 21490942 | Y43: 21845279
A44: New ARR | B44: 272000 | C44: 272000 | D44: 272000 | E44: 340000 | F44: 249900 | G44: 285600 | H44: 357000 | I44: 285600 | J44: 357000 | K44: 392700 | L44: 357000 | M44: 321300 | N44: 464100 | O44: 428400 | P44: 464100 | Q44: 535500 | R44: 340578 | S44: 416262 | T44: 491946 | U44: 454104 | V44: 529788 | W44: 491946 | X44: 416262 | Y44: 454104
A45: Expansion ARR | B45: 108179.48 | C45: 111714.93 | D45: 116742.72 | E45: 126941.34 | F45: 117974.5 | G45: 126610.6 | H45: 142006.73 | I45: 132437.45 | J45: 141904.8 | K45: 150364.55 | L45: 158120.04 | M45: 140997.02 | N45: 150753.18 | O45: 151749.9 | P45: 169306.61 | Q45: 159969.83 | R45: 146792.61 | S45: 166382.6 | T45: 181579.68 | U45: 178955.41 | V45: 171513.15 | W45: 189070.55 | X45: 150229.29 | Y45: 173574.52
A46: Price ARR | B46: 0 | C46: 0 | D46: 0 | E46: 0 | F46: 634932.95 | G46: 0 | H46: 0 | I46: 0 | J46: 0 | K46: 0 | L46: 0 | M46: 0 | N46: 0 | O46: 0 | P46: 0 | Q46: 0 | R46: 1079504.4 | S46: 0 | T46: 0 | U46: 0 | V46: 0 | W46: 0 | X46: 0 | Y46: 0
A47: Churned ARR | B47: -107128.97 | C47: -95548.488 | D47: -108541.94 | E47: -109700.12 | F47: -114354.29 | G47: -116177.87 | H47: -116875.24 | I47: -122293.79 | J47: -122141.47 | K47: -128717.97 | L47: -133238.61 | M47: -137850.45 | N47: -139451.45 | O47: -146975.41 | P47: -150025.74 | Q47: -154144.54 | R47: -212915.02 | S47: -213357.15 | T47: -233772.41 | U47: -223709.66 | V47: -222797.23 | W47: -232669.02 | X47: -212154.58 | Y47: -211884.17
A48: Closing Platform ARR | B48: =B43+B44+B45+B46+B47 | C48: =C43+C44+C45+C46+C47 | D48: =D43+D44+D45+D46+D47 | E48: =E43+E44+E45+E46+E47 | F48: =F43+F44+F45+F46+F47 | G48: =G43+G44+G45+G46+G47 | H48: =H43+H44+H45+H46+H47 | I48: =I43+I44+I45+I46+I47 | ... Y48: =Y43+Y44+Y45+Y46+Y47
A49: Opening customers | B49: 380 | C49: 384.46009 | D49: 389.33986 | E49: 393.83609 | F49: 400.33537 | G49: 403.73026 | H49: 408.27813 | I49: 414.84104 | J49: 419.28468 | K49: 425.76761 | L49: 433.0988 | M49: 439.34001 | N49: 444.49081 | O49: 453.63086 | P49: 461.59837 | Q49: 470.51683 | R49: 481.36062 | S49: 484.66418 | T49: 490.31898 | U49: 497.50498 | V49: 503.98287 | W49: 512.52258 | X49: 519.85559 | Y49: 525.72367
A50: New logos | B50: 8 | C50: 8 | D50: 8 | E50: 10 | F50: 7 | G50: 8 | H50: 10 | I50: 8 | J50: 10 | K50: 11 | L50: 10 | M50: 9 | N50: 13 | O50: 12 | P50: 13 | Q50: 15 | R50: 9 | S50: 11 | T50: 13 | U50: 12 | V50: 14 | W50: 13 | X50: 11 | Y50: 12
A51: Churned customers | B51: -3.5399137 | C51: -3.1202261 | D51: -3.5037678 | E51: -3.5007214 | F51: -3.6051102 | G51: -3.4521334 | H51: -3.4370889 | I51: -3.5563616 | J51: -3.5170646 | K51: -3.6688135 | L51: -3.7587931 | M51: -3.849191 | N51: -3.8599527 | O51: -4.0324876 | P51: -4.0815405 | Q51: -4.1562107 | R51: -5.6964421 | S51: -5.3451965 | T51: -5.8140057 | U51: -5.5221085 | V51: -5.4602944 | W51: -5.6669877 | X51: -5.1319176 | Y51: -5.0991577
A52: Closing customers | B52: =B49+B50+B51 | C52: =C49+C50+C51 | D52: =D49+D50+D51 | E52: =E49+E50+E51 | F52: =F49+F50+F51 | G52: =G49+G50+G51 | H52: =H49+H50+H51 | I52: =I49+I50+I51 | ... Y52: =Y49+Y50+Y51
A53: Insights attach rate | B53: 0.126 | C53: 0.132 | D53: 0.138 | E53: 0.144 | F53: 0.15 | G53: 0.156 | H53: 0.162 | I53: 0.168 | J53: 0.174 | K53: 0.18 | L53: 0.186 | M53: 0.192 | N53: 0.198 | O53: 0.204 | P53: 0.21 | Q53: 0.216 | R53: 0.221 | S53: 0.226 | T53: 0.231 | U53: 0.236 | V53: 0.241 | W53: 0.246 | X53: 0.251 | Y53: 0.256
A54: Insights customers | B54: 48.441971 | C54: 51.392862 | D54: 54.349381 | E54: 57.648293 | F54: 60.559539 | G54: 63.691388 | H54: 67.204248 | I54: 70.439826 | J54: 74.083565 | K54: 77.957784 | L54: 81.717241 | M54: 85.342236 | N54: 89.818911 | O54: 94.166068 | P54: 98.808535 | Q54: 103.97389 | R54: 107.11078 | S54: 110.81209 | T54: 114.92365 | U54: 118.93996 | V54: 123.51794 | W54: 127.88447 | X54: 131.95664 | Y54: 136.35188
A55: Insights ARR per customer | B55: 11615 | C55: 11731.15 | D55: 11848.461 | E55: 11966.946 | F55: 12086.616 | G55: 12207.482 | H55: 12329.557 | I55: 12452.852 | J55: 12577.381 | K55: 12703.154 | L55: 12830.186 | M55: 12958.488 | N55: 13088.073 | O55: 13218.953 | P55: 13351.143 | Q55: 13484.654 | R55: 13619.501 | S55: 13755.696 | T55: 13893.253 | U55: 14032.185 | V55: 14172.507 | W55: 14314.232 | X55: 14457.375 | Y55: 14601.948
A56: Insights ARR | B56: 562653.49 | C56: 602897.37 | D56: 643956.55 | E56: 689874.02 | F56: 731959.87 | G56: 777511.45 | H56: 828598.58 | I56: 877176.73 | J56: 931777.19 | K56: 990309.77 | L56: 1048447.4 | M56: 1105906.3 | N56: 1175556.4 | O56: 1244776.9 | P56: 1319206.9 | Q56: 1402052 | R56: 1458795.4 | S56: 1524297.4 | T56: 1596663.3 | U56: 1668987.5 | V56: 1750558.9 | W56: 1830568.1 | X56: 1907746.6 | Y56: 1991003.1
A57: Total ARR | B57: =B48+B56 | C57: =C48+C56 | D57: =D48+D56 | E57: =E48+E56 | F57: =F48+F56 | G57: =G48+G56 | H57: =H48+H56 | I57: =I48+I56 | ... Y57: =Y48+Y56
A58: Shaded yellow: values from the model. Shaded blue: Excel formulas.
A60: Actuals: cloud hosting
A61: USD, monthly | B61: 2024-09 | C61: 2024-10 | D61: 2024-11 | E61: 2024-12 | F61: 2025-01 | G61: 2025-02 | H61: 2025-03 | I61: 2025-04 | J61: 2025-05 | K61: 2025-06 | L61: 2025-07 | M61: 2025-08 | N61: 2025-09 | O61: 2025-10 | P61: 2025-11 | Q61: 2025-12 | R61: 2026-01 | S61: 2026-02 | T61: 2026-03 | U61: 2026-04 | V61: 2026-05 | W61: 2026-06 | X61: 2026-07 | Y61: 2026-08
A62: Platform compute units | B62: 74918.053 | C62: 78743.251 | D62: 79566.706 | E62: 79088.042 | F62: 81989.662 | G62: 81263.716 | H62: 82001.643 | I62: 86189.514 | J62: 85453.68 | K62: 84690.734 | L62: 88517.94 | M62: 89878.133 | N62: 93087.798 | O62: 91168.694 | P62: 92056.207 | Q62: 98228.505 | R62: 97536.082 | S62: 96719.116 | T62: 97293.069 | U62: 98998.37 | V62: 101710.44 | W62: 103164.82 | X62: 103407.87 | Y62: 107717.02
A63: Insights compute units | B63: 70587.464 | C63: 78413.48 | D63: 80879.643 | E63: 84969.652 | F63: 91697.475 | G63: 96018.651 | H63: 99333.457 | I63: 105700.66 | J63: 110526.35 | K63: 116577.4 | L63: 120975.42 | M63: 124254.91 | N63: 137599.32 | O63: 144102.66 | P63: 144341.27 | Q63: 152164.52 | R63: 164691.33 | S63: 168598.91 | T63: 229634.52 | U63: 232535.85 | V63: 248808.01 | W63: 256858.35 | X63: 257596.32 | Y63: 274210.2
A64: Total units | B64: =B62+B63 | C64: =C62+C63 | D64: =D62+D63 | E64: =E62+E63 | F64: =F62+F63 | G64: =G62+G63 | H64: =H62+H63 | I64: =I62+I63 | ... Y64: =Y62+Y63
A65: Committed units | B65: 0 | C65: 0 | D65: 0 | E65: 0 | F65: 0 | G65: 0 | H65: 0 | I65: 0 | J65: 0 | K65: 0 | L65: 0 | M65: 0 | N65: 0 | O65: 0 | P65: 0 | Q65: 0 | R65: 0 | S65: 0 | T65: 0 | U65: 0 | V65: 0 | W65: 0 | X65: 0 | Y65: 0
A66: On-demand unit price | B66: 0.43912 | C66: 0.43824176 | D66: 0.43736528 | E66: 0.43649055 | F66: 0.43561756 | G66: 0.43474633 | H66: 0.43387684 | I66: 0.43300908 | J66: 0.43214307 | K66: 0.43127878 | L66: 0.43041622 | M66: 0.42955539 | N66: 0.42869628 | O66: 0.42783889 | P66: 0.42698321 | Q66: 0.42612924 | R66: 0.42527698 | S66: 0.42442643 | T66: 0.42357758 | U66: 0.42273042 | V66: 0.42188496 | W66: 0.42104119 | X66: 0.42019911 | Y66: 0.41935871
A67: Commitment discount | B67: 0 | C67: 0 | D67: 0 | E67: 0 | F67: 0 | G67: 0 | H67: 0 | I67: 0 | J67: 0 | K67: 0 | L67: 0 | M67: 0 | N67: 0 | O67: 0 | P67: 0 | Q67: 0 | R67: 0 | S67: 0 | T67: 0 | U67: 0 | V67: 0 | W67: 0 | X67: 0 | Y67: 0
A68: Committed cost | B68: =MIN(B64,B65)*B66*(1-B67) | C68: =MIN(C64,C65)*C66*(1-C67) | D68: =MIN(D64,D65)*D66*(1-D67) | E68: =MIN(E64,E65)*E66*(1-E67) | F68: =MIN(F64,F65)*F66*(1-F67) | G68: =MIN(G64,G65)*G66*(1-G67) | H68: =MIN(H64,H65)*H66*(1-H67) | I68: =MIN(I64,I65)*I66*(1-I67) | ... Y68: =MIN(Y64,Y65)*Y66*(1-Y67)
A69: On-demand cost | B69: =MAX(B64-B65,0)*B66 | C69: =MAX(C64-C65,0)*C66 | D69: =MAX(D64-D65,0)*D66 | E69: =MAX(E64-E65,0)*E66 | F69: =MAX(F64-F65,0)*F66 | G69: =MAX(G64-G65,0)*G66 | H69: =MAX(H64-H65,0)*H66 | I69: =MAX(I64-I65,0)*I66 | ... Y69: =MAX(Y64-Y65,0)*Y66
A70: Fixed cloud cost | B70: 25000 | C70: 25000 | D70: 25000 | E70: 25000 | F70: 25000 | G70: 25000 | H70: 25000 | I70: 25000 | J70: 25000 | K70: 25000 | L70: 25000 | M70: 25000 | N70: 25000 | O70: 25000 | P70: 25000 | Q70: 25000 | R70: 28000 | S70: 28000 | T70: 28000 | U70: 28000 | V70: 28000 | W70: 28000 | X70: 28000 | Y70: 28000
A71: Cloud hosting total | B71: =B68+B69+B70 | C71: =C68+C69+C70 | D71: =D68+D69+D70 | E71: =E68+E69+E70 | F71: =F68+F69+F70 | G71: =G68+G69+G70 | H71: =H68+H69+H70 | I71: =I68+I69+I70 | ... Y71: =Y68+Y69+Y70
A72: Shaded yellow: values from the model. Shaded blue: Excel formulas.
A74: Actuals: cash
A75: USD, monthly | B75: 2024-09 | C75: 2024-10 | D75: 2024-11 | E75: 2024-12 | F75: 2025-01 | G75: 2025-02 | H75: 2025-03 | I75: 2025-04 | J75: 2025-05 | K75: 2025-06 | L75: 2025-07 | M75: 2025-08 | N75: 2025-09 | O75: 2025-10 | P75: 2025-11 | Q75: 2025-12 | R75: 2026-01 | S75: 2026-02 | T75: 2026-03 | U75: 2026-04 | V75: 2026-05 | W75: 2026-06 | X75: 2026-07 | Y75: 2026-08
A76: Opening cash | B76: =21000000.0 | C76: =B83 | D76: =C83 | E76: =D83 | F76: =E83 | G76: =F83 | H76: =G83 | I76: =H83 | J76: =I83 | ... Y76: =X83
A77: EBITDA | B77: -912715.59 | C77: -916724.77 | D77: -913992.67 | E77: -917685.03 | F77: -878605.21 | G77: -892330.46 | H77: -971840.71 | I77: -908898.18 | J77: -938243.89 | K77: -930976.33 | L77: -948299.47 | M77: -860130.34 | N77: -1014302.9 | O77: -985674.4 | P77: -962876.72 | Q77: -971291.93 | R77: -799686.51 | S77: -819616.22 | T77: -932059.89 | U77: -859335.35 | V77: -1071683.2 | W77: -813918.03 | X77: -761394.08 | Y77: -770720.08
A78: Equipment capex | B78: 0 | C78: -3500 | D78: -7000 | E78: 0 | F78: -14000 | G78: -7000 | H78: -10500 | I78: -10500 | J78: -10500 | K78: -7000 | L78: -17500 | M78: -7000 | N78: -14000 | O78: -14000 | P78: -7000 | Q78: -3500 | R78: -7000 | S78: -3500 | T78: -17500 | U78: -10500 | V78: -14000 | W78: -7000 | X78: -10500 | Y78: -7000
A79: Change in receivables | B79: -38913.001 | C79: -41051.29 | D79: -40157.495 | E79: -50394.837 | F79: -116317.38 | G79: -42698.039 | H79: -54152.327 | I79: -43040.227 | J79: -53920.473 | K79: -59109.895 | L79: -55002.383 | M79: -47738.188 | N79: -68131.48 | O79: -62799.366 | P79: -69726.36 | Q79: -78021.306 | R79: -176337.93 | S79: -54348.681 | T79: -64014.898 | U79: -60209.245 | V79: -70009.411 | W79: -66044.587 | X79: -53939.403 | Y79: -62381.349
A80: Change in deferred revenue | B80: 57072.401 | C80: 60208.559 | D80: 58897.659 | E80: 73912.428 | F80: 170598.82 | G80: 62623.791 | H80: 79423.413 | I80: 63125.666 | J80: 79083.361 | K80: 86694.513 | L80: 80670.162 | M80: 70016.01 | N80: 99926.17 | O80: 92105.736 | P80: 102265.33 | Q80: 114431.25 | R80: 258628.96 | S80: 79711.399 | T80: 93888.517 | U80: 88306.893 | V80: 102680.47 | W80: 96865.395 | X80: 79111.124 | Y80: 91492.646
A81: Financing | B81: 0 | C81: 0 | D81: 0 | E81: 0 | F81: 0 | G81: 0 | H81: 0 | I81: 0 | J81: 0 | K81: 0 | L81: 0 | M81: 0 | N81: 0 | O81: 0 | P81: 0 | Q81: 0 | R81: 0 | S81: 0 | T81: 25000000 | U81: 0 | V81: 0 | W81: 0 | X81: 0 | Y81: 0
A82: Net cash flow | B82: =B77+B78+B79+B80+B81 | C82: =C77+C78+C79+C80+C81 | D82: =D77+D78+D79+D80+D81 | E82: =E77+E78+E79+E80+E81 | F82: =F77+F78+F79+F80+F81 | G82: =G77+G78+G79+G80+G81 | H82: =H77+H78+H79+H80+H81 | I82: =I77+I78+I79+I80+I81 | ... Y82: =Y77+Y78+Y79+Y80+Y81
A83: Closing cash | B83: =B76+B82 | C83: =C76+C82 | D83: =D76+D82 | E83: =E76+E82 | F83: =F76+F82 | G83: =G76+G82 | H83: =H76+H82 | I83: =I76+I82 | ... Y83: =Y76+Y82
A84: Receivables | B84: 1541963 | C84: 1583014.3 | D84: 1623171.8 | E84: 1673566.6 | F84: 1789884 | G84: 1832582 | H84: 1886734.4 | I84: 1929774.6 | J84: 1983695.1 | K84: 2042805 | L84: 2097807.3 | M84: 2145545.5 | N84: 2213677 | O84: 2276476.4 | P84: 2346202.7 | Q84: 2424224 | R84: 2600562 | S84: 2654910.6 | T84: 2718925.5 | U84: 2779134.8 | V84: 2849144.2 | W84: 2915188.8 | X84: 2969128.2 | Y84: 3031509.5
A85: Deferred revenue | B85: 2261545.7 | C85: 2321754.3 | D85: 2380652 | E85: 2454564.4 | F85: 2625163.2 | G85: 2687787 | H85: 2767210.4 | I85: 2830336.1 | J85: 2909419.4 | K85: 2996113.9 | L85: 3076784.1 | M85: 3146800.1 | N85: 3246726.3 | O85: 3338832 | P85: 3441097.3 | Q85: 3555528.6 | R85: 3814157.6 | S85: 3893869 | T85: 3987757.5 | U85: 4076064.4 | V85: 4178744.8 | W85: 4275610.2 | X85: 4354721.4 | Y85: 4446214
A86: Net burn, trailing 3 months | B86: 894556.19 | C86: 897811.85 | D86: 899292.07 | E86: 899162.48 | F86: 878247.91 | G86: 870631.97 | H86: 891599.36 | I86: 911929.02 | J86: 926654.45 | K86: 911095.15 | L86: 924701.47 | M86: 898458.64 | N86: 927164.13 | O86: 937242.91 | P86: 968071.32 | Q86: 948695.93 | R86: 866705.07 | S86: 820176.99 | T86: 813945.09 | U86: 853059.16 | V86: 938145.37 | W86: 894949.02 | X86: 863277.24 | Y86: 761809.45
A87: Runway (months) | B87: 22.475328 | C87: 21.390202 | D87: 20.351702 | E87: 19.36019 | F87: 18.866692 | G87: 18.021654 | H87: 16.524415 | I87: 15.169871 | J87: 13.932124 | K87: 13.170823 | L87: 11.960337 | M87: 11.369348 | N87: 9.9425551 | O87: 8.8002932 | P87: 7.5517934 | Q87: 6.7168968 | R87: 6.5165156 | S87: 5.9135329 | T87: 35.5435 | U87: 32.927048 | V87: 28.81825 | W87: 29.326375 | X87: 29.537311 | Y87: 32.488806
A88: Shaded yellow: values from the model. Shaded blue: Excel formulas.

Sheet Budget FY2026
A1: Budget FY2026: P&L
A2: USD, monthly | B2: 2026-01 | C2: 2026-02 | D2: 2026-03 | E2: 2026-04 | F2: 2026-05 | G2: 2026-06 | H2: 2026-07 | I2: 2026-08 | J2: 2026-09 | K2: 2026-10 | L2: 2026-11 | M2: 2026-12
A3: Platform revenue | B3: 1614950.5 | C3: 1660358.5 | D3: 1714652.2 | E3: 1763407.2 | F3: 1816411.8 | G3: 1874614.7 | H3: 1919980.4 | I3: 1965383.6 | J3: 2021133 | K3: 2076928.5 | L3: 2130193.3 | M3: 2193810.6
A4: Insights revenue | B4: 123404.15 | C4: 130574.92 | D4: 138757.38 | E4: 146734.36 | F4: 155372.69 | G4: 164804.51 | H4: 173285.45 | I4: 182028.4 | J4: 192132.35 | K4: 202567.4 | L4: 213046.87 | M4: 225055.15
A5: Revenue | B5: =B3+B4 | C5: =C3+C4 | D5: =D3+D4 | E5: =E3+E4 | F5: =F3+F4 | G5: =G3+G4 | H5: =H3+H4 | I5: =I3+I4 | ... M5: =M3+M4
A6: Cloud hosting | B6: 139018.65 | C6: 142927.85 | D6: 147536.93 | E6: 151773.61 | F6: 156375 | G6: 161424.06 | H6: 165507.83 | I6: 169624.24 | J6: 174607.9 | K6: 179636.34 | L6: 184494 | M6: 190258.07
A7: Third-party software and data | B7: 52150.641 | C7: 53728.003 | D7: 55602.286 | E7: 57304.246 | F7: 59153.536 | G7: 61182.576 | H7: 62797.974 | I7: 64422.361 | J7: 66397.96 | K7: 68384.878 | L7: 70297.205 | M7: 72565.974
A8: Payment processing | B8: 26075.32 | C8: 26864.001 | D8: 27801.143 | E8: 28652.123 | F8: 29576.768 | G8: 30591.288 | H8: 31398.987 | I8: 32211.181 | J8: 33198.98 | K8: 34192.439 | L8: 35148.603 | M8: 36282.987
A9: Customer operations payroll | B9: 269286 | C9: 269286 | D9: 288569.46 | E9: 288569.46 | F9: 288569.46 | G9: 288569.46 | H9: 288569.46 | I9: 288569.46 | J9: 288569.46 | K9: 288569.46 | L9: 288569.46 | M9: 288569.46
A10: Customer operations recruiting | B10: 0 | C10: 0 | D10: 27000 | E10: 0 | F10: 0 | G10: 0 | H10: 0 | I10: 0 | J10: 0 | K10: 0 | L10: 0 | M10: 0
A11: Cost of revenue | B11: =B6+B7+B8+B9+B10 | C11: =C6+C7+C8+C9+C10 | D11: =D6+D7+D8+D9+D10 | E11: =E6+E7+E8+E9+E10 | F11: =F6+F7+F8+F9+F10 | G11: =G6+G7+G8+G9+G10 | H11: =H6+H7+H8+H9+H10 | I11: =I6+I7+I8+I9+I10 | ... M11: =M6+M7+M8+M9+M10
A12: Gross profit | B12: =B5-B11 | C12: =C5-C11 | D12: =D5-D11 | E12: =E5-E11 | F12: =F5-F11 | G12: =G5-G11 | H12: =H5-H11 | I12: =I5-I11 | ... M12: =M5-M11
A13: Gross margin | B13: =IF(B5=0,0,B12/B5) | C13: =IF(C5=0,0,C12/C5) | D13: =IF(D5=0,0,D12/D5) | E13: =IF(E5=0,0,E12/E5) | F13: =IF(F5=0,0,F12/F5) | G13: =IF(G5=0,0,G12/G5) | H13: =IF(H5=0,0,H12/H5) | I13: =IF(I5=0,0,I12/I5) | ... M13: =IF(M5=0,0,M12/M5)
A14: R&D payroll | B14: 868781.29 | C14: 925520.35 | D14: 950092.54 | E14: 950092.54 | F14: 950092.54 | G14: 950092.54 | H14: 950092.54 | I14: 950092.54 | J14: 950092.54 | K14: 950092.54 | L14: 950092.54 | M14: 950092.54
A15: R&D recruiting | B15: 42750 | C15: 73500 | D15: 28500 | E15: 0 | F15: 0 | G15: 0 | H15: 0 | I15: 0 | J15: 0 | K15: 0 | L15: 0 | M15: 0
A16: R&D tooling | B16: 29547 | C16: 31752 | D16: 32634 | E16: 32634 | F16: 32634 | G16: 32634 | H16: 32634 | I16: 32634 | J16: 32634 | K16: 32634 | L16: 32634 | M16: 32634
A17: R&D contractors | B17: 60000 | C17: 60000 | D17: 60000 | E17: 60000 | F17: 60000 | G17: 60000 | H17: 60000 | I17: 60000 | J17: 60000 | K17: 60000 | L17: 60000 | M17: 60000
A18: R&D total | B18: =B14+B15+B16+B17 | C18: =C14+C15+C16+C17 | D18: =D14+D15+D16+D17 | E18: =E14+E15+E16+E17 | F18: =F14+F15+F16+F17 | G18: =G14+G15+G16+G17 | H18: =H14+H15+H16+H17 | I18: =I14+I15+I16+I17 | ... M18: =M14+M15+M16+M17
A19: Sales and marketing payroll | B19: 333392.35 | C19: 339895.06 | D19: 339895.06 | E19: 352750.7 | F19: 352750.7 | G19: 352750.7 | H19: 352750.7 | I19: 352750.7 | J19: 352750.7 | K19: 352750.7 | L19: 352750.7 | M19: 352750.7
A20: Sales and marketing recruiting | B20: 33000 | C20: 9750 | D20: 0 | E20: 18000 | F20: 0 | G20: 0 | H20: 0 | I20: 0 | J20: 0 | K20: 0 | L20: 0 | M20: 0
A21: Sales commission | B21: 64535.604 | C21: 71430.283 | D21: 82569.437 | E21: 76492.576 | F21: 82103.649 | G21: 88897.453 | H21: 74103.373 | I21: 74624.414 | J21: 87515.938 | K21: 88156.24 | L21: 85704.561 | M21: 98686.377
A22: Marketing programmes | B22: 353430 | C22: 395010 | D22: 474320 | E22: 424270 | F22: 462000 | G22: 508200 | H22: 392700 | I22: 392700 | J22: 485100 | K22: 485100 | L22: 462000 | M22: 554400
A23: Sales and marketing total | B23: =B19+B20+B21+B22 | C23: =C19+C20+C21+C22 | D23: =D19+D20+D21+D22 | E23: =E19+E20+E21+E22 | F23: =F19+F20+F21+F22 | G23: =G19+G20+G21+G22 | H23: =H19+H20+H21+H22 | I23: =I19+I20+I21+I22 | ... M23: =M19+M20+M21+M22
A24: G&A payroll | B24: 240302.36 | C24: 249554.54 | D24: 249554.54 | E24: 249554.54 | F24: 249554.54 | G24: 249554.54 | H24: 249554.54 | I24: 249554.54 | J24: 249554.54 | K24: 249554.54 | L24: 249554.54 | M24: 249554.54
A25: G&A recruiting | B25: 0 | C25: 13500 | D25: 0 | E25: 0 | F25: 0 | G25: 0 | H25: 0 | I25: 0 | J25: 0 | K25: 0 | L25: 0 | M25: 0
A26: Rent | B26: 65317 | C26: 68894 | D26: 71050 | E26: 71540 | F26: 71540 | G26: 71540 | H26: 71540 | I26: 71540 | J26: 71540 | K26: 71540 | L26: 71540 | M26: 71540
A27: Software seats | B27: 23990.4 | C27: 25225.2 | D27: 25930.8 | E27: 26107.2 | F27: 26107.2 | G27: 26107.2 | H27: 26107.2 | I27: 26107.2 | J27: 26107.2 | K27: 26107.2 | L27: 26107.2 | M27: 26107.2
A28: Fixed G&A | B28: 75000 | C28: 75000 | D28: 75000 | E28: 75000 | F28: 75000 | G28: 75000 | H28: 75000 | I28: 75000 | J28: 75000 | K28: 75000 | L28: 75000 | M28: 75000
A29: G&A total | B29: =B24+B25+B26+B27+B28 | C29: =C24+C25+C26+C27+C28 | D29: =D24+D25+D26+D27+D28 | E29: =E24+E25+E26+E27+E28 | F29: =F24+F25+F26+F27+F28 | G29: =G24+G25+G26+G27+G28 | H29: =H24+H25+H26+H27+H28 | I29: =I24+I25+I26+I27+I28 | ... M29: =M24+M25+M26+M27+M28
A30: Operating expenses | B30: =B18+B23+B29 | C30: =C18+C23+C29 | D30: =D18+D23+D29 | E30: =E18+E23+E29 | F30: =F18+F23+F29 | G30: =G18+G23+G29 | H30: =H18+H23+H29 | I30: =I18+I23+I29 | ... M30: =M18+M23+M29
A31: EBITDA | B31: =B12-B30 | C31: =C12-C30 | D31: =D12-D30 | E31: =E12-E30 | F31: =F12-F30 | G31: =G12-G30 | H31: =H12-H30 | I31: =I12-I30 | ... M31: =M12-M30
A32: EBITDA margin | B32: =IF(B5=0,0,B31/B5) | C32: =IF(C5=0,0,C31/C5) | D32: =IF(D5=0,0,D31/D5) | E32: =IF(E5=0,0,E31/E5) | F32: =IF(F5=0,0,F31/F5) | G32: =IF(G5=0,0,G31/G5) | H32: =IF(H5=0,0,H31/H5) | I32: =IF(I5=0,0,I31/I5) | ... M32: =IF(M5=0,0,M31/M5)
A33: FTE total | B33: 133.28 | C33: 140.14 | D33: 144.06 | E33: 145.04 | F33: 145.04 | G33: 145.04 | H33: 145.04 | I33: 145.04 | J33: 145.04 | K33: 145.04 | L33: 145.04 | M33: 145.04
A34: FTE customer operations | B34: 25.48 | C34: 25.48 | D34: 27.44 | E34: 27.44 | F34: 27.44 | G34: 27.44 | H34: 27.44 | I34: 27.44 | J34: 27.44 | K34: 27.44 | L34: 27.44 | M34: 27.44
A35: FTE R&D | B35: 65.66 | C35: 70.56 | D35: 72.52 | E35: 72.52 | F35: 72.52 | G35: 72.52 | H35: 72.52 | I35: 72.52 | J35: 72.52 | K35: 72.52 | L35: 72.52 | M35: 72.52
A36: FTE sales and marketing | B36: 28.42 | C36: 29.4 | D36: 29.4 | E36: 30.38 | F36: 30.38 | G36: 30.38 | H36: 30.38 | I36: 30.38 | J36: 30.38 | K36: 30.38 | L36: 30.38 | M36: 30.38
A37: FTE G&A | B37: 13.72 | C37: 14.7 | D37: 14.7 | E37: 14.7 | F37: 14.7 | G37: 14.7 | H37: 14.7 | I37: 14.7 | J37: 14.7 | K37: 14.7 | L37: 14.7 | M37: 14.7
A38: Total ARR (closing) | B38: 20860256 | C38: 21491201 | D38: 22240915 | E38: 22921698 | F38: 23661414 | G38: 24473030 | H38: 25119190 | I38: 25768945 | J38: 26559184 | K38: 27353951 | L38: 28118882 | M38: 29026389
A39: Shaded yellow: values from the model. Shaded blue: Excel formulas.
A41: Budget FY2026: ARR roll-forward
A42: USD, monthly | B42: 2026-01 | C42: 2026-02 | D42: 2026-03 | E42: 2026-04 | F42: 2026-05 | G42: 2026-06 | H42: 2026-07 | I42: 2026-08 | J42: 2026-09 | K42: 2026-10 | L42: 2026-11 | M42: 2026-12
A43: Opening Platform ARR | B43: 17991740 | C43: 19379407 | D43: 19924302 | E43: 20575826 | F43: 21160886 | G43: 21796942 | H43: 22495376 | I43: 23039764 | J43: 23584604 | K43: 24253596 | L43: 24923143 | M43: 25562320
A44: New ARR | B44: 473154.41 | C44: 528819.64 | D44: 634995.9 | E44: 567991.46 | F44: 618502.5 | G44: 680352.75 | H44: 525727.12 | I44: 525727.12 | J44: 649427.62 | K44: 649427.62 | L44: 618502.5 | M44: 742203
A45: Expansion ARR | B45: 172201.63 | C45: 185483.19 | D45: 190698.47 | E45: 196934.3 | F45: 202533.99 | G45: 208621.78 | H45: 215306.6 | I45: 220517.02 | J45: 225731.76 | K45: 232134.78 | L45: 238543.11 | M45: 244660.77
A46: Price ARR | B46: 899587.02 | C46: 0 | D46: 0 | E46: 0 | F46: 0 | G46: 0 | H46: 0 | I46: 0 | J46: 0 | K46: 0 | L46: 0 | M46: 0
A47: Churned ARR | B47: -157276.79 | C47: -169407.23 | D47: -174170.5 | E47: -179865.87 | F47: -184980.23 | G47: -190540.39 | H47: -196645.83 | I47: -201404.66 | J47: -206167.43 | K47: -212015.5 | L47: -217868.42 | M47: -223455.85
A48: Closing Platform ARR | B48: =B43+B44+B45+B46+B47 | C48: =C43+C44+C45+C46+C47 | D48: =D43+D44+D45+D46+D47 | E48: =E43+E44+E45+E46+E47 | F48: =F43+F44+F45+F46+F47 | G48: =G43+G44+G45+G46+G47 | H48: =H43+H44+H45+H46+H47 | I48: =I43+I44+I45+I46+I47 | ... M48: =M43+M44+M45+M46+M47
A49: Opening customers | B49: 481.36062 | C49: 489.77526 | D49: 499.60133 | E49: 512.17401 | F49: 522.84928 | G49: 534.77874 | H49: 548.25391 | I49: 557.48629 | J49: 566.63796 | K49: 579.00963 | L49: 591.27316 | M49: 602.60448
A50: New logos | B50: 12.6225 | C50: 14.1075 | D50: 16.94 | E50: 15.1525 | F50: 16.5 | G50: 18.15 | H50: 14.025 | I50: 14.025 | J50: 17.325 | K50: 17.325 | L50: 16.5 | M50: 19.8
A51: Churned customers | B51: -4.2078673 | C51: -4.2814247 | D51: -4.3673205 | E51: -4.4772259 | F51: -4.570545 | G51: -4.6748277 | H51: -4.7926224 | I51: -4.8733283 | J51: -4.9533286 | K51: -5.0614769 | L51: -5.1686799 | M51: -5.2677339
A52: Closing customers | B52: =B49+B50+B51 | C52: =C49+C50+C51 | D52: =D49+D50+D51 | E52: =E49+E50+E51 | F52: =F49+F50+F51 | G52: =G49+G50+G51 | H52: =H49+H50+H51 | I52: =I49+I50+I51 | ... M52: =M49+M50+M51
A53: Insights attach rate | B53: 0.222 | C53: 0.228 | D53: 0.234 | E53: 0.24 | F53: 0.246 | G53: 0.252 | H53: 0.258 | I53: 0.264 | J53: 0.27 | K53: 0.276 | L53: 0.282 | M53: 0.288
A54: Insights customers | B54: 108.73011 | C54: 113.9091 | D54: 119.84872 | E54: 125.48383 | F54: 131.55557 | G54: 138.15999 | H54: 143.83146 | I54: 149.59242 | J54: 156.3326 | K54: 163.19139 | L54: 169.93446 | M54: 177.73538
A55: Insights ARR per customer | B55: 13619.501 | C55: 13755.696 | D55: 13893.253 | E55: 14032.185 | F55: 14172.507 | G55: 14314.232 | H55: 14457.375 | I55: 14601.948 | J55: 14747.968 | K55: 14895.448 | L55: 15044.402 | M55: 15194.846
A56: Insights ARR | B56: 1480849.8 | C56: 1566899 | D56: 1665088.6 | E56: 1760812.4 | F56: 1864472.3 | G56: 1977654.1 | H56: 2079425.4 | I56: 2184340.8 | J56: 2305588.2 | K56: 2430808.8 | L56: 2556562.4 | M56: 2700661.8
A57: Total ARR | B57: =B48+B56 | C57: =C48+C56 | D57: =D48+D56 | E57: =E48+E56 | F57: =F48+F56 | G57: =G48+G56 | H57: =H48+H56 | I57: =I48+I56 | ... M57: =M48+M56
A58: Shaded yellow: values from the model. Shaded blue: Excel formulas.
A60: Budget FY2026: cloud hosting
A61: USD, monthly | B61: 2026-01 | C61: 2026-02 | D61: 2026-03 | E61: 2026-04 | F61: 2026-05 | G61: 2026-06 | H61: 2026-07 | I61: 2026-08 | J61: 2026-09 | K61: 2026-10 | L61: 2026-11 | M61: 2026-12
A62: Platform compute units | B62: 97955.051 | C62: 99920.266 | D62: 102434.8 | E62: 104569.86 | F62: 106955.75 | G62: 109650.78 | H62: 111497.26 | I62: 113327.59 | J62: 115801.93 | K62: 118254.63 | L62: 120520.9 | M62: 123427.35
A63: Insights compute units | B63: 163095.16 | C63: 170863.66 | D63: 179773.08 | E63: 188225.74 | F63: 197333.35 | G63: 207239.98 | H63: 215747.19 | I63: 224388.63 | J63: 234498.9 | K63: 244787.09 | L63: 254901.69 | M63: 266603.07
A64: Total units | B64: =B62+B63 | C64: =C62+C63 | D64: =D62+D63 | E64: =E62+E63 | F64: =F62+F63 | G64: =G62+G63 | H64: =H62+H63 | I64: =I62+I63 | ... M64: =M62+M63
A65: Committed units | B65: 0 | C65: 0 | D65: 0 | E65: 0 | F65: 0 | G65: 0 | H65: 0 | I65: 0 | J65: 0 | K65: 0 | L65: 0 | M65: 0
A66: On-demand unit price | B66: 0.42527698 | C66: 0.42442643 | D66: 0.42357758 | E66: 0.42273042 | F66: 0.42188496 | G66: 0.42104119 | H66: 0.42019911 | I66: 0.41935871 | J66: 0.41851999 | K66: 0.41768295 | L66: 0.41684759 | M66: 0.41601389
A67: Commitment discount | B67: 0 | C67: 0 | D67: 0 | E67: 0 | F67: 0 | G67: 0 | H67: 0 | I67: 0 | J67: 0 | K67: 0 | L67: 0 | M67: 0
A68: Committed cost | B68: =MIN(B64,B65)*B66*(1-B67) | C68: =MIN(C64,C65)*C66*(1-C67) | D68: =MIN(D64,D65)*D66*(1-D67) | E68: =MIN(E64,E65)*E66*(1-E67) | F68: =MIN(F64,F65)*F66*(1-F67) | G68: =MIN(G64,G65)*G66*(1-G67) | H68: =MIN(H64,H65)*H66*(1-H67) | I68: =MIN(I64,I65)*I66*(1-I67) | ... M68: =MIN(M64,M65)*M66*(1-M67)
A69: On-demand cost | B69: =MAX(B64-B65,0)*B66 | C69: =MAX(C64-C65,0)*C66 | D69: =MAX(D64-D65,0)*D66 | E69: =MAX(E64-E65,0)*E66 | F69: =MAX(F64-F65,0)*F66 | G69: =MAX(G64-G65,0)*G66 | H69: =MAX(H64-H65,0)*H66 | I69: =MAX(I64-I65,0)*I66 | ... M69: =MAX(M64-M65,0)*M66
A70: Fixed cloud cost | B70: 28000 | C70: 28000 | D70: 28000 | E70: 28000 | F70: 28000 | G70: 28000 | H70: 28000 | I70: 28000 | J70: 28000 | K70: 28000 | L70: 28000 | M70: 28000
A71: Cloud hosting total | B71: =B68+B69+B70 | C71: =C68+C69+C70 | D71: =D68+D69+D70 | E71: =E68+E69+E70 | F71: =F68+F69+F70 | G71: =G68+G69+G70 | H71: =H68+H69+H70 | I71: =I68+I69+I70 | ... M71: =M68+M69+M70
A72: Shaded yellow: values from the model. Shaded blue: Excel formulas.
A74: Budget FY2026: cash
A75: USD, monthly | B75: 2026-01 | C75: 2026-02 | D75: 2026-03 | E75: 2026-04 | F75: 2026-05 | G75: 2026-06 | H75: 2026-07 | I75: 2026-08 | J75: 2026-09 | K75: 2026-10 | L75: 2026-11 | M75: 2026-12
A76: Opening cash | B76: =6372292.646893708 | C76: =B83 | D76: =C83 | E76: =D83 | F76: =E83 | G76: =F83 | H76: =G83 | I76: =H83 | J76: =I83 | ... M76: =L83
A77: EBITDA | B77: -938221.91 | C77: -1040903.9 | D77: -1082646.6 | E77: -952599.47 | F77: -923672.85 | G77: -917124.61 | H77: -739490.8 | I77: -692418.59 | J77: -739803.89 | K77: -682222.38 | L77: -600652.63 | M77: -639576.06
A78: Equipment capex | B78: -17500 | C78: -24500 | D78: -14000 | E78: -3500 | F78: 0 | G78: 0 | H78: 0 | I78: 0 | J78: 0 | K78: 0 | L78: 0 | M78: 0
A79: Change in receivables | B79: -183308 | C79: -78868.099 | D79: -93714.179 | E79: -85097.961 | F79: -92464.523 | G79: -101452 | H79: -80769.888 | I79: -81219.371 | J79: -98779.913 | K79: -99345.942 | L79: -95616.345 | M79: -113438.41
A80: Change in deferred revenue | B80: 268851.74 | C80: 115673.21 | D80: 137447.46 | E80: 124810.34 | F80: 135614.63 | G80: 148796.27 | H80: 118462.5 | I80: 119121.74 | J80: 144877.21 | K80: 145707.38 | L80: 140237.31 | M80: 166376.34
A81: Financing | B81: 0 | C81: 0 | D81: 0 | E81: 0 | F81: 0 | G81: 0 | H81: 0 | I81: 0 | J81: 0 | K81: 0 | L81: 0 | M81: 0
A82: Net cash flow | B82: =B77+B78+B79+B80+B81 | C82: =C77+C78+C79+C80+C81 | D82: =D77+D78+D79+D80+D81 | E82: =E77+E78+E79+E80+E81 | F82: =F77+F78+F79+F80+F81 | G82: =G77+G78+G79+G80+G81 | H82: =H77+H78+H79+H80+H81 | I82: =I77+I78+I79+I80+I81 | ... M82: =M77+M78+M79+M80+M81
A83: Closing cash | B83: =B76+B82 | C83: =C76+C82 | D83: =D76+D82 | E83: =E76+E82 | F83: =F76+F82 | G83: =G76+G82 | H83: =H76+H82 | I83: =I76+I82 | ... M83: =M76+M82
A84: Receivables | B84: 2607532 | C84: 2686400.1 | D84: 2780114.3 | E84: 2865212.3 | F84: 2957676.8 | G84: 3059128.8 | H84: 3139898.7 | I84: 3221118.1 | J84: 3319898 | K84: 3419243.9 | L84: 3514860.3 | M84: 3628298.7
A85: Deferred revenue | B85: 3824380.3 | C85: 3940053.5 | D85: 4077501 | E85: 4202311.4 | F85: 4337926 | G85: 4486722.3 | H85: 4605184.8 | I85: 4724306.5 | J85: 4869183.7 | K85: 5014891.1 | L85: 5155128.4 | M85: 5321504.7
A86: Net burn, trailing 3 months | B86: 870178.18 | C86: 949388.46 | D86: 983896.76 | E86: 999299.73 | F86: 949941.06 | G86: 888896.72 | H86: 817367.09 | I86: 742031.58 | J86: 683340.33 | K86: 661361.25 | L86: 628533.07 | M86: 592843.58
A87: Runway (months) | B87: 6.3229746 | C87: 4.7119972 | D87: 3.4765867 | E87: 2.5059701 | F87: 1.7092561 | G87: 0.84814374 | H87: 0.063758389 | I87: -0.81182826 | J87: -1.8967252 | K87: -2.9212019 | L87: -3.9584256 | M87: -5.1862576
A88: Shaded yellow: values from the model. Shaded blue: Excel formulas.

Sheet Bridge YTD
A1: January to August 2026, actual versus budget. impact = effect on EBITDA (favorable positive). Components sum to the EBITDA variance.
A3: line_label | B3: component | C3: budget | D3: actual | E3: impact | F3: material
A4: Platform revenue | B4: volume | C4: 14329759 | D4: 13868284 | E4: -560502.28 | F4: TRUE
A5: Platform revenue | B5: price | C5: 14329759 | D5: 13868284 | E5: 99027.443 | F5: FALSE
A6: Insights revenue | B6: volume | C6: 1214961.9 | D6: 1144051.7 | E6: -70910.158 | F6: TRUE
A7: Insights revenue | B7: price | C7: 1214961.9 | D7: 1144051.7 | E7: 1.1340982e-10 | F7: FALSE
A8: Cloud hosting | B8: usage | C8: 1234188.2 | D8: 1338077.3 | E8: -103889.09 | F8: TRUE
A9: Cloud hosting | B9: rate | C9: 1234188.2 | D9: 1338077.3 | E9: -7.7886588e-11 | F9: FALSE
A10: Cloud hosting | B10: fixed | C10: 1234188.2 | D10: 1338077.3 | E10: 0 | F10: FALSE
A11: Customer operations payroll | B11: headcount | C11: 2269988.8 | D11: 2246332.3 | E11: 16771.977 | F11: FALSE
A12: Customer operations payroll | B12: rate | C12: 2269988.8 | D12: 2246332.3 | E12: 6884.4833 | F12: FALSE
A13: R&D payroll | B13: headcount | C13: 7494856.9 | D13: 7123324.8 | E13: 410908.1 | F13: TRUE
A14: R&D payroll | B14: rate | C14: 7494856.9 | D14: 7123324.8 | E14: -39376.046 | F14: FALSE
A15: Sales and marketing payroll | B15: headcount | C15: 2776935.9 | D15: 2556186.4 | E15: 187083.45 | F15: TRUE
... A32: Fixed G&A | B32: spend | C32: 600000 | D32: 600000 | E32: 0 | F32: FALSE

Sheet Plan base
A1: Plan base: P&L
A2: USD, monthly | B2: 2026-09 | C2: 2026-10 | D2: 2026-11 | E2: 2026-12 | F2: 2027-01 | G2: 2027-02 | H2: 2027-03 | I2: 2027-04 | J2: 2027-05 | K2: 2027-06 | L2: 2027-07 | M2: 2027-08 | N2: 2027-09 | O2: 2027-10 | P2: 2027-11 | Q2: 2027-12 | R2: 2028-01 | S2: 2028-02
A3: Platform revenue | B3: 1896810.2 | C3: 1938531.1 | D3: 1978974.7 | E3: 2028358.5 | F3: 2169336.7 | G3: 2213218 | H3: 2265667 | I3: 2312379.4 | J3: 2363785.4 | K3: 2421151.5 | L3: 2466113.2 | M3: 2511708 | N3: 2568031.1 | O3: 2624354.2 | P3: 2677995.3 | Q3: 2742364.5 | R3: 2930173.5 | S3: 2983680.4
A4: Insights revenue | B4: 174264.46 | C4: 182865.14 | D4: 191583.63 | E4: 201560.34 | F4: 210490.55 | G4: 220156.57 | H4: 231101.58 | I4: 242874.19 | J4: 255595.04 | K4: 269489.52 | L4: 282165.2 | M4: 295289.61 | N4: 310324.12 | O4: 325820.1 | P4: 341374.79 | Q4: 359072.68 | R4: 374707.05 | S4: 391212.27
A5: Revenue | B5: =B3+B4 | C5: =C3+C4 | D5: =D3+D4 | E5: =E3+E4 | F5: =F3+F4 | G5: =G3+G4 | H5: =H3+H4 | I5: =I3+I4 | ... S5: =S3+S4
A6: Cloud hosting | B6: 150990.8 | C6: 154738.82 | D6: 158423.03 | E6: 162807.69 | F6: 166339.77 | G6: 171538.51 | H6: 177682.32 | I6: 184045.32 | J6: 190948.11 | K6: 198540.35 | L6: 204896.54 | M6: 211369.16 | N6: 219062.92 | O6: 226828 | P6: 234360.44 | Q6: 243179.31 | R6: 250217.82 | S6: 257616.99
A7: Third-party software and data | B7: 62132.241 | C7: 63641.886 | D7: 65116.749 | E7: 66897.565 | F7: 71394.817 | G7: 73001.238 | H7: 74903.059 | I7: 76657.609 | J7: 78581.414 | K7: 80719.232 | L7: 82448.351 | M7: 84209.93 | N7: 86350.658 | O7: 88505.23 | P7: 90581.101 | Q7: 93043.115 | R7: 99146.417 | S7: 101246.78
A8: Payment processing | B8: 31066.121 | C8: 31820.943 | D8: 32558.375 | E8: 33448.783 | F8: 35697.408 | G8: 36500.619 | H8: 37451.529 | I8: 38328.805 | J8: 39290.707 | K8: 40359.616 | L8: 41224.175 | M8: 42104.965 | N8: 43175.329 | O8: 44252.615 | P8: 45290.551 | Q8: 46521.558 | R8: 49573.208 | S8: 50623.39
A9: Customer operations payroll | B9: 276901.48 | C9: 276901.48 | D9: 276901.48 | E9: 276901.48 | F9: 286593.03 | G9: 286593.03 | H9: 286593.03 | I9: 286593.03 | J9: 286593.03 | K9: 286593.03 | L9: 286593.03 | M9: 286593.03 | N9: 286593.03 | O9: 286593.03 | P9: 286593.03 | Q9: 296234.76 | R9: 306602.98 | S9: 306602.98
A10: Customer operations recruiting | B10: 0 | C10: 0 | D10: 0 | E10: 0 | F10: 0 | G10: 0 | H10: 0 | I10: 0 | J10: 0 | K10: 0 | L10: 0 | M10: 0 | N10: 0 | O10: 0 | P10: 0 | Q10: 13500 | R10: 0 | S10: 0
A11: Cost of revenue | B11: =B6+B7+B8+B9+B10 | C11: =C6+C7+C8+C9+C10 | D11: =D6+D7+D8+D9+D10 | E11: =E6+E7+E8+E9+E10 | F11: =F6+F7+F8+F9+F10 | G11: =G6+G7+G8+G9+G10 | H11: =H6+H7+H8+H9+H10 | I11: =I6+I7+I8+I9+I10 | ... S11: =S6+S7+S8+S9+S10
A12: Gross profit | B12: =B5-B11 | C12: =C5-C11 | D12: =D5-D11 | E12: =E5-E11 | F12: =F5-F11 | G12: =G5-G11 | H12: =H5-H11 | I12: =I5-I11 | ... S12: =S5-S11
A13: Gross margin | B13: =IF(B5=0,0,B12/B5) | C13: =IF(C5=0,0,C12/C5) | D13: =IF(D5=0,0,D12/D5) | E13: =IF(E5=0,0,E12/E5) | F13: =IF(F5=0,0,F12/F5) | G13: =IF(G5=0,0,G12/G5) | H13: =IF(H5=0,0,H12/H5) | I13: =IF(I5=0,0,I12/I5) | ... S13: =IF(S5=0,0,S12/S5)
A14: R&D payroll | B14: 917162.28 | C14: 942862.78 | D14: 983087.54 | E14: 983087.54 | F14: 1054404 | G14: 1067983.4 | H14: 1087515.8 | I14: 1087515.8 | J14: 1108208.2 | K14: 1108208.2 | L14: 1108208.2 | M14: 1108208.2 | N14: 1108208.2 | O14: 1108208.2 | P14: 1108208.2 | Q14: 1108208.2 | R14: 1146995.4 | S14: 1146995.4
A15: R&D recruiting | B15: 0 | C15: 37500 | D15: 52500 | E15: 0 | F15: 46500 | G15: 15750 | H15: 28500 | I15: 0 | J15: 24000 | K15: 0 | L15: 0 | M15: 0 | N15: 0 | O15: 0 | P15: 0 | Q15: 0 | R15: 0 | S15: 0
A16: R&D tooling | B16: 31752 | C16: 32634 | D16: 34398 | E16: 34398 | F16: 35721 | G16: 36162 | H16: 37044 | I16: 37044 | J16: 37926 | K16: 37926 | L16: 37926 | M16: 37926 | N16: 37926 | O16: 37926 | P16: 37926 | Q16: 37926 | R16: 37926 | S16: 37926
A17: R&D contractors | B17: 60000 | C17: 60000 | D17: 60000 | E17: 60000 | F17: 60000 | G17: 60000 | H17: 60000 | I17: 60000 | J17: 60000 | K17: 60000 | L17: 60000 | M17: 60000 | N17: 60000 | O17: 60000 | P17: 60000 | Q17: 60000 | R17: 60000 | S17: 60000
A18: R&D total | B18: =B14+B15+B16+B17 | C18: =C14+C15+C16+C17 | D18: =D14+D15+D16+D17 | E18: =E14+E15+E16+E17 | F18: =F14+F15+F16+F17 | G18: =G14+G15+G16+G17 | H18: =H14+H15+H16+H17 | I18: =I14+I15+I16+I17 | ... S18: =S14+S15+S16+S17
A19: Sales and marketing payroll | B19: 313737.72 | C19: 324742.3 | D19: 324742.3 | E19: 324742.3 | F19: 371122.87 | G19: 383978.51 | H19: 383978.51 | I19: 394983.09 | J19: 394983.09 | K19: 394983.09 | L19: 394983.09 | M19: 394983.09 | N19: 394983.09 | O19: 394983.09 | P19: 394983.09 | Q19: 394983.09 | R19: 408807.5 | S19: 408807.5
A20: Sales and marketing recruiting | B20: 0 | C20: 16500 | D20: 0 | E20: 0 | F20: 52500 | G20: 18000 | H20: 0 | I20: 16500 | J20: 0 | K20: 0 | L20: 0 | M20: 0 | N20: 0 | O20: 0 | P20: 0 | Q20: 0 | R20: 0 | S20: 0
A21: Sales commission | B21: 69524.73 | C21: 69962.379 | D21: 68867.426 | E21: 80019.884 | F21: 68749.661 | G21: 75413.813 | H21: 86155.324 | I21: 79821.577 | J21: 85943.896 | K21: 93635.279 | L21: 79351.659 | M21: 80583.218 | N21: 93935.354 | O21: 94526.179 | P21: 91898.542 | Q21: 105335.08 | R21: 89596.154 | S21: 94945.643
A22: Marketing programmes | B22: 396900 | C22: 396900 | D22: 384750 | E22: 469800 | F22: 358425 | G22: 397575 | H22: 475200 | I22: 423225 | J22: 465750 | K22: 519750 | L22: 407362.5 | M22: 413100 | N22: 510300 | O22: 510300 | P22: 486000 | Q22: 583200 | R22: 437400 | S22: 461700
A23: Sales and marketing total | B23: =B19+B20+B21+B22 | C23: =C19+C20+C21+C22 | D23: =D19+D20+D21+D22 | E23: =E19+E20+E21+E22 | F23: =F19+F20+F21+F22 | G23: =G19+G20+G21+G22 | H23: =H19+H20+H21+H22 | I23: =I19+I20+I21+I22 | ... S23: =S19+S20+S21+S22
A24: G&A payroll | B24: 247823.66 | C24: 247823.66 | D24: 247823.66 | E24: 247823.66 | F24: 265749.67 | G24: 265749.67 | H24: 265749.67 | I24: 265749.67 | J24: 265749.67 | K24: 265749.67 | L24: 265749.67 | M24: 265749.67 | N24: 265749.67 | O24: 265749.67 | P24: 265749.67 | Q24: 265749.67 | R24: 275050.91 | S24: 275050.91
A25: G&A recruiting | B25: 0 | C25: 0 | D25: 0 | E25: 0 | F25: 13500 | G25: 0 | H25: 0 | I25: 0 | J25: 0 | K25: 0 | L25: 0 | M25: 0 | N25: 0 | O25: 0 | P25: 0 | Q25: 0 | R25: 0 | S25: 0
A26: Rent | B26: 68600 | C26: 69972 | D26: 72030 | E26: 72030 | F26: 76048 | G26: 77126 | H26: 78008 | I26: 78498 | J26: 79674 | K26: 79674 | L26: 79674 | M26: 79674 | N26: 79674 | O26: 79674 | P26: 79674 | Q26: 80164 | R26: 80164 | S26: 80164
A27: Software seats | B27: 25048.8 | C27: 25578 | D27: 26283.6 | E27: 26283.6 | F27: 27694.8 | G27: 28047.6 | H27: 28400.4 | I27: 28576.8 | J27: 28929.6 | K27: 28929.6 | L27: 28929.6 | M27: 28929.6 | N27: 28929.6 | O27: 28929.6 | P27: 28929.6 | Q27: 29106 | R27: 29106 | S27: 29106
A28: Fixed G&A | B28: 75000 | C28: 75000 | D28: 75000 | E28: 75000 | F28: 75000 | G28: 75000 | H28: 75000 | I28: 75000 | J28: 75000 | K28: 75000 | L28: 75000 | M28: 75000 | N28: 75000 | O28: 75000 | P28: 75000 | Q28: 75000 | R28: 75000 | S28: 75000
A29: G&A total | B29: =B24+B25+B26+B27+B28 | C29: =C24+C25+C26+C27+C28 | D29: =D24+D25+D26+D27+D28 | E29: =E24+E25+E26+E27+E28 | F29: =F24+F25+F26+F27+F28 | G29: =G24+G25+G26+G27+G28 | H29: =H24+H25+H26+H27+H28 | I29: =I24+I25+I26+I27+I28 | ... S29: =S24+S25+S26+S27+S28
A30: Operating expenses | B30: =B18+B23+B29 | C30: =C18+C23+C29 | D30: =D18+D23+D29 | E30: =E18+E23+E29 | F30: =F18+F23+F29 | G30: =G18+G23+G29 | H30: =H18+H23+H29 | I30: =I18+I23+I29 | ... S30: =S18+S23+S29
A31: EBITDA | B31: =B12-B30 | C31: =C12-C30 | D31: =D12-D30 | E31: =E12-E30 | F31: =F12-F30 | G31: =G12-G30 | H31: =H12-H30 | I31: =I12-I30 | ... S31: =S12-S30
A32: EBITDA margin | B32: =IF(B5=0,0,B31/B5) | C32: =IF(C5=0,0,C31/C5) | D32: =IF(D5=0,0,D31/D5) | E32: =IF(E5=0,0,E31/E5) | F32: =IF(F5=0,0,F31/F5) | G32: =IF(G5=0,0,G31/G5) | H32: =IF(H5=0,0,H31/H5) | I32: =IF(I5=0,0,I31/I5) | ... S32: =IF(S5=0,0,S31/S5)
A33: FTE total | B33: 139.16 | C33: 142.1 | D33: 146.02 | E33: 146.02 | F33: 153.86 | G33: 155.82 | H33: 157.78 | I33: 158.76 | J33: 160.72 | K33: 160.72 | L33: 160.72 | M33: 160.72 | N33: 160.72 | O33: 160.72 | P33: 160.72 | Q33: 161.7 | R33: 161.7 | S33: 161.7
A34: FTE customer operations | B34: 26.46 | C34: 26.46 | D34: 26.46 | E34: 26.46 | F34: 26.46 | G34: 26.46 | H34: 26.46 | I34: 26.46 | J34: 26.46 | K34: 26.46 | L34: 26.46 | M34: 26.46 | N34: 26.46 | O34: 26.46 | P34: 26.46 | Q34: 27.44 | R34: 27.44 | S34: 27.44
A35: FTE R&D | B35: 70.56 | C35: 72.52 | D35: 76.44 | E35: 76.44 | F35: 79.38 | G35: 80.36 | H35: 82.32 | I35: 82.32 | J35: 84.28 | K35: 84.28 | L35: 84.28 | M35: 84.28 | N35: 84.28 | O35: 84.28 | P35: 84.28 | Q35: 84.28 | R35: 84.28 | S35: 84.28
A36: FTE sales and marketing | B36: 27.44 | C36: 28.42 | D36: 28.42 | E36: 28.42 | F36: 32.34 | G36: 33.32 | H36: 33.32 | I36: 34.3 | J36: 34.3 | K36: 34.3 | L36: 34.3 | M36: 34.3 | N36: 34.3 | O36: 34.3 | P36: 34.3 | Q36: 34.3 | R36: 34.3 | S36: 34.3
A37: FTE G&A | B37: 14.7 | C37: 14.7 | D37: 14.7 | E37: 14.7 | F37: 15.68 | G37: 15.68 | H37: 15.68 | I37: 15.68 | J37: 15.68 | K37: 15.68 | L37: 15.68 | M37: 15.68 | N37: 15.68 | O37: 15.68 | P37: 15.68 | Q37: 15.68 | R37: 15.68 | S37: 15.68
A38: Total ARR (closing) | B38: 24852896 | C38: 25456754 | D38: 26046700 | E38: 26759026 | F38: 28557927 | G38: 29200495 | H38: 29961224 | I38: 30663044 | J38: 31432566 | K38: 32287693 | L38: 32979340 | M38: 33683972 | N38: 34540263 | O38: 35402092 | P38: 36232441 | Q38: 37217246 | R38: 39658567 | S38: 40498712
A39: Shaded yellow: values from the model. Shaded blue: Excel formulas.
A41: Plan base: ARR roll-forward
A42: USD, monthly | B42: 2026-09 | C42: 2026-10 | D42: 2026-11 | E42: 2026-12 | F42: 2027-01 | G42: 2027-02 | H42: 2027-03 | I42: 2027-04 | J42: 2027-05 | K42: 2027-06 | L42: 2027-07 | M42: 2027-08 | N42: 2027-09 | O42: 2027-10 | P42: 2027-11 | Q42: 2027-12 | R42: 2028-01 | S42: 2028-02
A43: Opening Platform ARR | B43: 22261073 | C43: 22761723 | D43: 23262373 | E43: 23747696 | F43: 24340302 | G43: 26032040 | H43: 26558616 | I43: 27188005 | J43: 27748553 | K43: 28365425 | L43: 29053819 | M43: 29593358 | N43: 30140497 | O43: 30816374 | P43: 31492251 | Q43: 32135943 | R43: 32908374 | S43: 35162082
A44: New ARR | B44: 500649.66 | C44: 500649.66 | D44: 485323.65 | E44: 592605.72 | F44: 474723.16 | G44: 526576.16 | H44: 629388.14 | I44: 560548.82 | J44: 616871.9 | K44: 688393.28 | L44: 539539.41 | M44: 547138.56 | N44: 675877.04 | O44: 675877.04 | P44: 643692.42 | Q44: 772430.9 | R44: 608289.34 | S44: 642083.19
A45: Expansion ARR | B45: 194597.64 | C45: 198974.13 | D45: 203350.61 | E45: 207593.12 | F45: 212773.45 | G45: 227561.97 | H45: 232165.09 | I45: 237666.96 | J45: 242567.06 | K45: 247959.51 | L45: 253977.18 | M45: 258693.62 | N45: 263476.49 | O45: 269384.75 | P45: 275293 | Q45: 280919.91 | R45: 287672.2 | S45: 307373.24
A46: Price ARR | B46: 0 | C46: 0 | D46: 0 | E46: 0 | F46: 1217015.1 | G46: 0 | H46: 0 | I46: 0 | J46: 0 | K46: 0 | L46: 0 | M46: 0 | N46: 0 | O46: 0 | P46: 0 | Q46: 0 | R46: 1645418.7 | S46: 0
A47: Churned ARR | B47: -194597.64 | C47: -198974.13 | D47: -203350.61 | E47: -207593.12 | F47: -212773.45 | G47: -227561.97 | H47: -232165.09 | I47: -237666.96 | J47: -242567.06 | K47: -247959.51 | L47: -253977.18 | M47: -258693.62 | N47: -263476.49 | O47: -269384.75 | P47: -275293 | Q47: -280919.91 | R47: -287672.2 | S47: -307373.24
A48: Closing Platform ARR | B48: =B43+B44+B45+B46+B47 | C48: =C43+C44+C45+C46+C47 | D48: =D43+D44+D45+D46+D47 | E48: =E43+E44+E45+E46+E47 | F48: =F43+F44+F45+F46+F47 | G48: =G43+G44+G45+G46+G47 | H48: =H43+H44+H45+H46+H47 | I48: =I43+I44+I45+I46+I47 | ... S48: =S43+S44+S45+S46+S47
A49: Opening customers | B49: 532.62451 | C49: 541.19852 | D49: 549.69757 | E49: 557.71733 | F49: 568.50198 | G49: 575.47986 | H49: 583.70174 | I49: 594.43924 | J49: 603.35039 | K49: 613.60113 | L49: 625.56227 | M49: 633.6726 | N49: 641.90328 | O49: 653.30201 | P49: 664.6011 | Q49: 674.99141 | R49: 688.5309 | S49: 697.09203
A50: New logos | B50: 13.23 | C50: 13.23 | D50: 12.825 | E50: 15.66 | F50: 11.9475 | G50: 13.2525 | H50: 15.84 | I50: 14.1075 | J50: 15.525 | K50: 17.325 | L50: 13.57875 | M50: 13.77 | N50: 17.01 | O50: 17.01 | P50: 16.2 | Q50: 19.44 | R50: 14.58 | S50: 15.39
A51: Churned customers | B51: -4.6559963 | C51: -4.7309469 | D51: -4.8052423 | E51: -4.8753479 | F51: -4.9696231 | G51: -5.030621 | H51: -5.1024935 | I51: -5.1963566 | J51: -5.2742543 | K51: -5.3638624 | L51: -5.468422 | M51: -5.5393193 | N51: -5.6112687 | O51: -5.710912 | P51: -5.8096842 | Q51: -5.9005123 | R51: -6.0188693 | S51: -6.0937073
A52: Closing customers | B52: =B49+B50+B51 | C52: =C49+C50+C51 | D52: =D49+D50+D51 | E52: =E49+E50+E51 | F52: =F49+F50+F51 | G52: =G49+G50+G51 | H52: =H49+H50+H51 | I52: =I49+I50+I51 | ... S52: =S49+S50+S51
A53: Insights attach rate | B53: 0.262 | C53: 0.268 | D53: 0.274 | E53: 0.28 | F53: 0.286 | G53: 0.292 | H53: 0.298 | I53: 0.3055 | J53: 0.313 | K53: 0.3205 | L53: 0.328 | M53: 0.3355 | N53: 0.343 | O53: 0.3505 | P53: 0.358 | Q53: 0.3655 | R53: 0.373 | S53: 0.3805
A54: Insights customers | B54: 141.79401 | C54: 147.31895 | D54: 152.81455 | E54: 159.18055 | F54: 164.58724 | G54: 170.44091 | H54: 177.14289 | I54: 184.32354 | J54: 192.05715 | K54: 200.49271 | L54: 207.84461 | M54: 215.35855 | N54: 224.08259 | O54: 232.94268 | P54: 241.64693 | Q54: 251.65804 | R54: 260.01533 | S54: 268.78076
A55: Insights ARR per customer | B55: 14747.968 | C55: 14895.448 | D55: 15044.402 | E55: 15194.846 | F55: 15346.795 | G55: 15500.263 | H55: 15655.265 | I55: 15811.818 | J55: 15969.936 | K55: 16129.635 | L55: 16290.932 | M55: 16453.841 | N55: 16618.379 | O55: 16784.563 | P55: 16952.409 | Q55: 17121.933 | R55: 17293.152 | S55: 17466.084
A56: Insights ARR | B56: 2091173.5 | C56: 2194381.7 | D56: 2299003.5 | E56: 2418724 | F56: 2525886.5 | G56: 2641878.8 | H56: 2773219 | I56: 2914490.3 | J56: 3067140.5 | K56: 3233874.3 | L56: 3385982.4 | M56: 3543475.3 | N56: 3723889.5 | O56: 3909841.2 | P56: 4096497.5 | Q56: 4308872.2 | R56: 4496484.7 | S56: 4694547.2
A57: Total ARR | B57: =B48+B56 | C57: =C48+C56 | D57: =D48+D56 | E57: =E48+E56 | F57: =F48+F56 | G57: =G48+G56 | H57: =H48+H56 | I57: =I48+I56 | ... S57: =S48+S56
A58: Shaded yellow: values from the model. Shaded blue: Excel formulas.
A60: Plan base: cloud hosting
A61: USD, monthly | B61: 2026-09 | C61: 2026-10 | D61: 2026-11 | E61: 2026-12 | F61: 2027-01 | G61: 2027-02 | H61: 2027-03 | I61: 2027-04 | J61: 2027-05 | K61: 2027-06 | L61: 2027-07 | M61: 2027-08 | N61: 2027-09 | O61: 2027-10 | P61: 2027-11 | Q61: 2027-12 | R61: 2028-01 | S61: 2028-02
A62: Platform compute units | B62: 108239.7 | C62: 109939.51 | D62: 111543.47 | E62: 113700.4 | F62: 115095.97 | G62: 116740.35 | H62: 118887.85 | I62: 120670.08 | J62: 122720.23 | K62: 125112.45 | L62: 126734.52 | M62: 128380.66 | N62: 130660.4 | O62: 132920.22 | P62: 134998.28 | Q62: 137706.18 | R62: 139418.41 | S62: 141277.66
A63: Insights compute units | B63: 283588.02 | C63: 294637.9 | D63: 305629.1 | E63: 318361.11 | F63: 329174.48 | G63: 340881.81 | H63: 354285.79 | I63: 368647.09 | J63: 384114.31 | K63: 400985.41 | L63: 415689.22 | M63: 430717.1 | N63: 448165.18 | O63: 465885.37 | P63: 483293.85 | Q63: 503316.09 | R63: 520030.66 | S63: 537561.51
A64: Total units | B64: =B62+B63 | C64: =C62+C63 | D64: =D62+D63 | E64: =E62+E63 | F64: =F62+F63 | G64: =G62+G63 | H64: =H62+H63 | I64: =I62+I63 | ... S64: =S62+S63
A65: Committed units | B65: 444819.65 | C65: 444819.65 | D65: 444819.65 | E65: 444819.65 | F65: 444819.65 | G65: 444819.65 | H65: 444819.65 | I65: 444819.65 | J65: 444819.65 | K65: 444819.65 | L65: 444819.65 | M65: 444819.65 | N65: 444819.65 | O65: 444819.65 | P65: 444819.65 | Q65: 444819.65 | R65: 444819.65 | S65: 444819.65
A66: On-demand unit price | B66: 0.41851999 | C66: 0.41768295 | D66: 0.41684759 | E66: 0.41601389 | F66: 0.41518186 | G66: 0.4143515 | H66: 0.4135228 | I66: 0.41269575 | J66: 0.41187036 | K66: 0.41104662 | L66: 0.41022453 | M66: 0.40940408 | N66: 0.40858527 | O66: 0.4077681 | P66: 0.40695256 | Q66: 0.40613866 | R66: 0.40532638 | S66: 0.40451573
A67: Commitment discount | B67: 0.25 | C67: 0.25 | D67: 0.25 | E67: 0.25 | F67: 0.25 | G67: 0.25 | H67: 0.25 | I67: 0.25 | J67: 0.25 | K67: 0.25 | L67: 0.25 | M67: 0.25 | N67: 0.25 | O67: 0.25 | P67: 0.25 | Q67: 0.25 | R67: 0.25 | S67: 0.25
A68: Committed cost | B68: =MIN(B64,B65)*B66*(1-B67) | C68: =MIN(C64,C65)*C66*(1-C67) | D68: =MIN(D64,D65)*D66*(1-D67) | E68: =MIN(E64,E65)*E66*(1-E67) | F68: =MIN(F64,F65)*F66*(1-F67) | G68: =MIN(G64,G65)*G66*(1-G67) | H68: =MIN(H64,H65)*H66*(1-H67) | I68: =MIN(I64,I65)*I66*(1-I67) | ... S68: =MIN(S64,S65)*S66*(1-S67)
A69: On-demand cost | B69: =MAX(B64-B65,0)*B66 | C69: =MAX(C64-C65,0)*C66 | D69: =MAX(D64-D65,0)*D66 | E69: =MAX(E64-E65,0)*E66 | F69: =MAX(F64-F65,0)*F66 | G69: =MAX(G64-G65,0)*G66 | H69: =MAX(H64-H65,0)*H66 | I69: =MAX(I64-I65,0)*I66 | ... S69: =MAX(S64-S65,0)*S66
A70: Fixed cloud cost | B70: 28000 | C70: 28000 | D70: 28000 | E70: 28000 | F70: 28000 | G70: 28000 | H70: 28000 | I70: 28000 | J70: 28000 | K70: 28000 | L70: 28000 | M70: 28000 | N70: 28000 | O70: 28000 | P70: 28000 | Q70: 28000 | R70: 28000 | S70: 28000
A71: Cloud hosting total | B71: =B68+B69+B70 | C71: =C68+C69+C70 | D71: =D68+D69+D70 | E71: =E68+E69+E70 | F71: =F68+F69+F70 | G71: =G68+G69+G70 | H71: =H68+H69+H70 | I71: =I68+I69+I70 | ... S71: =S68+S69+S70
A72: Shaded yellow: values from the model. Shaded blue: Excel formulas.
A74: Plan base: cash
A75: USD, monthly | B75: 2026-09 | C75: 2026-10 | D75: 2026-11 | E75: 2026-12 | F75: 2027-01 | G75: 2027-02 | H75: 2027-03 | I75: 2027-04 | J75: 2027-05 | K75: 2027-06 | L75: 2027-07 | M75: 2027-08 | N75: 2027-09 | O75: 2027-10 | P75: 2027-11 | Q75: 2027-12 | R75: 2028-01 | S75: 2028-02
A76: Opening cash | B76: =24750279.18739851 | C76: =B83 | D76: =C83 | E76: =D83 | F76: =E83 | G76: =F83 | H76: =G83 | I76: =H83 | J76: =I83 | ... S76: =R83
A77: EBITDA | B77: -655565.14 | C77: -705182.06 | D77: -691923.85 | E77: -683321.67 | F77: -685612.84 | G77: -635044.79 | H77: -685413 | I77: -577285.05 | J77: -602197.21 | K77: -579426.96 | L77: -404068.42 | M77: -361433.17 | N77: -411532.56 | O77: -351301.26 | P77: -265824.15 | Q77: -330713.57 | R77: -40705.876 | S77: -10892.937
A78: Equipment capex | B78: 0 | C78: -10500 | D78: -14000 | E78: 0 | F78: -28000 | G78: -7000 | H78: -7000 | I78: -3500 | J78: -7000 | K78: 0 | L78: 0 | M78: 0 | N78: 0 | O78: 0 | P78: 0 | Q78: -3500 | R78: 0 | S78: 0
A79: Change in receivables | B79: -75102.517 | C79: -75482.226 | D79: -73743.184 | E79: -89040.781 | F79: -224862.6 | G79: -80321.052 | H79: -95091.04 | I79: -87727.514 | J79: -96190.26 | K79: -106890.89 | L79: -86455.941 | M79: -88078.94 | N79: -107036.4 | O79: -107728.6 | P79: -103793.59 | Q79: -123100.7 | R79: -305165.07 | S79: -105018.22
A80: Change in deferred revenue | B80: 110150.36 | C80: 110707.27 | D80: 108156.67 | E80: 130593.14 | F80: 329798.48 | G80: 117804.21 | H80: 139466.86 | I80: 128667.02 | J80: 141079.05 | K80: 156773.3 | L80: 126802.05 | M80: 129182.45 | N80: 156986.72 | O80: 158001.94 | P80: 152230.59 | Q80: 180547.69 | R80: 447575.43 | S80: 154026.72
A81: Financing | B81: 0 | C81: 0 | D81: 0 | E81: 0 | F81: 0 | G81: 0 | H81: 0 | I81: 0 | J81: 0 | K81: 0 | L81: 0 | M81: 0 | N81: 0 | O81: 0 | P81: 0 | Q81: 0 | R81: 0 | S81: 0
A82: Net cash flow | B82: =B77+B78+B79+B80+B81 | C82: =C77+C78+C79+C80+C81 | D82: =D77+D78+D79+D80+D81 | E82: =E77+E78+E79+E80+E81 | F82: =F77+F78+F79+F80+F81 | G82: =G77+G78+G79+G80+G81 | H82: =H77+H78+H79+H80+H81 | I82: =I77+I78+I79+I80+I81 | ... S82: =S77+S78+S79+S80+S81
A83: Closing cash | B83: =B76+B82 | C83: =C76+C82 | D83: =D76+D82 | E83: =E76+E82 | F83: =F76+F82 | G83: =G76+G82 | H83: =H76+H82 | I83: =I76+I82 | ... S83: =S76+S82
A84: Receivables | B84: 3106612.1 | C84: 3182094.3 | D84: 3255837.5 | E84: 3344878.3 | F84: 3569740.8 | G84: 3650061.9 | H84: 3745152.9 | I84: 3832880.5 | J84: 3929070.7 | K84: 4035961.6 | L84: 4122417.5 | M84: 4210496.5 | N84: 4317532.9 | O84: 4425261.5 | P84: 4529055.1 | Q84: 4652155.8 | R84: 4957320.8 | S84: 5062339
A85: Deferred revenue | B85: 4556364.4 | C85: 4667071.6 | D85: 4775228.3 | E85: 4905821.4 | F85: 5235619.9 | G85: 5353424.1 | H85: 5492891 | I85: 5621558 | J85: 5762637 | K85: 5919410.3 | L85: 6046212.4 | M85: 6175394.8 | N85: 6332381.6 | O85: 6490383.5 | P85: 6642614.1 | Q85: 6823161.8 | R85: 7270737.2 | S85: 7424763.9
A86: Net burn, trailing 3 months | B86: 620517.3 | C86: 650487.16 | D86: 657494.9 | E86: 664578.9 | F86: 640652.21 | G86: 618335.97 | H86: 620425.26 | I86: 597481.45 | J86: 584063.72 | K86: 544566.17 | L86: 485858.43 | M86: 404532.17 | N86: 348544.74 | O86: 327646.6 | P86: 293332.43 | Q86: 265060.55 | R86: 130816.41 | S86: 45648.843
A87: Runway (months) | B87: 38.886526 | C87: 36.048836 | D87: 34.643302 | E87: 33.308348 | F87: 33.602238 | G87: 33.837247 | H87: 32.678794 | I87: 33.030153 | J87: 32.822781 | K87: 34.231012 | L87: 37.61863 | M87: 44.389545 | N87: 50.48252 | O87: 52.783666 | P87: 58.21723 | Q87: 63.382632 | R87: 129.20351 | S87: 371.09495
A88: Shaded yellow: values from the model. Shaded blue: Excel formulas.

Sheet Plan upside
A1: Plan upside: P&L
A2: USD, monthly | B2: 2026-09 | C2: 2026-10 | D2: 2026-11 | E2: 2026-12 | F2: 2027-01 | G2: 2027-02 | H2: 2027-03 | I2: 2027-04 | J2: 2027-05 | K2: 2027-06 | L2: 2027-07 | M2: 2027-08 | N2: 2027-09 | O2: 2027-10 | P2: 2027-11 | Q2: 2027-12 | R2: 2028-01 | S2: 2028-02
A3: Platform revenue | B3: 1910656.7 | C3: 1966361 | D3: 2020641.7 | E3: 2085983.1 | F3: 2286418.9 | G3: 2346712.2 | H3: 2417825.2 | I3: 2481968.6 | J3: 2552116.1 | K3: 2629860 | L3: 2692345.7 | M3: 2755774.3 | N3: 2832721.4 | O3: 2909858.2 | P3: 2983844.7 | Q3: 3071375.7 | R3: 3358285 | S3: 3434479.8
A4: Insights revenue | B4: 178411.47 | C4: 191495.49 | D4: 205006.64 | E4: 220430.55 | F4: 234797.76 | G4: 250426.91 | H4: 268092.09 | I4: 286911.72 | J4: 307390.69 | K4: 329890.73 | L4: 351069.55 | M4: 373257.06 | N4: 398593.85 | O4: 425045.4 | P4: 452034.26 | Q4: 482680.01 | R4: 510724.23 | S4: 540545.67
A5: Revenue | B5: =B3+B4 | C5: =C3+C4 | D5: =D3+D4 | E5: =E3+E4 | F5: =F3+F4 | G5: =G3+G4 | H5: =H3+H4 | I5: =I3+I4 | ... S5: =S3+S4
A6: Cloud hosting | B6: 152780.36 | C6: 158372.26 | D6: 163929.89 | E6: 171801.63 | F6: 179213.64 | G6: 187250.38 | H6: 196475.54 | I6: 205868.64 | J6: 216015.71 | K6: 227119.08 | L6: 236682.28 | M6: 246447.38 | N6: 257864.41 | O6: 269437.4 | P6: 280762.91 | Q6: 293850.07 | R6: 304634.12 | S6: 315944.52
A7: Third-party software and data | B7: 62672.045 | C7: 64735.694 | D7: 66769.449 | E7: 69192.41 | F7: 75636.501 | G7: 77914.173 | H7: 80577.519 | I7: 83066.41 | J7: 85785.205 | K7: 88792.521 | L7: 91302.458 | M7: 93870.942 | N7: 96939.456 | O7: 100047.11 | P7: 103076.37 | Q7: 106621.67 | R7: 116070.28 | S7: 119250.76
A8: Payment processing | B8: 31336.022 | C8: 32367.847 | D8: 33384.725 | E8: 34596.205 | F8: 37818.25 | G8: 38957.086 | H8: 40288.759 | I8: 41533.205 | J8: 42892.602 | K8: 44396.261 | L8: 45651.229 | M8: 46935.471 | N8: 48469.728 | O8: 50023.554 | P8: 51538.185 | Q8: 53310.836 | R8: 58035.138 | S8: 59625.382
A9: Customer operations payroll | B9: 276901.48 | C9: 276901.48 | D9: 276901.48 | E9: 276901.48 | F9: 286593.03 | G9: 286593.03 | H9: 286593.03 | I9: 286593.03 | J9: 286593.03 | K9: 286593.03 | L9: 296234.76 | M9: 296234.76 | N9: 296234.76 | O9: 305876.49 | P9: 305876.49 | Q9: 305876.49 | R9: 326223.9 | S9: 326223.9
A10: Customer operations recruiting | B10: 0 | C10: 0 | D10: 0 | E10: 0 | F10: 0 | G10: 0 | H10: 0 | I10: 0 | J10: 0 | K10: 0 | L10: 13500 | M10: 0 | N10: 0 | O10: 13500 | P10: 0 | Q10: 0 | R10: 13500 | S10: 0
A11: Cost of revenue | B11: =B6+B7+B8+B9+B10 | C11: =C6+C7+C8+C9+C10 | D11: =D6+D7+D8+D9+D10 | E11: =E6+E7+E8+E9+E10 | F11: =F6+F7+F8+F9+F10 | G11: =G6+G7+G8+G9+G10 | H11: =H6+H7+H8+H9+H10 | I11: =I6+I7+I8+I9+I10 | ... S11: =S6+S7+S8+S9+S10
A12: Gross profit | B12: =B5-B11 | C12: =C5-C11 | D12: =D5-D11 | E12: =E5-E11 | F12: =F5-F11 | G12: =G5-G11 | H12: =H5-H11 | I12: =I5-I11 | ... S12: =S5-S11
A13: Gross margin | B13: =IF(B5=0,0,B12/B5) | C13: =IF(C5=0,0,C12/C5) | D13: =IF(D5=0,0,D12/D5) | E13: =IF(E5=0,0,E12/E5) | F13: =IF(F5=0,0,F12/F5) | G13: =IF(G5=0,0,G12/G5) | H13: =IF(H5=0,0,H12/H5) | I13: =IF(I5=0,0,I12/I5) | ... S13: =IF(S5=0,0,S12/S5)
A14: R&D payroll | B14: 917162.28 | C14: 942862.78 | D14: 983087.54 | E14: 983087.54 | F14: 1054404 | G14: 1067983.4 | H14: 1087515.8 | I14: 1087515.8 | J14: 1108208.2 | K14: 1108208.2 | L14: 1108208.2 | M14: 1108208.2 | N14: 1108208.2 | O14: 1108208.2 | P14: 1108208.2 | Q14: 1108208.2 | R14: 1146995.4 | S14: 1146995.4
A15: R&D recruiting | B15: 0 | C15: 37500 | D15: 52500 | E15: 0 | F15: 46500 | G15: 15750 | H15: 28500 | I15: 0 | J15: 24000 | K15: 0 | L15: 0 | M15: 0 | N15: 0 | O15: 0 | P15: 0 | Q15: 0 | R15: 0 | S15: 0
A16: R&D tooling | B16: 31752 | C16: 32634 | D16: 34398 | E16: 34398 | F16: 35721 | G16: 36162 | H16: 37044 | I16: 37044 | J16: 37926 | K16: 37926 | L16: 37926 | M16: 37926 | N16: 37926 | O16: 37926 | P16: 37926 | Q16: 37926 | R16: 37926 | S16: 37926
A17: R&D contractors | B17: 60000 | C17: 60000 | D17: 60000 | E17: 60000 | F17: 60000 | G17: 60000 | H17: 60000 | I17: 60000 | J17: 60000 | K17: 60000 | L17: 60000 | M17: 60000 | N17: 60000 | O17: 60000 | P17: 60000 | Q17: 60000 | R17: 60000 | S17: 60000
A18: R&D total | B18: =B14+B15+B16+B17 | C18: =C14+C15+C16+C17 | D18: =D14+D15+D16+D17 | E18: =E14+E15+E16+E17 | F18: =F14+F15+F16+F17 | G18: =G14+G15+G16+G17 | H18: =H14+H15+H16+H17 | I18: =I14+I15+I16+I17 | ... S18: =S14+S15+S16+S17
A19: Sales and marketing payroll | B19: 313737.72 | C19: 324742.3 | D19: 324742.3 | E19: 324742.3 | F19: 371122.87 | G19: 383978.51 | H19: 383978.51 | I19: 394983.09 | J19: 394983.09 | K19: 394983.09 | L19: 394983.09 | M19: 394983.09 | N19: 394983.09 | O19: 394983.09 | P19: 394983.09 | Q19: 394983.09 | R19: 408807.5 | S19: 408807.5
A20: Sales and marketing recruiting | B20: 0 | C20: 16500 | D20: 0 | E20: 0 | F20: 52500 | G20: 18000 | H20: 0 | I20: 16500 | J20: 0 | K20: 0 | L20: 0 | M20: 0 | N20: 0 | O20: 0 | P20: 0 | Q20: 0 | R20: 0 | S20: 0
A21: Sales commission | B21: 82095.114 | C21: 82721.289 | D21: 81475.83 | E21: 95199.76 | F21: 82633.386 | G21: 91350.359 | H21: 104835.05 | I21: 97062.451 | J21: 104800.32 | K21: 114498.81 | L21: 96835.097 | M21: 98485.712 | N21: 115234.89 | O21: 116101.99 | P21: 112962.62 | Q21: 129830.77 | R21: 111816.36 | S21: 119338.68
A22: Marketing programmes | B22: 452760 | C22: 452760 | D22: 438900 | E22: 535920 | F22: 408870 | G22: 453530 | H22: 542080 | I22: 482790 | J22: 531300 | K22: 592900 | L22: 464695 | M22: 471240 | N22: 582120 | O22: 582120 | P22: 554400 | Q22: 665280 | R22: 498960 | S22: 526680
A23: Sales and marketing total | B23: =B19+B20+B21+B22 | C23: =C19+C20+C21+C22 | D23: =D19+D20+D21+D22 | E23: =E19+E20+E21+E22 | F23: =F19+F20+F21+F22 | G23: =G19+G20+G21+G22 | H23: =H19+H20+H21+H22 | I23: =I19+I20+I21+I22 | ... S23: =S19+S20+S21+S22
A24: G&A payroll | B24: 247823.66 | C24: 247823.66 | D24: 247823.66 | E24: 247823.66 | F24: 265749.67 | G24: 265749.67 | H24: 265749.67 | I24: 265749.67 | J24: 265749.67 | K24: 265749.67 | L24: 265749.67 | M24: 265749.67 | N24: 265749.67 | O24: 265749.67 | P24: 265749.67 | Q24: 265749.67 | R24: 275050.91 | S24: 275050.91
A25: G&A recruiting | B25: 0 | C25: 0 | D25: 0 | E25: 0 | F25: 13500 | G25: 0 | H25: 0 | I25: 0 | J25: 0 | K25: 0 | L25: 0 | M25: 0 | N25: 0 | O25: 0 | P25: 0 | Q25: 0 | R25: 0 | S25: 0
A26: Rent | B26: 68600 | C26: 69972 | D26: 72030 | E26: 72030 | F26: 76048 | G26: 77126 | H26: 78008 | I26: 78498 | J26: 79674 | K26: 79674 | L26: 80164 | M26: 80164 | N26: 80164 | O26: 80654 | P26: 80654 | Q26: 80654 | R26: 81144 | S26: 81144
A27: Software seats | B27: 25048.8 | C27: 25578 | D27: 26283.6 | E27: 26283.6 | F27: 27694.8 | G27: 28047.6 | H27: 28400.4 | I27: 28576.8 | J27: 28929.6 | K27: 28929.6 | L27: 29106 | M27: 29106 | N27: 29106 | O27: 29282.4 | P27: 29282.4 | Q27: 29282.4 | R27: 29458.8 | S27: 29458.8
A28: Fixed G&A | B28: 75000 | C28: 75000 | D28: 75000 | E28: 75000 | F28: 75000 | G28: 75000 | H28: 75000 | I28: 75000 | J28: 75000 | K28: 75000 | L28: 75000 | M28: 75000 | N28: 75000 | O28: 75000 | P28: 75000 | Q28: 75000 | R28: 75000 | S28: 75000
A29: G&A total | B29: =B24+B25+B26+B27+B28 | C29: =C24+C25+C26+C27+C28 | D29: =D24+D25+D26+D27+D28 | E29: =E24+E25+E26+E27+E28 | F29: =F24+F25+F26+F27+F28 | G29: =G24+G25+G26+G27+G28 | H29: =H24+H25+H26+H27+H28 | I29: =I24+I25+I26+I27+I28 | ... S29: =S24+S25+S26+S27+S28
A30: Operating expenses | B30: =B18+B23+B29 | C30: =C18+C23+C29 | D30: =D18+D23+D29 | E30: =E18+E23+E29 | F30: =F18+F23+F29 | G30: =G18+G23+G29 | H30: =H18+H23+H29 | I30: =I18+I23+I29 | ... S30: =S18+S23+S29
A31: EBITDA | B31: =B12-B30 | C31: =C12-C30 | D31: =D12-D30 | E31: =E12-E30 | F31: =F12-F30 | G31: =G12-G30 | H31: =H12-H30 | I31: =I12-I30 | ... S31: =S12-S30
A32: EBITDA margin | B32: =IF(B5=0,0,B31/B5) | C32: =IF(C5=0,0,C31/C5) | D32: =IF(D5=0,0,D31/D5) | E32: =IF(E5=0,0,E31/E5) | F32: =IF(F5=0,0,F31/F5) | G32: =IF(G5=0,0,G31/G5) | H32: =IF(H5=0,0,H31/H5) | I32: =IF(I5=0,0,I31/I5) | ... S32: =IF(S5=0,0,S31/S5)
A33: FTE total | B33: 139.16 | C33: 142.1 | D33: 146.02 | E33: 146.02 | F33: 153.86 | G33: 155.82 | H33: 157.78 | I33: 158.76 | J33: 160.72 | K33: 160.72 | L33: 161.7 | M33: 161.7 | N33: 161.7 | O33: 162.68 | P33: 162.68 | Q33: 162.68 | R33: 163.66 | S33: 163.66
A34: FTE customer operations | B34: 26.46 | C34: 26.46 | D34: 26.46 | E34: 26.46 | F34: 26.46 | G34: 26.46 | H34: 26.46 | I34: 26.46 | J34: 26.46 | K34: 26.46 | L34: 27.44 | M34: 27.44 | N34: 27.44 | O34: 28.42 | P34: 28.42 | Q34: 28.42 | R34: 29.4 | S34: 29.4
A35: FTE R&D | B35: 70.56 | C35: 72.52 | D35: 76.44 | E35: 76.44 | F35: 79.38 | G35: 80.36 | H35: 82.32 | I35: 82.32 | J35: 84.28 | K35: 84.28 | L35: 84.28 | M35: 84.28 | N35: 84.28 | O35: 84.28 | P35: 84.28 | Q35: 84.28 | R35: 84.28 | S35: 84.28
A36: FTE sales and marketing | B36: 27.44 | C36: 28.42 | D36: 28.42 | E36: 28.42 | F36: 32.34 | G36: 33.32 | H36: 33.32 | I36: 34.3 | J36: 34.3 | K36: 34.3 | L36: 34.3 | M36: 34.3 | N36: 34.3 | O36: 34.3 | P36: 34.3 | Q36: 34.3 | R36: 34.3 | S36: 34.3
A37: FTE G&A | B37: 14.7 | C37: 14.7 | D37: 14.7 | E37: 14.7 | F37: 15.68 | G37: 15.68 | H37: 15.68 | I37: 15.68 | J37: 15.68 | K37: 15.68 | L37: 15.68 | M37: 15.68 | N37: 15.68 | O37: 15.68 | P37: 15.68 | Q37: 15.68 | R37: 15.68 | S37: 15.68
A38: Total ARR (closing) | B38: 25068818 | C38: 25894278 | D38: 26707780 | E38: 27676964 | F38: 30254600 | G38: 31165669 | H38: 32231007 | I38: 33226564 | J38: 34314082 | K38: 35517008 | L38: 36520983 | M38: 37548377 | N38: 38775783 | O38: 40018843 | P38: 41230548 | Q38: 42648669 | R38: 46428110 | S38: 47700306
A39: Shaded yellow: values from the model. Shaded blue: Excel formulas.
A41: Plan upside: ARR roll-forward
A42: USD, monthly | B42: 2026-09 | C42: 2026-10 | D42: 2026-11 | E42: 2026-12 | F42: 2027-01 | G42: 2027-02 | H42: 2027-03 | I42: 2027-04 | J42: 2027-05 | K42: 2027-06 | L42: 2027-07 | M42: 2027-08 | N42: 2027-09 | O42: 2027-10 | P42: 2027-11 | Q42: 2027-12 | R42: 2028-01 | S42: 2028-02
A43: Opening Platform ARR | B43: 22261073 | C43: 22927880 | D43: 23596332 | E43: 24247700 | F43: 25031797 | G43: 27437027 | H43: 28160546 | I43: 29013902 | J43: 29783624 | K43: 30625394 | L43: 31558320 | M43: 32308149 | N43: 33069292 | O43: 33992656 | P43: 34918298 | Q43: 35806137 | R43: 36856509 | S43: 40299420
A44: New ARR | B44: 611905.14 | C44: 611905.14 | D44: 593173.35 | E44: 724295.88 | F44: 591268.95 | G44: 655852 | H44: 783904.6 | I44: 698165.03 | J44: 768315.59 | K44: 857395.65 | L44: 671997.76 | M44: 681462.52 | N44: 841806.64 | O44: 841806.64 | P44: 801720.61 | Q44: 962064.73 | R44: 772056.95 | S44: 814949
A45: Expansion ARR | B45: 209046 | C45: 215307.75 | D45: 221584.95 | E45: 227701.72 | F45: 235064.91 | G45: 257651.59 | H45: 264445.9 | I45: 272459.47 | J45: 279687.66 | K45: 287592.43 | L45: 296353.21 | M45: 303394.6 | N45: 310542.23 | O45: 319213.22 | P45: 327905.6 | Q45: 336242.98 | R45: 346106.66 | S45: 378437.84
A46: Price ARR | B46: 0 | C46: 0 | D46: 0 | E46: 0 | F46: 1752225.8 | G46: 0 | H46: 0 | I46: 0 | J46: 0 | K46: 0 | L46: 0 | M46: 0 | N46: 0 | O46: 0 | P46: 0 | Q46: 0 | R46: 2579955.6 | S46: 0
A47: Churned ARR | B47: -154144.19 | C47: -158761.42 | D47: -163390.03 | E47: -167900.35 | F47: -173329.74 | G47: -189984.47 | H47: -194994.4 | I47: -200903.36 | J47: -206233.21 | K47: -212061.94 | L47: -218521.88 | M47: -223713.98 | N47: -228984.43 | O47: -235378.16 | P47: -241787.66 | Q47: -247935.39 | R47: -255208.57 | S47: -279048.6
A48: Closing Platform ARR | B48: =B43+B44+B45+B46+B47 | C48: =C43+C44+C45+C46+C47 | D48: =D43+D44+D45+D46+D47 | E48: =E43+E44+E45+E46+E47 | F48: =F43+F44+F45+F46+F47 | G48: =G43+G44+G45+G46+G47 | H48: =H43+H44+H45+H46+H47 | I48: =I43+I44+I45+I46+I47 | ... S48: =S43+S44+S45+S46+S47
A49: Opening customers | B49: 532.62451 | C49: 545.10642 | D49: 557.50189 | E49: 569.31654 | F49: 584.51437 | G49: 595.06947 | H49: 607.14648 | I49: 622.30237 | J49: 635.23581 | K49: 649.81219 | L49: 666.48764 | M49: 678.46888 | N49: 690.6009 | O49: 706.60891 | P49: 722.50608 | Q49: 737.30317 | R49: 755.9578 | S49: 768.54326
A50: New logos | B50: 16.17 | C50: 16.17 | D50: 15.675 | E50: 19.14 | F50: 14.6025 | G50: 16.1975 | H50: 19.36 | I50: 17.2425 | J50: 18.975 | K50: 21.175 | L50: 16.59625 | M50: 16.83 | N50: 20.79 | O50: 20.79 | P50: 19.8 | Q50: 23.76 | R50: 17.82 | S50: 18.81
A51: Churned customers | B51: -3.6880959 | C51: -3.7745254 | D51: -3.8603564 | E51: -3.9421655 | F51: -4.0474011 | G51: -4.1204887 | H51: -4.2041145 | I51: -4.3090597 | J51: -4.3986158 | K51: -4.4995482 | L51: -4.6150154 | M51: -4.6979781 | N51: -4.7819849 | O51: -4.8928305 | P51: -5.0029086 | Q51: -5.1053693 | R51: -5.2345411 | S51: -5.3216876
A52: Closing customers | B52: =B49+B50+B51 | C52: =C49+C50+C51 | D52: =D49+D50+D51 | E52: =E49+E50+E51 | F52: =F49+F50+F51 | G52: =G49+G50+G51 | H52: =H49+H50+H51 | I52: =I49+I50+I51 | ... S52: =S49+S50+S51
A53: Insights attach rate | B53: 0.265 | C53: 0.274 | D53: 0.283 | E53: 0.292 | F53: 0.301 | G53: 0.31 | H53: 0.319 | I53: 0.3295 | J53: 0.34 | K53: 0.3505 | L53: 0.361 | M53: 0.3715 | N53: 0.382 | O53: 0.3925 | P53: 0.403 | Q53: 0.4135 | R53: 0.424 | S53: 0.4345
A54: Insights customers | B54: 144.4532 | C54: 152.75552 | D54: 161.11658 | E54: 170.6782 | F54: 179.11591 | G54: 188.21541 | H54: 198.51445 | I54: 209.3102 | J54: 220.93614 | K54: 233.60392 | L54: 244.92726 | M54: 256.55823 | N54: 269.9246 | O54: 283.58364 | P54: 297.13318 | Q54: 312.58855 | R54: 325.86234 | S54: 339.79272
A55: Insights ARR per customer | B55: 14820.978 | C55: 15043.292 | D55: 15268.942 | E55: 15497.976 | F55: 15730.445 | G55: 15966.402 | H55: 16205.898 | I55: 16448.987 | J55: 16695.721 | K55: 16946.157 | L55: 17200.35 | M55: 17458.355 | N55: 17720.23 | O55: 17986.034 | P55: 18255.824 | Q55: 18529.662 | R55: 18807.606 | S55: 19089.721
A56: Insights ARR | B56: 2140937.7 | C56: 2297945.9 | D56: 2460079.7 | E56: 2645166.6 | F56: 2817573.1 | G56: 3005122.9 | H56: 3217105 | I56: 3442940.7 | J56: 3688688.3 | K56: 3958688.8 | L56: 4212834.6 | M56: 4479084.7 | N56: 4783126.1 | O56: 5100544.9 | P56: 5424411.1 | Q56: 5792160.1 | R56: 6128690.7 | S56: 6486548.1
A57: Total ARR | B57: =B48+B56 | C57: =C48+C56 | D57: =D48+D56 | E57: =E48+E56 | F57: =F48+F56 | G57: =G48+G56 | H57: =H48+H56 | I57: =I48+I56 | ... S57: =S48+S56
A58: Shaded yellow: values from the model. Shaded blue: Excel formulas.
A60: Plan upside: cloud hosting
A61: USD, monthly | B61: 2026-09 | C61: 2026-10 | D61: 2026-11 | E61: 2026-12 | F61: 2027-01 | G61: 2027-02 | H61: 2027-03 | I61: 2027-04 | J61: 2027-05 | K61: 2027-06 | L61: 2027-07 | M61: 2027-08 | N61: 2027-09 | O61: 2027-10 | P61: 2027-11 | Q61: 2027-12 | R61: 2028-01 | S61: 2028-02
A62: Platform compute units | B62: 109021.28 | C62: 111500.38 | D62: 113863.31 | E62: 116902.87 | F62: 119013.89 | G62: 121429.3 | H62: 124460.47 | I62: 127047.16 | J62: 129962.44 | K62: 133297.53 | L62: 135693.78 | M62: 138120.18 | N62: 141321.78 | O62: 144501.22 | P62: 147460.63 | Q62: 151191.56 | R62: 153708.65 | S62: 156406.32
A63: Insights compute units | B63: 288906.4 | C63: 305511.04 | D63: 322233.16 | E63: 341356.39 | F63: 358231.82 | G63: 376430.82 | H63: 397028.91 | I63: 418620.4 | J63: 441872.29 | K63: 467207.84 | L63: 489854.53 | M63: 513116.47 | N63: 539849.21 | O63: 567167.28 | P63: 594266.36 | Q63: 625177.1 | R63: 651724.69 | S63: 679585.44
A64: Total units | B64: =B62+B63 | C64: =C62+C63 | D64: =D62+D63 | E64: =E62+E63 | F64: =F62+F63 | G64: =G62+G63 | H64: =H62+H63 | I64: =I62+I63 | ... S64: =S62+S63
A65: Committed units | B65: 444819.65 | C65: 444819.65 | D65: 444819.65 | E65: 444819.65 | F65: 444819.65 | G65: 444819.65 | H65: 444819.65 | I65: 444819.65 | J65: 444819.65 | K65: 444819.65 | L65: 444819.65 | M65: 444819.65 | N65: 444819.65 | O65: 444819.65 | P65: 444819.65 | Q65: 444819.65 | R65: 444819.65 | S65: 444819.65
A66: On-demand unit price | B66: 0.41810063 | C66: 0.41684633 | D66: 0.41559579 | E66: 0.41434901 | F66: 0.41310596 | G66: 0.41186664 | H66: 0.41063104 | I66: 0.40939915 | J66: 0.40817095 | K66: 0.40694644 | L66: 0.4057256 | M66: 0.40450842 | N66: 0.4032949 | O66: 0.40208501 | P66: 0.40087876 | Q66: 0.39967612 | R66: 0.39847709 | S66: 0.39728166
A67: Commitment discount | B67: 0.25 | C67: 0.25 | D67: 0.25 | E67: 0.25 | F67: 0.25 | G67: 0.25 | H67: 0.25 | I67: 0.25 | J67: 0.25 | K67: 0.25 | L67: 0.25 | M67: 0.25 | N67: 0.25 | O67: 0.25 | P67: 0.25 | Q67: 0.25 | R67: 0.25 | S67: 0.25
A68: Committed cost | B68: =MIN(B64,B65)*B66*(1-B67) | C68: =MIN(C64,C65)*C66*(1-C67) | D68: =MIN(D64,D65)*D66*(1-D67) | E68: =MIN(E64,E65)*E66*(1-E67) | F68: =MIN(F64,F65)*F66*(1-F67) | G68: =MIN(G64,G65)*G66*(1-G67) | H68: =MIN(H64,H65)*H66*(1-H67) | I68: =MIN(I64,I65)*I66*(1-I67) | ... S68: =MIN(S64,S65)*S66*(1-S67)
A69: On-demand cost | B69: =MAX(B64-B65,0)*B66 | C69: =MAX(C64-C65,0)*C66 | D69: =MAX(D64-D65,0)*D66 | E69: =MAX(E64-E65,0)*E66 | F69: =MAX(F64-F65,0)*F66 | G69: =MAX(G64-G65,0)*G66 | H69: =MAX(H64-H65,0)*H66 | I69: =MAX(I64-I65,0)*I66 | ... S69: =MAX(S64-S65,0)*S66
A70: Fixed cloud cost | B70: 28000 | C70: 28000 | D70: 28000 | E70: 28000 | F70: 28000 | G70: 28000 | H70: 28000 | I70: 28000 | J70: 28000 | K70: 28000 | L70: 28000 | M70: 28000 | N70: 28000 | O70: 28000 | P70: 28000 | Q70: 28000 | R70: 28000 | S70: 28000
A71: Cloud hosting total | B71: =B68+B69+B70 | C71: =C68+C69+C70 | D71: =D68+D69+D70 | E71: =E68+E69+E70 | F71: =F68+F69+F70 | G71: =G68+G69+G70 | H71: =H68+H69+H70 | I71: =I68+I69+I70 | ... S71: =S68+S69+S70
A72: Shaded yellow: values from the model. Shaded blue: Excel formulas.
A74: Plan upside: cash
A75: USD, monthly | B75: 2026-09 | C75: 2026-10 | D75: 2026-11 | E75: 2026-12 | F75: 2027-01 | G75: 2027-02 | H75: 2027-03 | I75: 2027-04 | J75: 2027-05 | K75: 2027-06 | L75: 2027-07 | M75: 2027-08 | N75: 2027-09 | O75: 2027-10 | P75: 2027-11 | Q75: 2027-12 | R75: 2028-01 | S75: 2028-02
A76: Opening cash | B76: =24750279.18739851 | C76: =B83 | D76: =C83 | E76: =D83 | F76: =E83 | G76: =F83 | H76: =G83 | I76: =H83 | J76: =I83 | ... S76: =R83
A77: EBITDA | B77: -708601.33 | C77: -742614.85 | D77: -711578.18 | E77: -700562.94 | F77: -627788.49 | G77: -566253.11 | H77: -609128.98 | I77: -471900.73 | J77: -482350.57 | K77: -445019.51 | L77: -252622.47 | M77: -175319.81 | N77: -216684.96 | O77: -154006.29 | P77: -24540.921 | Q77: -52517.41 | R77: 325386.74 | S77: 393579.59
A78: Equipment capex | B78: 0 | C78: -10500 | D78: -14000 | E78: 0 | F78: -28000 | G78: -7000 | H78: -7000 | I78: -3500 | J78: -7000 | K78: 0 | L78: -3500 | M78: 0 | N78: 0 | O78: -3500 | P78: 0 | Q78: 0 | R78: -3500 | S78: 0
A79: Change in receivables | B79: -102092.69 | C79: -103182.47 | D79: -101687.75 | E79: -121148.02 | F79: -322204.55 | G79: -113883.62 | H79: -133167.28 | I79: -124444.59 | J79: -135939.71 | K79: -150365.82 | L79: -125496.87 | M79: -128424.16 | N79: -153425.74 | O79: -155382.55 | P79: -151463.1 | Q79: -177265.17 | R79: -472430.16 | S79: -159024.45
A80: Change in deferred revenue | B80: 149735.95 | C80: 151334.29 | D80: 149142.04 | E80: 177683.76 | F80: 472566.68 | G80: 167029.31 | H80: 195312.01 | I80: 182518.74 | J80: 199378.25 | K80: 220536.53 | L80: 184062.07 | M80: 188355.43 | N80: 225024.41 | O80: 227894.41 | P80: 222145.88 | Q80: 259988.91 | R80: 692897.58 | S80: 233235.86
A81: Financing | B81: 0 | C81: 0 | D81: 0 | E81: 0 | F81: 0 | G81: 0 | H81: 0 | I81: 0 | J81: 0 | K81: 0 | L81: 0 | M81: 0 | N81: 0 | O81: 0 | P81: 0 | Q81: 0 | R81: 0 | S81: 0
A82: Net cash flow | B82: =B77+B78+B79+B80+B81 | C82: =C77+C78+C79+C80+C81 | D82: =D77+D78+D79+D80+D81 | E82: =E77+E78+E79+E80+E81 | F82: =F77+F78+F79+F80+F81 | G82: =G77+G78+G79+G80+G81 | H82: =H77+H78+H79+H80+H81 | I82: =I77+I78+I79+I80+I81 | ... S82: =S77+S78+S79+S80+S81
A83: Closing cash | B83: =B76+B82 | C83: =C76+C82 | D83: =D76+D82 | E83: =E76+E82 | F83: =F76+F82 | G83: =G76+G82 | H83: =H76+H82 | I83: =I76+I82 | ... S83: =S76+S82
A84: Receivables | B84: 3133602.2 | C84: 3236784.7 | D84: 3338472.5 | E84: 3459620.5 | F84: 3781825 | G84: 3895708.6 | H84: 4028875.9 | I84: 4153320.5 | J84: 4289260.2 | K84: 4439626.1 | L84: 4565122.9 | M84: 4693547.1 | N84: 4846972.8 | O84: 5002355.4 | P84: 5153818.5 | Q84: 5331083.6 | R84: 5803513.8 | S84: 5962538.2
A85: Deferred revenue | B85: 4595950 | C85: 4747284.2 | D85: 4896426.3 | E85: 5074110 | F85: 5546676.7 | G85: 5713706 | H85: 5909018 | I85: 6091536.8 | J85: 6290915 | K85: 6511451.5 | L85: 6695513.6 | M85: 6883869 | N85: 7108893.5 | O85: 7336787.9 | P85: 7558933.7 | Q85: 7818922.7 | R85: 8511820.2 | S85: 8745056.1
A86: Net burn, trailing 3 months | B86: 660958.08 | C86: 682960.56 | D86: 681348.33 | E86: 675704.71 | F86: 609192.49 | G86: 556520.33 | H86: 526506.01 | I86: 497139.42 | J86: 465740.96 | K86: 406029.14 | L86: 332772.7 | M86: 229264.87 | N86: 152677.36 | O86: 115156.41 | P86: 61312.951 | Q86: 2882.0794 | R86: -206234.12 | S86: -346783.83
A87: Runway (months) | B87: 36.446065 | C87: 34.239691 | D87: 33.325442 | E87: 32.650663 | F87: 35.385828 | G87: 37.800368 | H87: 38.903048 | I87: 40.36164 | J87: 42.168184 | K87: 47.446352 | L87: 57.297502 | M87: 82.662713 | N87: 123.17851 | O87: 162.57518 | P87: 306.09711 | Q87: 6522.3474
A88: Shaded yellow: values from the model. Shaded blue: Excel formulas.

Sheet Plan downside
A1: Plan downside: P&L
A2: USD, monthly | B2: 2026-09 | C2: 2026-10 | D2: 2026-11 | E2: 2026-12 | F2: 2027-01 | G2: 2027-02 | H2: 2027-03 | I2: 2027-04 | J2: 2027-05 | K2: 2027-06 | L2: 2027-07 | M2: 2027-08 | N2: 2027-09 | O2: 2027-10 | P2: 2027-11 | Q2: 2027-12 | R2: 2028-01 | S2: 2028-02
A3: Platform revenue | B3: 1867082.8 | C3: 1879003.8 | D3: 1890143.4 | E3: 1906182.6 | F3: 1973434.4 | G3: 1985450.1 | H3: 2002062.5 | I3: 2015448.5 | J3: 2031311.6 | K3: 2050327.3 | L3: 2062468.1 | M3: 2074880.8 | N3: 2093065.3 | O3: 2111140.2 | P3: 2127644.4 | Q3: 2149895.7 | R3: 2228529.2 | S3: 2243697.1
A4: Insights revenue | B4: 168269.3 | C4: 170641.7 | D4: 172961.43 | E4: 175816.63 | F4: 178013.34 | G4: 180471.18 | H4: 183438.73 | I4: 187127.8 | J4: 191131.77 | K4: 195538.27 | L4: 199236.93 | M4: 203010.39 | N4: 207500.31 | O4: 212041.43 | P4: 216458.06 | Q4: 221637.77 | R4: 225789.54 | S4: 230166.82
A5: Revenue | B5: =B3+B4 | C5: =C3+C4 | D5: =D3+D4 | E5: =E3+E4 | F5: =F3+F4 | G5: =G3+G4 | H5: =H3+H4 | I5: =I3+I4 | ... S5: =S3+S4
A6: Cloud hosting | B6: 148101.8 | C6: 148928.75 | D6: 149704.24 | E6: 150840.21 | F6: 151500.6 | G6: 152328.84 | H6: 153491.39 | I6: 154937.65 | J6: 156572.26 | K6: 158448.87 | L6: 159826.71 | M6: 161231.45 | N6: 163080.01 | O6: 164932 | P6: 166674.63 | Q6: 169197.91 | R6: 171220.25 | S6: 173398.58
A7: Third-party software and data | B7: 61060.562 | C7: 61489.364 | D7: 61893.144 | E7: 62459.976 | F7: 64543.431 | G7: 64977.638 | H7: 65565.038 | I7: 66077.289 | J7: 66673.303 | K7: 67375.966 | L7: 67851.151 | M7: 68336.737 | N7: 69016.97 | O7: 69695.449 | P7: 70323.074 | Q7: 71146.005 | R7: 73629.561 | S7: 74215.918
A8: Payment processing | B8: 30530.281 | C8: 30744.682 | D8: 30946.572 | E8: 31229.988 | F8: 32271.716 | G8: 32488.819 | H8: 32782.519 | I8: 33038.645 | J8: 33336.651 | K8: 33687.983 | L8: 33925.575 | M8: 34168.368 | N8: 34508.485 | O8: 34847.724 | P8: 35161.537 | Q8: 35573.003 | R8: 36814.78 | S8: 37107.959
A9: Customer operations payroll | B9: 276901.48 | C9: 276901.48 | D9: 276901.48 | E9: 276901.48 | F9: 286593.03 | G9: 286593.03 | H9: 286593.03 | I9: 286593.03 | J9: 286593.03 | K9: 286593.03 | L9: 286593.03 | M9: 286593.03 | N9: 286593.03 | O9: 286593.03 | P9: 286593.03 | Q9: 286593.03 | R9: 296623.79 | S9: 296623.79
A10: Customer operations recruiting | B10: 0 | C10: 0 | D10: 0 | E10: 0 | F10: 0 | G10: 0 | H10: 0 | I10: 0 | J10: 0 | K10: 0 | L10: 0 | M10: 0 | N10: 0 | O10: 0 | P10: 0 | Q10: 0 | R10: 0 | S10: 0
A11: Cost of revenue | B11: =B6+B7+B8+B9+B10 | C11: =C6+C7+C8+C9+C10 | D11: =D6+D7+D8+D9+D10 | E11: =E6+E7+E8+E9+E10 | F11: =F6+F7+F8+F9+F10 | G11: =G6+G7+G8+G9+G10 | H11: =H6+H7+H8+H9+H10 | I11: =I6+I7+I8+I9+I10 | ... S11: =S6+S7+S8+S9+S10
A12: Gross profit | B12: =B5-B11 | C12: =C5-C11 | D12: =D5-D11 | E12: =E5-E11 | F12: =F5-F11 | G12: =G5-G11 | H12: =H5-H11 | I12: =I5-I11 | ... S12: =S5-S11
A13: Gross margin | B13: =IF(B5=0,0,B12/B5) | C13: =IF(C5=0,0,C12/C5) | D13: =IF(D5=0,0,D12/D5) | E13: =IF(E5=0,0,E12/E5) | F13: =IF(F5=0,0,F12/F5) | G13: =IF(G5=0,0,G12/G5) | H13: =IF(H5=0,0,H12/H5) | I13: =IF(I5=0,0,I12/I5) | ... S13: =IF(S5=0,0,S12/S5)
A14: R&D payroll | B14: 917162.28 | C14: 942862.78 | D14: 983087.54 | E14: 983087.54 | F14: 1054404 | G14: 1067983.4 | H14: 1087515.8 | I14: 1087515.8 | J14: 1108208.2 | K14: 1108208.2 | L14: 1108208.2 | M14: 1108208.2 | N14: 1108208.2 | O14: 1108208.2 | P14: 1108208.2 | Q14: 1108208.2 | R14: 1146995.4 | S14: 1146995.4
A15: R&D recruiting | B15: 0 | C15: 37500 | D15: 52500 | E15: 0 | F15: 46500 | G15: 15750 | H15: 28500 | I15: 0 | J15: 24000 | K15: 0 | L15: 0 | M15: 0 | N15: 0 | O15: 0 | P15: 0 | Q15: 0 | R15: 0 | S15: 0
A16: R&D tooling | B16: 31752 | C16: 32634 | D16: 34398 | E16: 34398 | F16: 35721 | G16: 36162 | H16: 37044 | I16: 37044 | J16: 37926 | K16: 37926 | L16: 37926 | M16: 37926 | N16: 37926 | O16: 37926 | P16: 37926 | Q16: 37926 | R16: 37926 | S16: 37926
A17: R&D contractors | B17: 60000 | C17: 60000 | D17: 60000 | E17: 60000 | F17: 60000 | G17: 60000 | H17: 60000 | I17: 60000 | J17: 60000 | K17: 60000 | L17: 60000 | M17: 60000 | N17: 60000 | O17: 60000 | P17: 60000 | Q17: 60000 | R17: 60000 | S17: 60000
A18: R&D total | B18: =B14+B15+B16+B17 | C18: =C14+C15+C16+C17 | D18: =D14+D15+D16+D17 | E18: =E14+E15+E16+E17 | F18: =F14+F15+F16+F17 | G18: =G14+G15+G16+G17 | H18: =H14+H15+H16+H17 | I18: =I14+I15+I16+I17 | ... S18: =S14+S15+S16+S17
A19: Sales and marketing payroll | B19: 313737.72 | C19: 324742.3 | D19: 324742.3 | E19: 324742.3 | F19: 371122.87 | G19: 383978.51 | H19: 383978.51 | I19: 394983.09 | J19: 394983.09 | K19: 394983.09 | L19: 394983.09 | M19: 394983.09 | N19: 394983.09 | O19: 394983.09 | P19: 394983.09 | Q19: 394983.09 | R19: 408807.5 | S19: 408807.5
A20: Sales and marketing recruiting | B20: 0 | C20: 16500 | D20: 0 | E20: 0 | F20: 52500 | G20: 18000 | H20: 0 | I20: 16500 | J20: 0 | K20: 0 | L20: 0 | M20: 0 | N20: 0 | O20: 0 | P20: 0 | Q20: 0 | R20: 0 | S20: 0
A21: Sales commission | B21: 42195.884 | C21: 42288.865 | D21: 41529.841 | E21: 47576.318 | F21: 40649.282 | G21: 43996.519 | H21: 49692.655 | I21: 46069.885 | J21: 49243.122 | K21: 53263.831 | L21: 45299.112 | M21: 45807.37 | N21: 52919.509 | O21: 53060.489 | P21: 51446.642 | Q21: 58590.501 | R21: 49186.297 | S21: 51602.517
A22: Marketing programmes | B22: 242550 | C22: 242550 | D22: 235125 | E22: 287100 | F22: 219037.5 | G22: 242962.5 | H22: 290400 | I22: 258637.5 | J22: 284625 | K22: 317625 | L22: 248943.75 | M22: 252450 | N22: 311850 | O22: 311850 | P22: 297000 | Q22: 356400 | R22: 267300 | S22: 282150
A23: Sales and marketing total | B23: =B19+B20+B21+B22 | C23: =C19+C20+C21+C22 | D23: =D19+D20+D21+D22 | E23: =E19+E20+E21+E22 | F23: =F19+F20+F21+F22 | G23: =G19+G20+G21+G22 | H23: =H19+H20+H21+H22 | I23: =I19+I20+I21+I22 | ... S23: =S19+S20+S21+S22
A24: G&A payroll | B24: 247823.66 | C24: 247823.66 | D24: 247823.66 | E24: 247823.66 | F24: 265749.67 | G24: 265749.67 | H24: 265749.67 | I24: 265749.67 | J24: 265749.67 | K24: 265749.67 | L24: 265749.67 | M24: 265749.67 | N24: 265749.67 | O24: 265749.67 | P24: 265749.67 | Q24: 265749.67 | R24: 275050.91 | S24: 275050.91
A25: G&A recruiting | B25: 0 | C25: 0 | D25: 0 | E25: 0 | F25: 13500 | G25: 0 | H25: 0 | I25: 0 | J25: 0 | K25: 0 | L25: 0 | M25: 0 | N25: 0 | O25: 0 | P25: 0 | Q25: 0 | R25: 0 | S25: 0
A26: Rent | B26: 68600 | C26: 69972 | D26: 72030 | E26: 72030 | F26: 76048 | G26: 77126 | H26: 78008 | I26: 78498 | J26: 79674 | K26: 79674 | L26: 79674 | M26: 79674 | N26: 79674 | O26: 79674 | P26: 79674 | Q26: 79674 | R26: 79674 | S26: 79674
A27: Software seats | B27: 25048.8 | C27: 25578 | D27: 26283.6 | E27: 26283.6 | F27: 27694.8 | G27: 28047.6 | H27: 28400.4 | I27: 28576.8 | J27: 28929.6 | K27: 28929.6 | L27: 28929.6 | M27: 28929.6 | N27: 28929.6 | O27: 28929.6 | P27: 28929.6 | Q27: 28929.6 | R27: 28929.6 | S27: 28929.6
A28: Fixed G&A | B28: 75000 | C28: 75000 | D28: 75000 | E28: 75000 | F28: 75000 | G28: 75000 | H28: 75000 | I28: 75000 | J28: 75000 | K28: 75000 | L28: 75000 | M28: 75000 | N28: 75000 | O28: 75000 | P28: 75000 | Q28: 75000 | R28: 75000 | S28: 75000
A29: G&A total | B29: =B24+B25+B26+B27+B28 | C29: =C24+C25+C26+C27+C28 | D29: =D24+D25+D26+D27+D28 | E29: =E24+E25+E26+E27+E28 | F29: =F24+F25+F26+F27+F28 | G29: =G24+G25+G26+G27+G28 | H29: =H24+H25+H26+H27+H28 | I29: =I24+I25+I26+I27+I28 | ... S29: =S24+S25+S26+S27+S28
A30: Operating expenses | B30: =B18+B23+B29 | C30: =C18+C23+C29 | D30: =D18+D23+D29 | E30: =E18+E23+E29 | F30: =F18+F23+F29 | G30: =G18+G23+G29 | H30: =H18+H23+H29 | I30: =I18+I23+I29 | ... S30: =S18+S23+S29
A31: EBITDA | B31: =B12-B30 | C31: =C12-C30 | D31: =D12-D30 | E31: =E12-E30 | F31: =F12-F30 | G31: =G12-G30 | H31: =H12-H30 | I31: =I12-I30 | ... S31: =S12-S30
A32: EBITDA margin | B32: =IF(B5=0,0,B31/B5) | C32: =IF(C5=0,0,C31/C5) | D32: =IF(D5=0,0,D31/D5) | E32: =IF(E5=0,0,E31/E5) | F32: =IF(F5=0,0,F31/F5) | G32: =IF(G5=0,0,G31/G5) | H32: =IF(H5=0,0,H31/H5) | I32: =IF(I5=0,0,I31/I5) | ... S32: =IF(S5=0,0,S31/S5)
A33: FTE total | B33: 139.16 | C33: 142.1 | D33: 146.02 | E33: 146.02 | F33: 153.86 | G33: 155.82 | H33: 157.78 | I33: 158.76 | J33: 160.72 | K33: 160.72 | L33: 160.72 | M33: 160.72 | N33: 160.72 | O33: 160.72 | P33: 160.72 | Q33: 160.72 | R33: 160.72 | S33: 160.72
A34: FTE customer operations | B34: 26.46 | C34: 26.46 | D34: 26.46 | E34: 26.46 | F34: 26.46 | G34: 26.46 | H34: 26.46 | I34: 26.46 | J34: 26.46 | K34: 26.46 | L34: 26.46 | M34: 26.46 | N34: 26.46 | O34: 26.46 | P34: 26.46 | Q34: 26.46 | R34: 26.46 | S34: 26.46
A35: FTE R&D | B35: 70.56 | C35: 72.52 | D35: 76.44 | E35: 76.44 | F35: 79.38 | G35: 80.36 | H35: 82.32 | I35: 82.32 | J35: 84.28 | K35: 84.28 | L35: 84.28 | M35: 84.28 | N35: 84.28 | O35: 84.28 | P35: 84.28 | Q35: 84.28 | R35: 84.28 | S35: 84.28
A36: FTE sales and marketing | B36: 27.44 | C36: 28.42 | D36: 28.42 | E36: 28.42 | F36: 32.34 | G36: 33.32 | H36: 33.32 | I36: 34.3 | J36: 34.3 | K36: 34.3 | L36: 34.3 | M36: 34.3 | N36: 34.3 | O36: 34.3 | P36: 34.3 | Q36: 34.3 | R36: 34.3 | S36: 34.3
A37: FTE G&A | B37: 14.7 | C37: 14.7 | D37: 14.7 | E37: 14.7 | F37: 15.68 | G37: 15.68 | H37: 15.68 | I37: 15.68 | J37: 15.68 | K37: 15.68 | L37: 15.68 | M37: 15.68 | N37: 15.68 | O37: 15.68 | P37: 15.68 | Q37: 15.68 | R37: 15.68 | S37: 15.68
A38: Total ARR (closing) | B38: 24424225 | C38: 24595746 | D38: 24757258 | E38: 24983990 | F38: 25817373 | G38: 25991055 | H38: 26226015 | I38: 26430916 | J38: 26669321 | K38: 26950386 | L38: 27140460 | M38: 27334695 | N38: 27606788 | O38: 27878180 | P38: 28129230 | Q38: 28458402 | R38: 29451824 | S38: 29686367
A39: Shaded yellow: values from the model. Shaded blue: Excel formulas.
A41: Plan downside: ARR roll-forward
A42: USD, monthly | B42: 2026-09 | C42: 2026-10 | D42: 2026-11 | E42: 2026-12 | F42: 2027-01 | G42: 2027-02 | H42: 2027-03 | I42: 2027-04 | J42: 2027-05 | K42: 2027-06 | L42: 2027-07 | M42: 2027-08 | N42: 2027-09 | O42: 2027-10 | P42: 2027-11 | Q42: 2027-12 | R42: 2028-01 | S42: 2028-02
A43: Opening Platform ARR | B43: 22261073 | C43: 22404993 | D43: 22548045 | E43: 22681720 | F43: 22874191 | G43: 23681212 | H43: 23825401 | I43: 24024750 | J43: 24185382 | K43: 24375740 | L43: 24603927 | M43: 24749617 | N43: 24898570 | O43: 25116784 | P43: 25333682 | Q43: 25531733 | R43: 25798749 | S43: 26742350
A44: New ARR | B44: 278138.7 | C44: 278138.7 | D44: 269624.25 | E44: 329225.4 | F44: 258711.56 | G44: 286970.08 | H44: 342999.89 | I44: 305484.28 | J44: 336178.87 | K44: 375156.13 | L44: 294034.71 | M44: 298176.04 | N44: 368335.11 | O44: 368335.11 | P44: 350795.34 | Q44: 420954.41 | R44: 325187.28 | S44: 343253.24
A45: Expansion ARR | B45: 143820.14 | C45: 144749.95 | D45: 145674.16 | E45: 146537.78 | F45: 147781.26 | G45: 152995.11 | H45: 153926.66 | I45: 155214.58 | J45: 156252.36 | K45: 157482.18 | L45: 158956.41 | M45: 159897.66 | N45: 160859.99 | O45: 162269.78 | P45: 163671.08 | Q45: 164950.61 | R45: 166675.69 | S45: 172771.93
A46: Price ARR | B46: 0 | C46: 0 | D46: 0 | E46: 0 | F46: 686225.72 | G46: 0 | H46: 0 | I46: 0 | J46: 0 | K46: 0 | L46: 0 | M46: 0 | N46: 0 | O46: 0 | P46: 0 | Q46: 0 | R46: 773962.46 | S46: 0
A47: Churned ARR | B47: -278039.01 | C47: -279836.56 | D47: -281623.27 | E47: -283292.86 | F47: -285696.8 | G47: -295776.44 | H47: -297577.34 | I47: -300067.2 | J47: -302073.47 | K47: -304451.03 | L47: -307301.07 | M47: -309120.73 | N47: -310981.14 | O47: -313706.61 | P47: -316415.65 | Q47: -318889.29 | R47: -322224.3 | S47: -334009.8
A48: Closing Platform ARR | B48: =B43+B44+B45+B46+B47 | C48: =C43+C44+C45+C46+C47 | D48: =D43+D44+D45+D46+D47 | E48: =E43+E44+E45+E46+E47 | F48: =F43+F44+F45+F46+F47 | G48: =G43+G44+G45+G46+G47 | H48: =H43+H44+H45+H46+H47 | I48: =I43+I44+I45+I46+I47 | ... S48: =S43+S44+S45+S46+S47
A49: Opening customers | B49: 532.62451 | C49: 533.32208 | D49: 534.01093 | E49: 534.46617 | F49: 536.49073 | G49: 536.42751 | H49: 537.09007 | I49: 539.18186 | J49: 540.28502 | K49: 542.1619 | L49: 545.01535 | M49: 545.7519 | N49: 546.5855 | O49: 549.20869 | P49: 551.79912 | Q49: 553.90719 | R49: 557.78894 | S49: 558.9222
A50: New logos | B50: 7.35 | C50: 7.35 | D50: 7.125 | E50: 8.7 | F50: 6.6375 | G50: 7.3625 | H50: 8.8 | I50: 7.8375 | J50: 8.625 | K50: 9.625 | L50: 7.54375 | M50: 7.65 | N50: 9.45 | O50: 9.45 | P50: 9 | Q50: 10.8 | R50: 8.1 | S50: 8.55
A51: Churned customers | B51: -6.6524373 | C51: -6.6611498 | D51: -6.6697535 | E51: -6.6754395 | F51: -6.7007261 | G51: -6.6999364 | H51: -6.7082117 | I51: -6.734338 | J51: -6.7481164 | K51: -6.7715585 | L51: -6.8071978 | M51: -6.8163973 | N51: -6.8268089 | O51: -6.8595723 | P51: -6.8919266 | Q51: -6.9182562 | R51: -6.9667389 | S51: -6.9808933
A52: Closing customers | B52: =B49+B50+B51 | C52: =C49+C50+C51 | D52: =D49+D50+D51 | E52: =E49+E50+E51 | F52: =F49+F50+F51 | G52: =G49+G50+G51 | H52: =H49+H50+H51 | I52: =I49+I50+I51 | ... S52: =S49+S50+S51
A53: Insights attach rate | B53: 0.258 | C53: 0.26 | D53: 0.262 | E53: 0.264 | F53: 0.266 | G53: 0.268 | H53: 0.27 | I53: 0.2735 | J53: 0.277 | K53: 0.2805 | L53: 0.284 | M53: 0.2875 | N53: 0.291 | O53: 0.2945 | P53: 0.298 | Q53: 0.3015 | R53: 0.305 | S53: 0.3085
A54: Insights customers | B54: 137.5971 | C54: 138.84284 | D54: 140.03014 | E54: 141.63355 | F54: 142.68972 | G54: 143.94014 | H54: 145.5791 | I54: 147.76795 | J54: 150.17885 | K54: 152.8768 | L54: 154.99354 | M54: 157.14333 | N54: 159.81973 | O54: 162.50484 | P54: 165.06434 | Q54: 168.17336 | R54: 170.47127 | S54: 172.91157
A55: Insights ARR per customer | B55: 14674.958 | C55: 14748.333 | D55: 14822.075 | E55: 14896.185 | F55: 14970.666 | G55: 15045.519 | H55: 15120.747 | I55: 15196.351 | J55: 15272.332 | K55: 15348.694 | L55: 15425.438 | M55: 15502.565 | N55: 15580.078 | O55: 15657.978 | P55: 15736.268 | Q55: 15814.949 | R55: 15894.024 | S55: 15973.494
A56: Insights ARR | B56: 2019231.6 | C56: 2047700.4 | D56: 2075537.1 | E56: 2109799.6 | F56: 2136160.1 | G56: 2165654.1 | H56: 2201264.8 | I56: 2245533.6 | J56: 2293581.3 | K56: 2346459.3 | L56: 2390843.2 | M56: 2436124.7 | N56: 2490003.8 | O56: 2544497.2 | P56: 2597496.7 | Q56: 2659653.2 | R56: 2709474.4 | S56: 2762001.9
A57: Total ARR | B57: =B48+B56 | C57: =C48+C56 | D57: =D48+D56 | E57: =E48+E56 | F57: =F48+F56 | G57: =G48+G56 | H57: =H48+H56 | I57: =I48+I56 | ... S57: =S48+S56
A58: Shaded yellow: values from the model. Shaded blue: Excel formulas.
A60: Plan downside: cloud hosting
A61: USD, monthly | B61: 2026-09 | C61: 2026-10 | D61: 2026-11 | E61: 2026-12 | F61: 2027-01 | G61: 2027-02 | H61: 2027-03 | I61: 2027-04 | J61: 2027-05 | K61: 2027-06 | L61: 2027-07 | M61: 2027-08 | N61: 2027-09 | O61: 2027-10 | P61: 2027-11 | Q61: 2027-12 | R61: 2028-01 | S61: 2028-02
A62: Platform compute units | B62: 106664.42 | C62: 106802.19 | D62: 106893.23 | E62: 107298.15 | F62: 107285.5 | G62: 107418.01 | H62: 107836.37 | I62: 108057 | J62: 108432.38 | K62: 109003.07 | L62: 109150.38 | M62: 109317.1 | N62: 109841.74 | O62: 110359.82 | P62: 110781.44 | Q62: 111557.79 | R62: 111784.44 | S62: 112098.26
A63: Insights compute units | B63: 275194.19 | C63: 277685.68 | D63: 280060.27 | E63: 283267.11 | F63: 285379.43 | G63: 287880.28 | H63: 291158.2 | I63: 295535.91 | J63: 300357.7 | K63: 305753.61 | L63: 309987.08 | M63: 314286.66 | N63: 319639.46 | O63: 325009.68 | P63: 330128.69 | Q63: 336346.73 | R63: 340942.54 | S63: 345823.13
A64: Total units | B64: =B62+B63 | C64: =C62+C63 | D64: =D62+D63 | E64: =E62+E63 | F64: =F62+F63 | G64: =G62+G63 | H64: =H62+H63 | I64: =I62+I63 | ... S64: =S62+S63
A65: Committed units | B65: 444819.65 | C65: 444819.65 | D65: 444819.65 | E65: 444819.65 | F65: 444819.65 | G65: 444819.65 | H65: 444819.65 | I65: 444819.65 | J65: 444819.65 | K65: 444819.65 | L65: 444819.65 | M65: 444819.65 | N65: 444819.65 | O65: 444819.65 | P65: 444819.65 | Q65: 444819.65 | R65: 444819.65 | S65: 444819.65
A66: On-demand unit price | B66: 0.41935871 | C66: 0.41935871 | D66: 0.41935871 | E66: 0.41935871 | F66: 0.41935871 | G66: 0.41935871 | H66: 0.41935871 | I66: 0.41935871 | J66: 0.41935871 | K66: 0.41935871 | L66: 0.41935871 | M66: 0.41935871 | N66: 0.41935871 | O66: 0.41935871 | P66: 0.41935871 | Q66: 0.41935871 | R66: 0.41935871 | S66: 0.41935871
A67: Commitment discount | B67: 0.25 | C67: 0.25 | D67: 0.25 | E67: 0.25 | F67: 0.25 | G67: 0.25 | H67: 0.25 | I67: 0.25 | J67: 0.25 | K67: 0.25 | L67: 0.25 | M67: 0.25 | N67: 0.25 | O67: 0.25 | P67: 0.25 | Q67: 0.25 | R67: 0.25 | S67: 0.25
A68: Committed cost | B68: =MIN(B64,B65)*B66*(1-B67) | C68: =MIN(C64,C65)*C66*(1-C67) | D68: =MIN(D64,D65)*D66*(1-D67) | E68: =MIN(E64,E65)*E66*(1-E67) | F68: =MIN(F64,F65)*F66*(1-F67) | G68: =MIN(G64,G65)*G66*(1-G67) | H68: =MIN(H64,H65)*H66*(1-H67) | I68: =MIN(I64,I65)*I66*(1-I67) | ... S68: =MIN(S64,S65)*S66*(1-S67)
A69: On-demand cost | B69: =MAX(B64-B65,0)*B66 | C69: =MAX(C64-C65,0)*C66 | D69: =MAX(D64-D65,0)*D66 | E69: =MAX(E64-E65,0)*E66 | F69: =MAX(F64-F65,0)*F66 | G69: =MAX(G64-G65,0)*G66 | H69: =MAX(H64-H65,0)*H66 | I69: =MAX(I64-I65,0)*I66 | ... S69: =MAX(S64-S65,0)*S66
A70: Fixed cloud cost | B70: 28000 | C70: 28000 | D70: 28000 | E70: 28000 | F70: 28000 | G70: 28000 | H70: 28000 | I70: 28000 | J70: 28000 | K70: 28000 | L70: 28000 | M70: 28000 | N70: 28000 | O70: 28000 | P70: 28000 | Q70: 28000 | R70: 28000 | S70: 28000
A71: Cloud hosting total | B71: =B68+B69+B70 | C71: =C68+C69+C70 | D71: =D68+D69+D70 | E71: =E68+E69+E70 | F71: =F68+F69+F70 | G71: =G68+G69+G70 | H71: =H68+H69+H70 | I71: =I68+I69+I70 | ... S71: =S68+S69+S70
A72: Shaded yellow: values from the model. Shaded blue: Excel formulas.
A74: Plan downside: cash
A75: USD, monthly | B75: 2026-09 | C75: 2026-10 | D75: 2026-11 | E75: 2026-12 | F75: 2027-01 | G75: 2027-02 | H75: 2027-03 | I75: 2027-04 | J75: 2027-05 | K75: 2027-06 | L75: 2027-07 | M75: 2027-08 | N75: 2027-09 | O75: 2027-10 | P75: 2027-11 | Q75: 2027-12 | R75: 2028-01 | S75: 2028-02
A76: Opening cash | B76: =24750279.18739851 | C76: =B83 | D76: =C83 | E76: =D83 | F76: =E83 | G76: =F83 | H76: =G83 | I76: =H83 | J76: =I83 | ... S76: =R83
A77: EBITDA | B77: -505112.41 | C77: -585870.42 | D77: -608860.59 | E77: -597473.88 | F77: -721388.22 | G77: -685223.25 | H77: -737219.74 | I77: -686645.05 | J77: -729070.47 | K77: -721599.67 | L77: -631204.83 | M77: -621166.25 | N77: -667872.88 | O77: -648267.58 | P77: -613566.95 | Q77: -656437.47 | R77: -552839.43 | S77: -553618.28
A78: Equipment capex | B78: 0 | C78: -10500 | D78: -14000 | E78: 0 | F78: -28000 | G78: -7000 | H78: -7000 | I78: -3500 | J78: -7000 | K78: 0 | L78: 0 | M78: 0 | N78: 0 | O78: 0 | P78: 0 | Q78: 0 | R78: 0 | S78: 0
A79: Change in receivables | B79: -21518.55 | C79: -21440.115 | D79: -20188.98 | E79: -28341.599 | F79: -104172.78 | G79: -21710.35 | H79: -29369.977 | I79: -25612.566 | J79: -29800.675 | K79: -35133.163 | L79: -23759.238 | M79: -24279.311 | N79: -34011.633 | O79: -33923.964 | P79: -31381.284 | Q79: -41146.527 | R79: -124177.8 | S79: -29317.852
A80: Change in deferred revenue | B80: 31560.54 | C80: 31445.502 | D80: 29610.504 | E80: 41567.679 | F80: 152786.74 | G80: 31841.847 | H80: 43075.967 | I80: 37565.097 | J80: 43707.656 | K80: 51528.639 | L80: 34846.882 | M80: 35609.656 | N80: 49883.729 | O80: 49755.147 | P80: 46025.883 | Q80: 60348.239 | R80: 182127.44 | S80: 42999.517
A81: Financing | B81: 0 | C81: 0 | D81: 0 | E81: 0 | F81: 0 | G81: 0 | H81: 0 | I81: 0 | J81: 0 | K81: 0 | L81: 0 | M81: 0 | N81: 0 | O81: 0 | P81: 0 | Q81: 0 | R81: 0 | S81: 0
A82: Net cash flow | B82: =B77+B78+B79+B80+B81 | C82: =C77+C78+C79+C80+C81 | D82: =D77+D78+D79+D80+D81 | E82: =E77+E78+E79+E80+E81 | F82: =F77+F78+F79+F80+F81 | G82: =G77+G78+G79+G80+G81 | H82: =H77+H78+H79+H80+H81 | I82: =I77+I78+I79+I80+I81 | ... S82: =S77+S78+S79+S80+S81
A83: Closing cash | B83: =B76+B82 | C83: =C76+C82 | D83: =D76+D82 | E83: =E76+E82 | F83: =F76+F82 | G83: =G76+G82 | H83: =H76+H82 | I83: =I76+I82 | ... S83: =S76+S82
A84: Receivables | B84: 3053028.1 | C84: 3074468.2 | D84: 3094657.2 | E84: 3122998.8 | F84: 3227171.6 | G84: 3248881.9 | H84: 3278251.9 | I84: 3303864.5 | J84: 3333665.1 | K84: 3368798.3 | L84: 3392557.5 | M84: 3416836.8 | N84: 3450848.5 | O84: 3484772.4 | P84: 3516153.7 | Q84: 3557300.3 | R84: 3681478 | S84: 3710795.9
A85: Deferred revenue | B85: 4477774.5 | C85: 4509220 | D85: 4538830.5 | E85: 4580398.2 | F85: 4733185 | G85: 4765026.8 | H85: 4808102.8 | I85: 4845667.9 | J85: 4889375.5 | K85: 4940904.2 | L85: 4975751 | M85: 5011360.7 | N85: 5061244.4 | O85: 5110999.6 | P85: 5157025.5 | Q85: 5217373.7 | R85: 5399501.1 | S85: 5442500.7
A86: Net burn, trailing 3 months | B86: 495070.42 | C86: 540717.73 | D86: 564958.18 | E86: 594683.97 | F86: 632820.38 | G86: 655704.61 | H86: 704459.92 | I86: 696932.67 | J86: 710289.92 | K86: 701853.4 | L86: 682494.96 | M86: 645052.43 | N86: 627317.96 | O86: 631424.36 | P86: 627786.51 | Q86: 622864.84 | R86: 577015.97 | S86: 557354.06
A87: Runway (months) | B87: 48.993451 | C87: 43.773012 | D87: 40.809047 | E87: 37.78672 | F87: 34.402152 | G87: 32.161267 | H87: 28.898418 | I87: 28.237426 | J87: 26.689695 | K87: 26.00574 | L87: 25.834769 | M87: 26.388962 | N87: 26.095639 | O87: 24.924326 | P87: 24.114733 | Q87: 23.282208 | R87: 24.274508 | S87: 24.162096
A88: Shaded yellow: values from the model. Shaded blue: Excel formulas.

Sheet Workforce
A1: Recommended option (phased_commit), base scenario. FTE is net of the vacancy allowance.
A3: month | B3: function | C3: location | D3: fte | E3: people_cost | F3: recruiting | G3: capex
A4: 2026-09 | B4: Customer Operations | C4: Austin | D4: 9.8 | E4: 104066.93 | F4: 0 | G4: 0
A5: 2026-09 | B5: Customer Operations | C5: Montreal | D5: 15.68 | E5: 156735.72 | F5: 0 | G5: 0
A6: 2026-09 | B6: Customer Operations | C6: Paris | D6: 0.98 | E6: 16098.826 | F6: 0 | G6: 0
A7: 2026-09 | B7: G&A | C7: Austin | D7: 0.98 | E7: 36328.649 | F7: 0 | G7: 0
A8: 2026-09 | B8: G&A | C8: Montreal | D8: 13.72 | E8: 211495.02 | F8: 0 | G8: 0
A9: 2026-09 | B9: R&D | C9: Montreal | D9: 44.1 | E9: 564219.96 | F9: 0 | G9: 0
A10: 2026-09 | B10: R&D | C10: Paris | D10: 26.46 | E10: 352942.32 | F10: 0 | G10: 0
A11: 2026-09 | B11: S&M | C11: Austin | D11: 26.46 | E11: 302953.43 | F11: 0 | G11: 0
A12: 2026-09 | B12: S&M | C12: Montreal | D12: 0.98 | E12: 10784.287 | F12: 0 | G12: 0
A13: 2026-10 | B13: Customer Operations | C13: Austin | D13: 9.8 | E13: 104066.93 | F13: 0 | G13: 0
A14: 2026-10 | B14: Customer Operations | C14: Montreal | D14: 15.68 | E14: 156735.72 | F14: 0 | G14: 0
A15: 2026-10 | B15: Customer Operations | C15: Paris | D15: 0.98 | E15: 16098.826 | F15: 0 | G15: 0
... A165: 2028-02 | B165: S&M | C165: Montreal | D165: 0.98 | E165: 11552.397 | F165: 0 | G165: 0

Sheet Checks
A1: Every formula subtotal in the workbook, recomputed against the model value. Difference must be 0.
A3: Sheet | B3: Line | C3: Months checked | D3: Sum of formula cells | E3: Sum of model values | F3: Difference
A4: Actuals | B4: Revenue | C4: 24 | D4: =SUM('Actuals'!B5:Y5) | E4: 35939752 | F4: =ROUND(D4-E4,4)
A5: Actuals | B5: Cost of revenue | C5: 24 | D5: =SUM('Actuals'!B11:Y11) | E5: 10930987 | F5: =ROUND(D5-E5,4)
A6: Actuals | B6: Gross profit | C6: 24 | D6: =SUM('Actuals'!B12:Y12) | E6: 25008764 | F6: =ROUND(D6-E6,4)
A7: Actuals | B7: Gross margin | C7: 24 | D7: =SUM('Actuals'!B13:Y13) | E7: 16.601264 | F7: =ROUND(D7-E7,4)
A8: Actuals | B8: R&D total | C8: 24 | D8: =SUM('Actuals'!B18:Y18) | E8: 21703053 | F8: =ROUND(D8-E8,4)
A9: Actuals | B9: Sales and marketing total | C9: 24 | D9: =SUM('Actuals'!B23:Y23) | E9: 15692025 | F9: =ROUND(D9-E9,4)
A10: Actuals | B10: G&A total | C10: 24 | D10: =SUM('Actuals'!B29:Y29) | E10: 9366688.7 | F10: =ROUND(D10-E10,4)
A11: Actuals | B11: Operating expenses | C11: 24 | D11: =SUM('Actuals'!B30:Y30) | E11: 46761766 | F11: =ROUND(D11-E11,4)
A12: Actuals | B12: EBITDA | C12: 24 | D12: =SUM('Actuals'!B31:Y31) | E12: -21753002 | F12: =ROUND(D12-E12,4)
A13: Actuals | B13: EBITDA margin | C13: 24 | D13: =SUM('Actuals'!B32:Y32) | E13: -15.246695 | F13: =ROUND(D13-E13,4)
A14: Actuals | B14: Closing Platform ARR | C14: 24 | D14: =SUM('Actuals'!B48:Y48) | E14: 4.0261574e+08 | F14: =ROUND(D14-E14,4)
A15: Actuals | B15: Closing customers | C15: 24 | D15: =SUM('Actuals'!B52:Y52) | E15: 10891.107 | F15: =ROUND(D15-E15,4)
A16: Actuals | B16: Total ARR | C16: 24 | D16: =SUM('Actuals'!B57:Y57) | E16: 4.3127702e+08 | F16: =ROUND(D16-E16,4)
A17: Actuals | B17: Total units | C17: 24 | D17: =SUM('Actuals'!B64:Y64) | E17: 5764464.9 | F17: =ROUND(D17-E17,4)
A18: Actuals | B18: Committed cost | C18: 24 | D18: =SUM('Actuals'!B68:Y68) | E18: 0 | F18: =ROUND(D18-E18,4)
A19: Actuals | B19: On-demand cost | C19: 24 | D19: =SUM('Actuals'!B69:Y69) | E19: 2463964.8 | F19: =ROUND(D19-E19,4)
A20: Actuals | B20: Cloud hosting total | C20: 24 | D20: =SUM('Actuals'!B71:Y71) | E20: 3087964.8 | F20: =ROUND(D20-E20,4)
A21: Actuals | B21: Opening cash | C21: 24 | D21: =SUM('Actuals'!B76:Y76) | E21: 3.8047832e+08 | F21: =ROUND(D21-E21,4)
A22: Actuals | B22: Net cash flow | C22: 24 | D22: =SUM('Actuals'!B82:Y82) | E22: 3750279.2 | F22: =ROUND(D22-E22,4)
A23: Actuals | B23: Closing cash | C23: 24 | D23: =SUM('Actuals'!B83:Y83) | E23: 3.8422859e+08 | F23: =ROUND(D23-E23,4)
A24: Budget FY2026 | B24: Revenue | C24: 12 | D24: =SUM('Budget FY2026'!B5:M5) | E24: 24799588 | F24: =ROUND(D24-E24,4)
A25: Budget FY2026 | B25: Cost of revenue | C25: 12 | D25: =SUM('Budget FY2026'!B11:M11) | E25: 6530432.5 | F25: =ROUND(D25-E25,4)
A26: Budget FY2026 | B26: Gross profit | C26: 12 | D26: =SUM('Budget FY2026'!B12:M12) | E26: 18269155 | F26: =ROUND(D26-E26,4)
A27: Budget FY2026 | B27: Gross margin | C27: 12 | D27: =SUM('Budget FY2026'!B13:M13) | E27: 8.8234482 | F27: =ROUND(D27-E27,4)
A28: Budget FY2026 | B28: R&D total | C28: 12 | D28: =SUM('Budget FY2026'!B18:M18) | E28: 12547616 | F28: =ROUND(D28-E28,4)
A29: Budget FY2026 | B29: Sales and marketing total | C29: 12 | D29: =SUM('Budget FY2026'!B23:M23) | E29: 10612739 | F29: =ROUND(D29-E29,4)
A30: Budget FY2026 | B30: G&A total | C30: 12 | D30: =SUM('Budget FY2026'!B29:M29) | E30: 5058134.6 | F30: =ROUND(D30-E30,4)
A31: Budget FY2026 | B31: Operating expenses | C31: 12 | D31: =SUM('Budget FY2026'!B30:M30) | E31: 28218489 | F31: =ROUND(D31-E31,4)
A32: Budget FY2026 | B32: EBITDA | C32: 12 | D32: =SUM('Budget FY2026'!B31:M31) | E32: -9949333.7 | F32: =ROUND(D32-E32,4)
A33: Budget FY2026 | B33: EBITDA margin | C33: 12 | D33: =SUM('Budget FY2026'!B32:M32) | E33: -4.9519198 | F33: =ROUND(D33-E33,4)
A34: Budget FY2026 | B34: Closing Platform ARR | C34: 12 | D34: =SUM('Budget FY2026'!B48:M48) | E34: 2.7302189e+08 | F34: =ROUND(D34-E34,4)
A35: Budget FY2026 | B35: Closing customers | C35: 12 | D35: =SUM('Budget FY2026'!B52:M52) | E35: 6621.5808 | F35: =ROUND(D35-E35,4)
A36: Budget FY2026 | B36: Total ARR | C36: 12 | D36: =SUM('Budget FY2026'!B57:M57) | E36: 2.9759506e+08 | F36: =ROUND(D36-E36,4)
A37: Budget FY2026 | B37: Total units | C37: 12 | D37: =SUM('Budget FY2026'!B64:M64) | E37: 3871773.7 | F37: =ROUND(D37-E37,4)
A38: Budget FY2026 | B38: Committed cost | C38: 12 | D38: =SUM('Budget FY2026'!B68:M68) | E38: 0 | F38: =ROUND(D38-E38,4)
A39: Budget FY2026 | B39: On-demand cost | C39: 12 | D39: =SUM('Budget FY2026'!B69:M69) | E39: 1627184.5 | F39: =ROUND(D39-E39,4)
A40: Budget FY2026 | B40: Cloud hosting total | C40: 12 | D40: =SUM('Budget FY2026'!B71:M71) | E40: 1963184.5 | F40: =ROUND(D40-E40,4)
A41: Budget FY2026 | B41: Opening cash | C41: 12 | D41: =SUM('Budget FY2026'!B76:M76) | E41: 18383977 | F41: =ROUND(D41-E41,4)
A42: Budget FY2026 | B42: Net cash flow | C42: 12 | D42: =SUM('Budget FY2026'!B82:M82) | E42: -9446932.2 | F42: =ROUND(D42-E42,4)
A43: Budget FY2026 | B43: Closing cash | C43: 12 | D43: =SUM('Budget FY2026'!B83:M83) | E43: 8937044.8 | F43: =ROUND(D43-E43,4)
A44: Plan base | B44: Revenue | C44: 18 | D44: =SUM('Plan base'!B5:S5) | E44: 47952580 | F44: =ROUND(D44-E44,4)
A45: Plan base | B45: Cost of revenue | C45: 18 | D45: =SUM('Plan base'!B11:S11) | E45: 10904522 | F45: =ROUND(D45-E45,4)
A46: Plan base | B46: Gross profit | C46: 18 | D46: =SUM('Plan base'!B12:S12) | E46: 37048058 | F46: =ROUND(D46-E46,4)
A47: Plan base | B47: Gross margin | C47: 18 | D47: =SUM('Plan base'!B13:S13) | E47: 13.878418 | F47: =ROUND(D47-E47,4)
A48: Plan base | B48: R&D total | C48: 18 | D48: =SUM('Plan base'!B18:S18) | E48: 21226438 | F48: =ROUND(D48-E48,4)
A49: Plan base | B49: Sales and marketing total | C49: 18 | D49: =SUM('Plan base'!B23:S23) | E49: 16508911 | F49: =ROUND(D49-E49,4)
A50: Plan base | B50: G&A total | C50: 18 | D50: =SUM('Plan base'!B29:S29) | E50: 7990153.3 | F50: =ROUND(D50-E50,4)
A51: Plan base | B51: Operating expenses | C51: 18 | D51: =SUM('Plan base'!B30:S30) | E51: 45725502 | F51: =ROUND(D51-E51,4)
A52: Plan base | B52: EBITDA | C52: 18 | D52: =SUM('Plan base'!B31:S31) | E52: -8677444.5 | F52: =ROUND(D52-E52,4)
A53: Plan base | B53: EBITDA margin | C53: 18 | D53: =SUM('Plan base'!B32:S32) | E53: -3.5169722 | F53: =ROUND(D53-E53,4)
A54: Plan base | B54: Closing Platform ARR | C54: 18 | D54: =SUM('Plan base'!B48:S48) | E54: 5.1711159e+08 | F54: =ROUND(D54-E54,4)
A55: Plan base | B55: Closing customers | C55: 18 | D55: =SUM('Plan base'!B52:S52) | E55: 11173.732 | F55: =ROUND(D55-E55,4)
A56: Plan base | B56: Total ARR | C56: 18 | D56: =SUM('Plan base'!B57:S57) | E56: 5.7543096e+08 | F56: =ROUND(D56-E56,4)
A57: Plan base | B57: Total units | C57: 18 | D57: =SUM('Plan base'!B64:S64) | E57: 9419710.3 | F57: =ROUND(D57-E57,4)
A58: Plan base | B58: Committed cost | C58: 18 | D58: =SUM('Plan base'!B68:S68) | E58: 2428932 | F58: =ROUND(D58-E58,4)
A59: Plan base | B59: On-demand cost | C59: 18 | D59: =SUM('Plan base'!B69:S69) | E59: 630653.9 | F59: =ROUND(D59-E59,4)
A60: Plan base | B60: Cloud hosting total | C60: 18 | D60: =SUM('Plan base'!B71:S71) | E60: 3563585.9 | F60: =ROUND(D60-E60,4)
A61: Plan base | B61: Opening cash | C61: 18 | D61: =SUM('Plan base'!B76:S76) | E61: 3.5941791e+08 | F61: =ROUND(D61-E61,4)
A62: Plan base | B62: Net cash flow | C62: 18 | D62: =SUM('Plan base'!B82:S82) | E62: -7810224.1 | F62: =ROUND(D62-E62,4)
A63: Plan base | B63: Closing cash | C63: 18 | D63: =SUM('Plan base'!B83:S83) | E63: 3.5160769e+08 | F63: =ROUND(D63-E63,4)
A64: Plan upside | B64: Revenue | C64: 18 | D64: =SUM('Plan upside'!B5:S5) | E64: 52744032 | F64: =ROUND(D64-E64,4)
A65: Plan upside | B65: Cost of revenue | C65: 18 | D65: =SUM('Plan upside'!B11:S11) | E65: 11764377 | F65: =ROUND(D65-E65,4)
A66: Plan upside | B66: Gross profit | C66: 18 | D66: =SUM('Plan upside'!B12:S12) | E66: 40979655 | F66: =ROUND(D66-E66,4)
A67: Plan upside | B67: Gross margin | C67: 18 | D67: =SUM('Plan upside'!B13:S13) | E67: 13.947152 | F67: =ROUND(D67-E67,4)
A68: Plan upside | B68: R&D total | C68: 18 | D68: =SUM('Plan upside'!B18:S18) | E68: 21226438 | F68: =ROUND(D68-E68,4)
A69: Plan upside | B69: Sales and marketing total | C69: 18 | D69: =SUM('Plan upside'!B23:S23) | E69: 17977591 | F69: =ROUND(D69-E69,4)
A70: Plan upside | B70: G&A total | C70: 18 | D70: =SUM('Plan upside'!B29:S29) | E70: 7998150.1 | F70: =ROUND(D70-E70,4)
A71: Plan upside | B71: Operating expenses | C71: 18 | D71: =SUM('Plan upside'!B30:S30) | E71: 47202179 | F71: =ROUND(D71-E71,4)
A72: Plan upside | B72: EBITDA | C72: 18 | D72: =SUM('Plan upside'!B31:S31) | E72: -6222524.2 | F72: =ROUND(D72-E72,4)
A73: Plan upside | B73: EBITDA margin | C73: 18 | D73: =SUM('Plan upside'!B32:S32) | E73: -2.5811705 | F73: =ROUND(D73-E73,4)
A74: Plan upside | B74: Closing Platform ARR | C74: 18 | D74: =SUM('Plan upside'!B48:S48) | E74: 5.6084674e+08 | F74: =ROUND(D74-E74,4)
A75: Plan upside | B75: Closing customers | C75: 18 | D75: =SUM('Plan upside'!B52:S52) | E75: 11874.514 | F75: =ROUND(D75-E75,4)
A76: Plan upside | B76: Total ARR | C76: 18 | D76: =SUM('Plan upside'!B57:S57) | E76: 6.3292839e+08 | F76: =ROUND(D76-E76,4)
A77: Plan upside | B77: Total units | C77: 18 | D77: =SUM('Plan upside'!B64:S64) | E77: 10753043 | F77: =ROUND(D77-E77,4)
A78: Plan upside | B78: Committed cost | C78: 18 | D78: =SUM('Plan upside'!B68:S68) | E78: 2421594.2 | F78: =ROUND(D78-E78,4)
A79: Plan upside | B79: On-demand cost | C79: 18 | D79: =SUM('Plan upside'!B69:S69) | E79: 1138856 | F79: =ROUND(D79-E79,4)
A80: Plan upside | B80: Cloud hosting total | C80: 18 | D80: =SUM('Plan upside'!B71:S71) | E80: 4064450.2 | F80: =ROUND(D80-E80,4)
A81: Plan upside | B81: Opening cash | C81: 18 | D81: =SUM('Plan upside'!B76:S76) | E81: 3.7149072e+08 | F81: =ROUND(D81-E81,4)
A82: Plan upside | B82: Net cash flow | C82: 18 | D82: =SUM('Plan upside'!B82:S82) | E82: -4942210.8 | F82: =ROUND(D82-E82,4)
A83: Plan upside | B83: Closing cash | C83: 18 | D83: =SUM('Plan upside'!B83:S83) | E83: 3.6654851e+08 | F83: =ROUND(D83-E83,4)
A84: Plan downside | B84: Revenue | C84: 18 | D84: =SUM('Plan downside'!B5:S5) | E84: 40211019 | F84: =ROUND(D84-E84,4)
A85: Plan downside | B85: Cost of revenue | C85: 18 | D85: =SUM('Plan downside'!B11:S11) | E85: 9803881.9 | F85: =ROUND(D85-E85,4)
A86: Plan downside | B86: Gross profit | C86: 18 | D86: =SUM('Plan downside'!B12:S12) | E86: 30407137 | F86: =ROUND(D86-E86,4)
A87: Plan downside | B87: Gross margin | C87: 18 | D87: =SUM('Plan downside'!B13:S13) | E87: 13.605567 | F87: =ROUND(D87-E87,4)
A88: Plan downside | B88: R&D total | C88: 18 | D88: =SUM('Plan downside'!B18:S18) | E88: 21226438 | F88: =ROUND(D88-E88,4)
A89: Plan downside | B89: Sales and marketing total | C89: 18 | D89: =SUM('Plan downside'!B23:S23) | E89: 12715982 | F89: =ROUND(D89-E89,4)
A90: Plan downside | B90: G&A total | C90: 18 | D90: =SUM('Plan downside'!B29:S29) | E90: 7988154.1 | F90: =ROUND(D90-E90,4)
A91: Plan downside | B91: Operating expenses | C91: 18 | D91: =SUM('Plan downside'!B30:S30) | E91: 41930575 | F91: =ROUND(D91-E91,4)
A92: Plan downside | B92: EBITDA | C92: 18 | D92: =SUM('Plan downside'!B31:S31) | E92: -11523437 | F92: =ROUND(D92-E92,4)
A93: Plan downside | B93: EBITDA margin | C93: 18 | D93: =SUM('Plan downside'!B32:S32) | E93: -5.1749031 | F93: =ROUND(D93-E93,4)
A94: Plan downside | B94: Closing Platform ARR | C94: 18 | D94: =SUM('Plan downside'!B48:S48) | E94: 4.4030121e+08 | F94: =ROUND(D94-E94,4)
A95: Plan downside | B95: Closing customers | C95: 18 | D95: =SUM('Plan downside'!B52:S52) | E95: 9802.9065 | F95: =ROUND(D95-E95,4)
A96: Plan downside | B96: Total ARR | C96: 18 | D96: =SUM('Plan downside'!B57:S57) | E96: 4.8253223e+08 | F96: =ROUND(D96-E96,4)
A97: Plan downside | B97: Total units | C97: 18 | D97: =SUM('Plan downside'!B64:S64) | E97: 7465017.6 | F97: =ROUND(D97-E97,4)
A98: Plan downside | B98: Committed cost | C98: 18 | D98: =SUM('Plan downside'!B68:S68) | E98: 2340312.1 | F98: =ROUND(D98-E98,4)
A99: Plan downside | B99: On-demand cost | C99: 18 | D99: =SUM('Plan downside'!B69:S69) | E99: 10103.999 | F99: =ROUND(D99-E99,4)
A100: Plan downside | B100: Cloud hosting total | C100: 18 | D100: =SUM('Plan downside'!B71:S71) | E100: 2854416.1 | F100: =ROUND(D100-E100,4)
A101: Plan downside | B101: Opening cash | C101: 18 | D101: =SUM('Plan downside'!B76:S76) | E101: 3.4871637e+08 | F101: =ROUND(D101-E101,4)
...
